Workbook

Sheet Summary
B2: FlexCapPro — Regression Test Suite Summary
B3: QA regression coverage across Register, Login, Supplier, Buyer, Email & In-App Notification modules — live view, updates automatically as Status is filled in
B5: TOTAL TEST CASES | G5: POSITIVE TEST CASES | L5: NEGATIVE TEST CASES | Q5: OTHER (DEFECT LOGS)
B6: =COUNTA(Register!D2:D41)+COUNTA(Login!D2:D34)+COUNTA('Forgot Password'!D2:D34)+COUNTA('Supplier Onboarding'!D2:D256)+COUNTA('Buyer Onboarding'!D2:D223)+COUNTA('Supplier Dashboard page'!D2:D109)+COUNTA('Supplier Buyer page'!D2:D115)+COUNTA('Supplier Reports Page'!D2:D75)+COUNTA('Supplier Invoices Page'!D2:D132)+COUNTA('Supplier Admin page '!D2:D84)+COUNTA('Supplier Help and Support Page'!D2:D55)+COUNTA('Supplier Entity'!D2:D305)+COUNTA('Buyer Dashboard'!D2:D83)+COUNTA('Add Supplier Page'!D2:D43)+COUNTA('Buyer Report Page'!D2:D75)+COUNTA('Buyer Help and Support Page'!D2:D55)+COUNTA('Buyer Entity Page'!D2:D258)+COUNTA('Buyer Add Card Page '!D2:D38)+COUNTA('Buyer Payable Page'!D2:D85)+COUNTA('Email Notification'!D2:D82)+COUNTA('In_App Notification'!D2:D65) -> 2201 | G6: =COUNTIF(Register!D2:D41,"*Positive*")+COUNTIF(Login!D2:D34,"*Positive*")+COUNTIF('Forgot Password'!D2:D34,"*Positive*")+COUNTIF('Supplier Onboarding'!D2:D256,"*Positive*")+COUNTIF('Buyer Onboarding'!D2:D223,"*Positive*")+COUNTIF('Supplier Dashboard page'!D2:D109,"*Positive*")+COUNTIF('Supplier Buyer page'!D2:D115,"*Positive*")+COUNTIF('Supplier Reports Page'!D2:D75,"*Positive*")+COUNTIF('Supplier Invoices Page'!D2:D132,"*Positive*")+COUNTIF('Supplier Admin page '!D2:D84,"*Positive*")+COUNTIF('Supplier Help and Support Page'!D2:D55,"*Positive*")+COUNTIF('Supplier Entity'!D2:D305,"*Positive*")+COUNTIF('Buyer Dashboard'!D2:D83,"*Positive*")+COUNTIF('Add Supplier Page'!D2:D43,"*Positive*")+COUNTIF('Buyer Report Page'!D2:D75,"*Positive*")+COUNTIF('Buyer Help and Support Page'!D2:D55,"*Positive*")+COUNTIF('Buyer Entity Page'!D2:D258,"*Positive*")+COUNTIF('Buyer Add Card Page '!D2:D38,"*Positive*")+COUNTIF('Buyer Payable Page'!D2:D85,"*Positive*")+COUNTIF('Email Notification'!D2:D82,"*Positive*")+COUNTIF('In_App Notification'!D2:D65,"*Positive*") -> 1072 | L6: =COUNTIF(Register!D2:D41,"*Negative*")+COUNTIF(Login!D2:D34,"*Negative*")+COUNTIF('Forgot Password'!D2:D34,"*Negative*")+COUNTIF('Supplier Onboarding'!D2:D256,"*Negative*")+COUNTIF('Buyer Onboarding'!D2:D223,"*Negative*")+COUNTIF('Supplier Dashboard page'!D2:D109,"*Negative*")+COUNTIF('Supplier Buyer page'!D2:D115,"*Negative*")+COUNTIF('Supplier Reports Page'!D2:D75,"*Negative*")+COUNTIF('Supplier Invoices Page'!D2:D132,"*Negative*")+COUNTIF('Supplier Admin page '!D2:D84,"*Negative*")+COUNTIF('Supplier Help and Support Page'!D2:D55,"*Negative*")+COUNTIF('Supplier Entity'!D2:D305,"*Negative*")+COUNTIF('Buyer Dashboard'!D2:D83,"*Negative*")+COUNTIF('Add Supplier Page'!D2:D43,"*Negative*")+COUNTIF('Buyer Report Page'!D2:D75,"*Negative*")+COUNTIF('Buyer Help and Support Page'!D2:D55,"*Negative*")+COUNTIF('Buyer Entity Page'!D2:D258,"*Negative*")+COUNTIF('Buyer Add Card Page '!D2:D38,"*Negative*")+COUNTIF('Buyer Payable Page'!D2:D85,"*Negative*")+COUNTIF('Email Notification'!D2:D82,"*Negative*")+COUNTIF('In_App Notification'!D2:D65,"*Negative*") -> 1120 | Q6: =COUNTA(Register!D2:D41)+COUNTA(Login!D2:D34)+COUNTA('Forgot Password'!D2:D34)+COUNTA('Supplier Onboarding'!D2:D256)+COUNTA('Buyer Onboarding'!D2:D223)+COUNTA('Supplier Dashboard page'!D2:D109)+COUNTA('Supplier Buyer page'!D2:D115)+COUNTA('Supplier Reports Page'!D2:D75)+COUNTA('Supplier Invoices Page'!D2:D132)+COUNTA('Supplier Admin page '!D2:D84)+COUNTA('Supplier Help and Support Page'!D2:D55)+COUNTA('Supplier Entity'!D2:D305)+COUNTA('Buyer Dashboard'!D2:D83)+COUNTA('Add Supplier Page'!D2:D43)+COUNTA('Buyer Report Page'!D2:D75)+COUNTA('Buyer Help and Support Page'!D2:D55)+COUNTA('Buyer Entity Page'!D2:D258)+COUNTA('Buyer Add Card Page '!D2:D38)+COUNTA('Buyer Payable Page'!D2:D85)+COUNTA('Email Notification'!D2:D82)+COUNTA('In_App Notification'!D2:D65)-(COUNTIF(Register!D2:D41,"*Positive*")+COUNTIF(Login!D2:D34,"*Positive*")+COUNTIF('Forgot Password'!D2:D34,"*Positive*")+COUNTIF('Supplier Onboarding'!D2:D256,"*Positive*")+COUNTIF('Buyer Onboarding'!D2:D223,"*Positive*")+COUNTIF('Supplier Dashboard page'!D2:D109,"*Positive*")+COUNTIF('Supplier Buyer page'!D2:D115,"*Positive*")+COUNTIF('Supplier Reports Page'!D2:D75,"*Positive*")+COUNTIF('Supplier Invoices Page'!D2:D132,"*Positive*")+COUNTIF('Supplier Admin page '!D2:D84,"*Positive*")+COUNTIF('Supplier Help and Support Page'!D2:D55,"*Positive*")+COUNTIF('Supplier Entity'!D2:D305,"*Positive*")+COUNTIF('Buyer Dashboard'!D2:D83,"*Positive*")+COUNTIF('Add Supplier Page'!D2:D43,"*Positive*")+COUNTIF('Buyer Report Page'!D2:D75,"*Positive*")+COUNTIF('Buyer Help and Support Page'!D2:D55,"*Positive*")+COUNTIF('Buyer Entity Page'!D2:D258,"*Positive*")+COUNTIF('Buyer Add Card Page '!D2:D38,"*Positive*")+COUNTIF('Buyer Payable Page'!D2:D85,"*Positive*")+COUNTIF('Email Notification'!D2:D82,"*Positive*")+COUNTIF('In_App Notification'!D2:D65,"*Positive*"))-(COUNTIF(Register!D2:D41,"*Negative*")+COUNTIF(Login!D2:D34,"*Negative*")+COUNTIF('Forgot Password'!D2:D34,"*Negative*")+COUNTIF('Supplier Onboarding'!D2:D256,"*Negative*")+COUNTIF('Buyer Onboarding'!D2:D223,"*Negative*")+COUNTIF('Supplier Dashboard page'!D2:D109,"*Negative*")+COUNTIF('Supplier Buyer page'!D2:D115,"*Negative*")+COUNTIF('Supplier Reports Page'!D2:D75,"*Negative*")+COUNTIF('Supplier Invoices Page'!D2:D132,"*Negative*")+COUNTIF('Supplier Admin page '!D2:D84,"*Negative*")+COUNTIF('Supplier Help and Support Page'!D2:D55,"*Negative*")+COUNTIF('Supplier Entity'!D2:D305,"*Negative*")+COUNTIF('Buyer Dashboard'!D2:D83,"*Negative*")+COUNTIF('Add Supplier Page'!D2:D43,"*Negative*")+COUNTIF('Buyer Report Page'!D2:D75,"*Negative*")+COUNTIF('Buyer Help and Support Page'!D2:D55,"*Negative*")+COUNTIF('Buyer Entity Page'!D2:D258,"*Negative*")+COUNTIF('Buyer Add Card Page '!D2:D38,"*Negative*")+COUNTIF('Buyer Payable Page'!D2:D85,"*Negative*")+COUNTIF('Email Notification'!D2:D82,"*Negative*")+COUNTIF('In_App Notification'!D2:D65,"*Negative*")) -> 9
B7: Across all 21 modules | G7: Standard/happy-path flows | L7: Edge cases & error handling | Q7: Defects found during authoring
B10: PASSED | G10: FAILED | L10: BLOCKED | Q10: NOT EXECUTED / PENDING
B11: =COUNTIF(Register!J2:J41,"Pass")+COUNTIF(Login!J2:J34,"Pass")+COUNTIF('Forgot Password'!J2:J34,"Pass")+COUNTIF('Supplier Onboarding'!J2:J256,"Pass")+COUNTIF('Buyer Onboarding'!J2:J223,"Pass")+COUNTIF('Supplier Dashboard page'!J2:J109,"Pass")+COUNTIF('Supplier Buyer page'!J2:J115,"Pass")+COUNTIF('Supplier Reports Page'!J2:J75,"Pass")+COUNTIF('Supplier Invoices Page'!J2:J132,"Pass")+COUNTIF('Supplier Admin page '!J2:J84,"Pass")+COUNTIF('Supplier Help and Support Page'!J2:J55,"Pass")+COUNTIF('Supplier Entity'!J2:J305,"Pass")+COUNTIF('Buyer Dashboard'!J2:J83,"Pass")+COUNTIF('Add Supplier Page'!J2:J43,"Pass")+COUNTIF('Buyer Report Page'!J2:J75,"Pass")+COUNTIF('Buyer Help and Support Page'!J2:J55,"Pass")+COUNTIF('Buyer Entity Page'!J2:J258,"Pass")+COUNTIF('Buyer Add Card Page '!J2:J38,"Pass")+COUNTIF('Buyer Payable Page'!J2:J85,"Pass")+COUNTIF('Email Notification'!J2:J82,"Pass")+COUNTIF('In_App Notification'!J2:J65,"Pass") -> 28 | G11: =COUNTIF(Register!J2:J41,"Fail")+COUNTIF(Login!J2:J34,"Fail")+COUNTIF('Forgot Password'!J2:J34,"Fail")+COUNTIF('Supplier Onboarding'!J2:J256,"Fail")+COUNTIF('Buyer Onboarding'!J2:J223,"Fail")+COUNTIF('Supplier Dashboard page'!J2:J109,"Fail")+COUNTIF('Supplier Buyer page'!J2:J115,"Fail")+COUNTIF('Supplier Reports Page'!J2:J75,"Fail")+COUNTIF('Supplier Invoices Page'!J2:J132,"Fail")+COUNTIF('Supplier Admin page '!J2:J84,"Fail")+COUNTIF('Supplier Help and Support Page'!J2:J55,"Fail")+COUNTIF('Supplier Entity'!J2:J305,"Fail")+COUNTIF('Buyer Dashboard'!J2:J83,"Fail")+COUNTIF('Add Supplier Page'!J2:J43,"Fail")+COUNTIF('Buyer Report Page'!J2:J75,"Fail")+COUNTIF('Buyer Help and Support Page'!J2:J55,"Fail")+COUNTIF('Buyer Entity Page'!J2:J258,"Fail")+COUNTIF('Buyer Add Card Page '!J2:J38,"Fail")+COUNTIF('Buyer Payable Page'!J2:J85,"Fail")+COUNTIF('Email Notification'!J2:J82,"Fail")+COUNTIF('In_App Notification'!J2:J65,"Fail") -> 5 | L11: =COUNTIF(Register!J2:J41,"Blocked")+COUNTIF(Login!J2:J34,"Blocked")+COUNTIF('Forgot Password'!J2:J34,"Blocked")+COUNTIF('Supplier Onboarding'!J2:J256,"Blocked")+COUNTIF('Buyer Onboarding'!J2:J223,"Blocked")+COUNTIF('Supplier Dashboard page'!J2:J109,"Blocked")+COUNTIF('Supplier Buyer page'!J2:J115,"Blocked")+COUNTIF('Supplier Reports Page'!J2:J75,"Blocked")+COUNTIF('Supplier Invoices Page'!J2:J132,"Blocked")+COUNTIF('Supplier Admin page '!J2:J84,"Blocked")+COUNTIF('Supplier Help and Support Page'!J2:J55,"Blocked")+COUNTIF('Supplier Entity'!J2:J305,"Blocked")+COUNTIF('Buyer Dashboard'!J2:J83,"Blocked")+COUNTIF('Add Supplier Page'!J2:J43,"Blocked")+COUNTIF('Buyer Report Page'!J2:J75,"Blocked")+COUNTIF('Buyer Help and Support Page'!J2:J55,"Blocked")+COUNTIF('Buyer Entity Page'!J2:J258,"Blocked")+COUNTIF('Buyer Add Card Page '!J2:J38,"Blocked")+COUNTIF('Buyer Payable Page'!J2:J85,"Blocked")+COUNTIF('Email Notification'!J2:J82,"Blocked")+COUNTIF('In_App Notification'!J2:J65,"Blocked") -> 0 | Q11: =COUNTA(Register!D2:D41)+COUNTA(Login!D2:D34)+COUNTA('Forgot Password'!D2:D34)+COUNTA('Supplier Onboarding'!D2:D256)+COUNTA('Buyer Onboarding'!D2:D223)+COUNTA('Supplier Dashboard page'!D2:D109)+COUNTA('Supplier Buyer page'!D2:D115)+COUNTA('Supplier Reports Page'!D2:D75)+COUNTA('Supplier Invoices Page'!D2:D132)+COUNTA('Supplier Admin page '!D2:D84)+COUNTA('Supplier Help and Support Page'!D2:D55)+COUNTA('Supplier Entity'!D2:D305)+COUNTA('Buyer Dashboard'!D2:D83)+COUNTA('Add Supplier Page'!D2:D43)+COUNTA('Buyer Report Page'!D2:D75)+COUNTA('Buyer Help and Support Page'!D2:D55)+COUNTA('Buyer Entity Page'!D2:D258)+COUNTA('Buyer Add Card Page '!D2:D38)+COUNTA('Buyer Payable Page'!D2:D85)+COUNTA('Email Notification'!D2:D82)+COUNTA('In_App Notification'!D2:D65)-(COUNTIF(Register!J2:J41,"Pass")+COUNTIF(Login!J2:J34,"Pass")+COUNTIF('Forgot Password'!J2:J34,"Pass")+COUNTIF('Supplier Onboarding'!J2:J256,"Pass")+COUNTIF('Buyer Onboarding'!J2:J223,"Pass")+COUNTIF('Supplier Dashboard page'!J2:J109,"Pass")+COUNTIF('Supplier Buyer page'!J2:J115,"Pass")+COUNTIF('Supplier Reports Page'!J2:J75,"Pass")+COUNTIF('Supplier Invoices Page'!J2:J132,"Pass")+COUNTIF('Supplier Admin page '!J2:J84,"Pass")+COUNTIF('Supplier Help and Support Page'!J2:J55,"Pass")+COUNTIF('Supplier Entity'!J2:J305,"Pass")+COUNTIF('Buyer Dashboard'!J2:J83,"Pass")+COUNTIF('Add Supplier Page'!J2:J43,"Pass")+COUNTIF('Buyer Report Page'!J2:J75,"Pass")+COUNTIF('Buyer Help and Support Page'!J2:J55,"Pass")+COUNTIF('Buyer Entity Page'!J2:J258,"Pass")+COUNTIF('Buyer Add Card Page '!J2:J38,"Pass")+COUNTIF('Buyer Payable Page'!J2:J85,"Pass")+COUNTIF('Email Notification'!J2:J82,"Pass")+COUNTIF('In_App Notification'!J2:J65,"Pass"))-(COUNTIF(Register!J2:J41,"Fail")+COUNTIF(Login!J2:J34,"Fail")+COUNTIF('Forgot Password'!J2:J34,"Fail")+COUNTIF('Supplier Onboarding'!J2:J256,"Fail")+COUNTIF('Buyer Onboarding'!J2:J223,"Fail")+COUNTIF('Supplier Dashboard page'!J2:J109,"Fail")+COUNTIF('Supplier Buyer page'!J2:J115,"Fail")+COUNTIF('Supplier Reports Page'!J2:J75,"Fail")+COUNTIF('Supplier Invoices Page'!J2:J132,"Fail")+COUNTIF('Supplier Admin page '!J2:J84,"Fail")+COUNTIF('Supplier Help and Support Page'!J2:J55,"Fail")+COUNTIF('Supplier Entity'!J2:J305,"Fail")+COUNTIF('Buyer Dashboard'!J2:J83,"Fail")+COUNTIF('Add Supplier Page'!J2:J43,"Fail")+COUNTIF('Buyer Report Page'!J2:J75,"Fail")+COUNTIF('Buyer Help and Support Page'!J2:J55,"Fail")+COUNTIF('Buyer Entity Page'!J2:J258,"Fail")+COUNTIF('Buyer Add Card Page '!J2:J38,"Fail")+COUNTIF('Buyer Payable Page'!J2:J85,"Fail")+COUNTIF('Email Notification'!J2:J82,"Fail")+COUNTIF('In_App Notification'!J2:J65,"Fail"))-(COUNTIF(Register!J2:J41,"Blocked")+COUNTIF(Login!J2:J34,"Blocked")+COUNTIF('Forgot Password'!J2:J34,"Blocked")+COUNTIF('Supplier Onboarding'!J2:J256,"Blocked")+COUNTIF('Buyer Onboarding'!J2:J223,"Blocked")+COUNTIF('Supplier Dashboard page'!J2:J109,"Blocked")+COUNTIF('Supplier Buyer page'!J2:J115,"Blocked")+COUNTIF('Supplier Reports Page'!J2:J75,"Blocked")+COUNTIF('Supplier Invoices Page'!J2:J132,"Blocked")+COUNTIF('Supplier Admin page '!J2:J84,"Blocked")+COUNTIF('Supplier Help and Support Page'!J2:J55,"Blocked")+COUNTIF('Supplier Entity'!J2:J305,"Blocked")+COUNTIF('Buyer Dashboard'!J2:J83,"Blocked")+COUNTIF('Add Supplier Page'!J2:J43,"Blocked")+COUNTIF('Buyer Report Page'!J2:J75,"Blocked")+COUNTIF('Buyer Help and Support Page'!J2:J55,"Blocked")+COUNTIF('Buyer Entity Page'!J2:J258,"Blocked")+COUNTIF('Buyer Add Card Page '!J2:J38,"Blocked")+COUNTIF('Buyer Payable Page'!J2:J85,"Blocked")+COUNTIF('Email Notification'!J2:J82,"Blocked")+COUNTIF('In_App Notification'!J2:J65,"Blocked"))-(COUNTIF(Register!J2:J41,"Not Applicable")+COUNTIF(Login!J2:J34,"Not Applicable")+COUNTIF('Forgot Password'!J2:J34,"Not Applicable")+COUNTIF('Supplier Onboarding'!J2:J256,"Not Applicable")+COUNTIF('Buyer Onboarding'!J2:J223,"Not Applicable")+COUNTIF('Supplier Dashboard page'!J2:J109,"Not Applicable")+COUNTIF('Supplier Buyer page'!J2:J115,"Not Applicable")+COUNTIF('Supplier Reports Page'!J2:J75,"Not Applicable")+COUNTIF('Supplier Invoices Page'!J2:J132,"Not Applicable")+COUNTIF('Supplier Admin page '!J2:J84,"Not Applicable")+COUNTIF('Supplier Help and Support Page'!J2:J55,"Not Applicable")+COUNTIF('Supplier Entity'!J2:J305,"Not Applicable")+COUNTIF('Buyer Dashboard'!J2:J83,"Not Applicable")+COUNTIF('Add Supplier Page'!J2:J43,"Not Applicable")+COUNTIF('Buyer Report Page'!J2:J75,"Not Applicable")+COUNTIF('Buyer Help and Support Page'!J2:J55,"Not Applicable")+COUNTIF('Buyer Entity Page'!J2:J258,"Not Applicable")+COUNTIF('Buyer Add Card Page '!J2:J38,"Not Applicable")+COUNTIF('Buyer Payable Page'!J2:J85,"Not Applicable")+COUNTIF('Email Notification'!J2:J82,"Not Applicable")+COUNTIF('In_App Notification'!J2:J65,"Not Applicable")) -> 2168
B12: Executed & working as expected | G12: Executed & defect found | L12: Could not be executed | Q12: Yet to be run by QA
B15: EXECUTION HEALTH
B16: Execution % (Pass+Fail+Blocked / Total) | E16: Pass Rate % (Pass / Executed) | H16: High Priority Test Cases | K16: Medium Priority Test Cases | N16: Low Priority Test Cases
B17: =IFERROR((COUNTIF(Register!J2:J41,"Pass")+COUNTIF(Login!J2:J34,"Pass")+COUNTIF('Forgot Password'!J2:J34,"Pass")+COUNTIF('Supplier Onboarding'!J2:J256,"Pass")+COUNTIF('Buyer Onboarding'!J2:J223,"Pass")+COUNTIF('Supplier Dashboard page'!J2:J109,"Pass")+COUNTIF('Supplier Buyer page'!J2:J115,"Pass")+COUNTIF('Supplier Reports Page'!J2:J75,"Pass")+COUNTIF('Supplier Invoices Page'!J2:J132,"Pass")+COUNTIF('Supplier Admin page '!J2:J84,"Pass")+COUNTIF('Supplier Help and Support Page'!J2:J55,"Pass")+COUNTIF('Supplier Entity'!J2:J305,"Pass")+COUNTIF('Buyer Dashboard'!J2:J83,"Pass")+COUNTIF('Add Supplier Page'!J2:J43,"Pass")+COUNTIF('Buyer Report Page'!J2:J75,"Pass")+COUNTIF('Buyer Help and Support Page'!J2:J55,"Pass")+COUNTIF('Buyer Entity Page'!J2:J258,"Pass")+COUNTIF('Buyer Add Card Page '!J2:J38,"Pass")+COUNTIF('Buyer Payable Page'!J2:J85,"Pass")+COUNTIF('Email Notification'!J2:J82,"Pass")+COUNTIF('In_App Notification'!J2:J65,"Pass")+COUNTIF(Register!J2:J41,"Fail")+COUNTIF(Login!J2:J34,"Fail")+COUNTIF('Forgot Password'!J2:J34,"Fail")+COUNTIF('Supplier Onboarding'!J2:J256,"Fail")+COUNTIF('Buyer Onboarding'!J2:J223,"Fail")+COUNTIF('Supplier Dashboard page'!J2:J109,"Fail")+COUNTIF('Supplier Buyer page'!J2:J115,"Fail")+COUNTIF('Supplier Reports Page'!J2:J75,"Fail")+COUNTIF('Supplier Invoices Page'!J2:J132,"Fail")+COUNTIF('Supplier Admin page '!J2:J84,"Fail")+COUNTIF('Supplier Help and Support Page'!J2:J55,"Fail")+COUNTIF('Supplier Entity'!J2:J305,"Fail")+COUNTIF('Buyer Dashboard'!J2:J83,"Fail")+COUNTIF('Add Supplier Page'!J2:J43,"Fail")+COUNTIF('Buyer Report Page'!J2:J75,"Fail")+COUNTIF('Buyer Help and Support Page'!J2:J55,"Fail")+COUNTIF('Buyer Entity Page'!J2:J258,"Fail")+COUNTIF('Buyer Add Card Page '!J2:J38,"Fail")+COUNTIF('Buyer Payable Page'!J2:J85,"Fail")+COUNTIF('Email Notification'!J2:J82,"Fail")+COUNTIF('In_App Notification'!J2:J65,"Fail")+COUNTIF(Register!J2:J41,"Blocked")+COUNTIF(Login!J2:J34,"Blocked")+COUNTIF('Forgot Password'!J2:J34,"Blocked")+COUNTIF('Supplier Onboarding'!J2:J256,"Blocked")+COUNTIF('Buyer Onboarding'!J2:J223,"Blocked")+COUNTIF('Supplier Dashboard page'!J2:J109,"Blocked")+COUNTIF('Supplier Buyer page'!J2:J115,"Blocked")+COUNTIF('Supplier Reports Page'!J2:J75,"Blocked")+COUNTIF('Supplier Invoices Page'!J2:J132,"Blocked")+COUNTIF('Supplier Admin page '!J2:J84,"Blocked")+COUNTIF('Supplier Help and Support Page'!J2:J55,"Blocked")+COUNTIF('Supplier Entity'!J2:J305,"Blocked")+COUNTIF('Buyer Dashboard'!J2:J83,"Blocked")+COUNTIF('Add Supplier Page'!J2:J43,"Blocked")+COUNTIF('Buyer Report Page'!J2:J75,"Blocked")+COUNTIF('Buyer Help and Support Page'!J2:J55,"Blocked")+COUNTIF('Buyer Entity Page'!J2:J258,"Blocked")+COUNTIF('Buyer Add Card Page '!J2:J38,"Blocked")+COUNTIF('Buyer Payable Page'!J2:J85,"Blocked")+COUNTIF('Email Notification'!J2:J82,"Blocked")+COUNTIF('In_App Notification'!J2:J65,"Blocked"))/(COUNTA(Register!D2:D41)+COUNTA(Login!D2:D34)+COUNTA('Forgot Password'!D2:D34)+COUNTA('Supplier Onboarding'!D2:D256)+COUNTA('Buyer Onboarding'!D2:D223)+COUNTA('Supplier Dashboard page'!D2:D109)+COUNTA('Supplier Buyer page'!D2:D115)+COUNTA('Supplier Reports Page'!D2:D75)+COUNTA('Supplier Invoices Page'!D2:D132)+COUNTA('Supplier Admin page '!D2:D84)+COUNTA('Supplier Help and Support Page'!D2:D55)+COUNTA('Supplier Entity'!D2:D305)+COUNTA('Buyer Dashboard'!D2:D83)+COUNTA('Add Supplier Page'!D2:D43)+COUNTA('Buyer Report Page'!D2:D75)+COUNTA('Buyer Help and Support Page'!D2:D55)+COUNTA('Buyer Entity Page'!D2:D258)+COUNTA('Buyer Add Card Page '!D2:D38)+COUNTA('Buyer Payable Page'!D2:D85)+COUNTA('Email Notification'!D2:D82)+COUNTA('In_App Notification'!D2:D65)),0) -> 0.014993185 | E17: =IFERROR((COUNTIF(Register!J2:J41,"Pass")+COUNTIF(Login!J2:J34,"Pass")+COUNTIF('Forgot Password'!J2:J34,"Pass")+COUNTIF('Supplier Onboarding'!J2:J256,"Pass")+COUNTIF('Buyer Onboarding'!J2:J223,"Pass")+COUNTIF('Supplier Dashboard page'!J2:J109,"Pass")+COUNTIF('Supplier Buyer page'!J2:J115,"Pass")+COUNTIF('Supplier Reports Page'!J2:J75,"Pass")+COUNTIF('Supplier Invoices Page'!J2:J132,"Pass")+COUNTIF('Supplier Admin page '!J2:J84,"Pass")+COUNTIF('Supplier Help and Support Page'!J2:J55,"Pass")+COUNTIF('Supplier Entity'!J2:J305,"Pass")+COUNTIF('Buyer Dashboard'!J2:J83,"Pass")+COUNTIF('Add Supplier Page'!J2:J43,"Pass")+COUNTIF('Buyer Report Page'!J2:J75,"Pass")+COUNTIF('Buyer Help and Support Page'!J2:J55,"Pass")+COUNTIF('Buyer Entity Page'!J2:J258,"Pass")+COUNTIF('Buyer Add Card Page '!J2:J38,"Pass")+COUNTIF('Buyer Payable Page'!J2:J85,"Pass")+COUNTIF('Email Notification'!J2:J82,"Pass")+COUNTIF('In_App Notification'!J2:J65,"Pass"))/(COUNTIF(Register!J2:J41,"Pass")+COUNTIF(Login!J2:J34,"Pass")+COUNTIF('Forgot Password'!J2:J34,"Pass")+COUNTIF('Supplier Onboarding'!J2:J256,"Pass")+COUNTIF('Buyer Onboarding'!J2:J223,"Pass")+COUNTIF('Supplier Dashboard page'!J2:J109,"Pass")+COUNTIF('Supplier Buyer page'!J2:J115,"Pass")+COUNTIF('Supplier Reports Page'!J2:J75,"Pass")+COUNTIF('Supplier Invoices Page'!J2:J132,"Pass")+COUNTIF('Supplier Admin page '!J2:J84,"Pass")+COUNTIF('Supplier Help and Support Page'!J2:J55,"Pass")+COUNTIF('Supplier Entity'!J2:J305,"Pass")+COUNTIF('Buyer Dashboard'!J2:J83,"Pass")+COUNTIF('Add Supplier Page'!J2:J43,"Pass")+COUNTIF('Buyer Report Page'!J2:J75,"Pass")+COUNTIF('Buyer Help and Support Page'!J2:J55,"Pass")+COUNTIF('Buyer Entity Page'!J2:J258,"Pass")+COUNTIF('Buyer Add Card Page '!J2:J38,"Pass")+COUNTIF('Buyer Payable Page'!J2:J85,"Pass")+COUNTIF('Email Notification'!J2:J82,"Pass")+COUNTIF('In_App Notification'!J2:J65,"Pass")+COUNTIF(Register!J2:J41,"Fail")+COUNTIF(Login!J2:J34,"Fail")+COUNTIF('Forgot Password'!J2:J34,"Fail")+COUNTIF('Supplier Onboarding'!J2:J256,"Fail")+COUNTIF('Buyer Onboarding'!J2:J223,"Fail")+COUNTIF('Supplier Dashboard page'!J2:J109,"Fail")+COUNTIF('Supplier Buyer page'!J2:J115,"Fail")+COUNTIF('Supplier Reports Page'!J2:J75,"Fail")+COUNTIF('Supplier Invoices Page'!J2:J132,"Fail")+COUNTIF('Supplier Admin page '!J2:J84,"Fail")+COUNTIF('Supplier Help and Support Page'!J2:J55,"Fail")+COUNTIF('Supplier Entity'!J2:J305,"Fail")+COUNTIF('Buyer Dashboard'!J2:J83,"Fail")+COUNTIF('Add Supplier Page'!J2:J43,"Fail")+COUNTIF('Buyer Report Page'!J2:J75,"Fail")+COUNTIF('Buyer Help and Support Page'!J2:J55,"Fail")+COUNTIF('Buyer Entity Page'!J2:J258,"Fail")+COUNTIF('Buyer Add Card Page '!J2:J38,"Fail")+COUNTIF('Buyer Payable Page'!J2:J85,"Fail")+COUNTIF('Email Notification'!J2:J82,"Fail")+COUNTIF('In_App Notification'!J2:J65,"Fail")),0) -> 0.84848485 | H17: =COUNTIF(Register!E2:E41,"High")+COUNTIF(Login!E2:E34,"High")+COUNTIF('Forgot Password'!E2:E34,"High")+COUNTIF('Supplier Onboarding'!E2:E256,"High")+COUNTIF('Buyer Onboarding'!E2:E223,"High")+COUNTIF('Supplier Dashboard page'!E2:E109,"High")+COUNTIF('Supplier Buyer page'!E2:E115,"High")+COUNTIF('Supplier Reports Page'!E2:E75,"High")+COUNTIF('Supplier Invoices Page'!E2:E132,"High")+COUNTIF('Supplier Admin page '!E2:E84,"High")+COUNTIF('Supplier Help and Support Page'!E2:E55,"High")+COUNTIF('Supplier Entity'!E2:E305,"High")+COUNTIF('Buyer Dashboard'!E2:E83,"High")+COUNTIF('Add Supplier Page'!E2:E43,"High")+COUNTIF('Buyer Report Page'!E2:E75,"High")+COUNTIF('Buyer Help and Support Page'!E2:E55,"High")+COUNTIF('Buyer Entity Page'!E2:E258,"High")+COUNTIF('Buyer Add Card Page '!E2:E38,"High")+COUNTIF('Buyer Payable Page'!E2:E85,"High")+COUNTIF('Email Notification'!E2:E82,"High")+COUNTIF('In_App Notification'!E2:E65,"High") -> 768 | K17: =COUNTIF(Register!E2:E41,"Medium")+COUNTIF(Login!E2:E34,"Medium")+COUNTIF('Forgot Password'!E2:E34,"Medium")+COUNTIF('Supplier Onboarding'!E2:E256,"Medium")+COUNTIF('Buyer Onboarding'!E2:E223,"Medium")+COUNTIF('Supplier Dashboard page'!E2:E109,"Medium")+COUNTIF('Supplier Buyer page'!E2:E115,"Medium")+COUNTIF('Supplier Reports Page'!E2:E75,"Medium")+COUNTIF('Supplier Invoices Page'!E2:E132,"Medium")+COUNTIF('Supplier Admin page '!E2:E84,"Medium")+COUNTIF('Supplier Help and Support Page'!E2:E55,"Medium")+COUNTIF('Supplier Entity'!E2:E305,"Medium")+COUNTIF('Buyer Dashboard'!E2:E83,"Medium")+COUNTIF('Add Supplier Page'!E2:E43,"Medium")+COUNTIF('Buyer Report Page'!E2:E75,"Medium")+COUNTIF('Buyer Help and Support Page'!E2:E55,"Medium")+COUNTIF('Buyer Entity Page'!E2:E258,"Medium")+COUNTIF('Buyer Add Card Page '!E2:E38,"Medium")+COUNTIF('Buyer Payable Page'!E2:E85,"Medium")+COUNTIF('Email Notification'!E2:E82,"Medium")+COUNTIF('In_App Notification'!E2:E65,"Medium") -> 1119 | N17: =COUNTIF(Register!E2:E41,"Low")+COUNTIF(Login!E2:E34,"Low")+COUNTIF('Forgot Password'!E2:E34,"Low")+COUNTIF('Supplier Onboarding'!E2:E256,"Low")+COUNTIF('Buyer Onboarding'!E2:E223,"Low")+COUNTIF('Supplier Dashboard page'!E2:E109,"Low")+COUNTIF('Supplier Buyer page'!E2:E115,"Low")+COUNTIF('Supplier Reports Page'!E2:E75,"Low")+COUNTIF('Supplier Invoices Page'!E2:E132,"Low")+COUNTIF('Supplier Admin page '!E2:E84,"Low")+COUNTIF('Supplier Help and Support Page'!E2:E55,"Low")+COUNTIF('Supplier Entity'!E2:E305,"Low")+COUNTIF('Buyer Dashboard'!E2:E83,"Low")+COUNTIF('Add Supplier Page'!E2:E43,"Low")+COUNTIF('Buyer Report Page'!E2:E75,"Low")+COUNTIF('Buyer Help and Support Page'!E2:E55,"Low")+COUNTIF('Buyer Entity Page'!E2:E258,"Low")+COUNTIF('Buyer Add Card Page '!E2:E38,"Low")+COUNTIF('Buyer Payable Page'!E2:E85,"Low")+COUNTIF('Email Notification'!E2:E82,"Low")+COUNTIF('In_App Notification'!E2:E65,"Low") -> 314
B19: TEST CASE TYPE BREAKDOWN (how the suite is composed)
B20: Test Case Type Category | C20: Count | D20: % of Suite
B21: Functional - Positive | C21: =COUNTIF(Register!D2:D41,"Functional - Positive")+COUNTIF(Login!D2:D34,"Functional - Positive")+COUNTIF('Forgot Password'!D2:D34,"Functional - Positive")+COUNTIF('Supplier Onboarding'!D2:D256,"Functional - Positive")+COUNTIF('Buyer Onboarding'!D2:D223,"Functional - Positive")+COUNTIF('Supplier Dashboard page'!D2:D109,"Functional - Positive")+COUNTIF('Supplier Buyer page'!D2:D115,"Functional - Positive")+COUNTIF('Supplier Reports Page'!D2:D75,"Functional - Positive")+COUNTIF('Supplier Invoices Page'!D2:D132,"Functional - Positive")+COUNTIF('Supplier Admin page '!D2:D84,"Functional - Positive")+COUNTIF('Supplier Help and Support Page'!D2:D55,"Functional - Positive")+COUNTIF('Supplier Entity'!D2:D305,"Functional - Positive")+COUNTIF('Buyer Dashboard'!D2:D83,"Functional - Positive")+COUNTIF('Add Supplier Page'!D2:D43,"Functional - Positive")+COUNTIF('Buyer Report Page'!D2:D75,"Functional - Positive")+COUNTIF('Buyer Help and Support Page'!D2:D55,"Functional - Positive")+COUNTIF('Buyer Entity Page'!D2:D258,"Functional - Positive")+COUNTIF('Buyer Add Card Page '!D2:D38,"Functional - Positive")+COUNTIF('Buyer Payable Page'!D2:D85,"Functional - Positive")+COUNTIF('Email Notification'!D2:D82,"Functional - Positive")+COUNTIF('In_App Notification'!D2:D65,"Functional - Positive") -> 179 | D21: =IFERROR(C21/(COUNTA(Register!D2:D41)+COUNTA(Login!D2:D34)+COUNTA('Forgot Password'!D2:D34)+COUNTA('Supplier Onboarding'!D2:D256)+COUNTA('Buyer Onboarding'!D2:D223)+COUNTA('Supplier Dashboard page'!D2:D109)+COUNTA('Supplier Buyer page'!D2:D115)+COUNTA('Supplier Reports Page'!D2:D75)+COUNTA('Supplier Invoices Page'!D2:D132)+COUNTA('Supplier Admin page '!D2:D84)+COUNTA('Supplier Help and Support Page'!D2:D55)+COUNTA('Supplier Entity'!D2:D305)+COUNTA('Buyer Dashboard'!D2:D83)+COUNTA('Add Supplier Page'!D2:D43)+COUNTA('Buyer Report Page'!D2:D75)+COUNTA('Buyer Help and Support Page'!D2:D55)+COUNTA('Buyer Entity Page'!D2:D258)+COUNTA('Buyer Add Card Page '!D2:D38)+COUNTA('Buyer Payable Page'!D2:D85)+COUNTA('Email Notification'!D2:D82)+COUNTA('In_App Notification'!D2:D65)),0) -> 0.08132667
B22: Functional - Negative | C22: =COUNTIF(Register!D2:D41,"Functional - Negative")+COUNTIF(Login!D2:D34,"Functional - Negative")+COUNTIF('Forgot Password'!D2:D34,"Functional - Negative")+COUNTIF('Supplier Onboarding'!D2:D256,"Functional - Negative")+COUNTIF('Buyer Onboarding'!D2:D223,"Functional - Negative")+COUNTIF('Supplier Dashboard page'!D2:D109,"Functional - Negative")+COUNTIF('Supplier Buyer page'!D2:D115,"Functional - Negative")+COUNTIF('Supplier Reports Page'!D2:D75,"Functional - Negative")+COUNTIF('Supplier Invoices Page'!D2:D132,"Functional - Negative")+COUNTIF('Supplier Admin page '!D2:D84,"Functional - Negative")+COUNTIF('Supplier Help and Support Page'!D2:D55,"Functional - Negative")+COUNTIF('Supplier Entity'!D2:D305,"Functional - Negative")+COUNTIF('Buyer Dashboard'!D2:D83,"Functional - Negative")+COUNTIF('Add Supplier Page'!D2:D43,"Functional - Negative")+COUNTIF('Buyer Report Page'!D2:D75,"Functional - Negative")+COUNTIF('Buyer Help and Support Page'!D2:D55,"Functional - Negative")+COUNTIF('Buyer Entity Page'!D2:D258,"Functional - Negative")+COUNTIF('Buyer Add Card Page '!D2:D38,"Functional - Negative")+COUNTIF('Buyer Payable Page'!D2:D85,"Functional - Negative")+COUNTIF('Email Notification'!D2:D82,"Functional - Negative")+COUNTIF('In_App Notification'!D2:D65,"Functional - Negative") -> 11 | D22: =IFERROR(C22/(COUNTA(Register!D2:D41)+COUNTA(Login!D2:D34)+COUNTA('Forgot Password'!D2:D34)+COUNTA('Supplier Onboarding'!D2:D256)+COUNTA('Buyer Onboarding'!D2:D223)+COUNTA('Supplier Dashboard page'!D2:D109)+COUNTA('Supplier Buyer page'!D2:D115)+COUNTA('Supplier Reports Page'!D2:D75)+COUNTA('Supplier Invoices Page'!D2:D132)+COUNTA('Supplier Admin page '!D2:D84)+COUNTA('Supplier Help and Support Page'!D2:D55)+COUNTA('Supplier Entity'!D2:D305)+COUNTA('Buyer Dashboard'!D2:D83)+COUNTA('Add Supplier Page'!D2:D43)+COUNTA('Buyer Report Page'!D2:D75)+COUNTA('Buyer Help and Support Page'!D2:D55)+COUNTA('Buyer Entity Page'!D2:D258)+COUNTA('Buyer Add Card Page '!D2:D38)+COUNTA('Buyer Payable Page'!D2:D85)+COUNTA('Email Notification'!D2:D82)+COUNTA('In_App Notification'!D2:D65)),0) -> 0.0049977283
B23: Validation - Positive | C23: =COUNTIF(Register!D2:D41,"Validation - Positive")+COUNTIF(Login!D2:D34,"Validation - Positive")+COUNTIF('Forgot Password'!D2:D34,"Validation - Positive")+COUNTIF('Supplier Onboarding'!D2:D256,"Validation - Positive")+COUNTIF('Buyer Onboarding'!D2:D223,"Validation - Positive")+COUNTIF('Supplier Dashboard page'!D2:D109,"Validation - Positive")+COUNTIF('Supplier Buyer page'!D2:D115,"Validation - Positive")+COUNTIF('Supplier Reports Page'!D2:D75,"Validation - Positive")+COUNTIF('Supplier Invoices Page'!D2:D132,"Validation - Positive")+COUNTIF('Supplier Admin page '!D2:D84,"Validation - Positive")+COUNTIF('Supplier Help and Support Page'!D2:D55,"Validation - Positive")+COUNTIF('Supplier Entity'!D2:D305,"Validation - Positive")+COUNTIF('Buyer Dashboard'!D2:D83,"Validation - Positive")+COUNTIF('Add Supplier Page'!D2:D43,"Validation - Positive")+COUNTIF('Buyer Report Page'!D2:D75,"Validation - Positive")+COUNTIF('Buyer Help and Support Page'!D2:D55,"Validation - Positive")+COUNTIF('Buyer Entity Page'!D2:D258,"Validation - Positive")+COUNTIF('Buyer Add Card Page '!D2:D38,"Validation - Positive")+COUNTIF('Buyer Payable Page'!D2:D85,"Validation - Positive")+COUNTIF('Email Notification'!D2:D82,"Validation - Positive")+COUNTIF('In_App Notification'!D2:D65,"Validation - Positive") -> 54 | D23: =IFERROR(C23/(COUNTA(Register!D2:D41)+COUNTA(Login!D2:D34)+COUNTA('Forgot Password'!D2:D34)+COUNTA('Supplier Onboarding'!D2:D256)+COUNTA('Buyer Onboarding'!D2:D223)+COUNTA('Supplier Dashboard page'!D2:D109)+COUNTA('Supplier Buyer page'!D2:D115)+COUNTA('Supplier Reports Page'!D2:D75)+COUNTA('Supplier Invoices Page'!D2:D132)+COUNTA('Supplier Admin page '!D2:D84)+COUNTA('Supplier Help and Support Page'!D2:D55)+COUNTA('Supplier Entity'!D2:D305)+COUNTA('Buyer Dashboard'!D2:D83)+COUNTA('Add Supplier Page'!D2:D43)+COUNTA('Buyer Report Page'!D2:D75)+COUNTA('Buyer Help and Support Page'!D2:D55)+COUNTA('Buyer Entity Page'!D2:D258)+COUNTA('Buyer Add Card Page '!D2:D38)+COUNTA('Buyer Payable Page'!D2:D85)+COUNTA('Email Notification'!D2:D82)+COUNTA('In_App Notification'!D2:D65)),0) -> 0.024534303
B24: Validation - Negative | C24: =COUNTIF(Register!D2:D41,"Validation - Negative")+COUNTIF(Login!D2:D34,"Validation - Negative")+COUNTIF('Forgot Password'!D2:D34,"Validation - Negative")+COUNTIF('Supplier Onboarding'!D2:D256,"Validation - Negative")+COUNTIF('Buyer Onboarding'!D2:D223,"Validation - Negative")+COUNTIF('Supplier Dashboard page'!D2:D109,"Validation - Negative")+COUNTIF('Supplier Buyer page'!D2:D115,"Validation - Negative")+COUNTIF('Supplier Reports Page'!D2:D75,"Validation - Negative")+COUNTIF('Supplier Invoices Page'!D2:D132,"Validation - Negative")+COUNTIF('Supplier Admin page '!D2:D84,"Validation - Negative")+COUNTIF('Supplier Help and Support Page'!D2:D55,"Validation - Negative")+COUNTIF('Supplier Entity'!D2:D305,"Validation - Negative")+COUNTIF('Buyer Dashboard'!D2:D83,"Validation - Negative")+COUNTIF('Add Supplier Page'!D2:D43,"Validation - Negative")+COUNTIF('Buyer Report Page'!D2:D75,"Validation - Negative")+COUNTIF('Buyer Help and Support Page'!D2:D55,"Validation - Negative")+COUNTIF('Buyer Entity Page'!D2:D258,"Validation - Negative")+COUNTIF('Buyer Add Card Page '!D2:D38,"Validation - Negative")+COUNTIF('Buyer Payable Page'!D2:D85,"Validation - Negative")+COUNTIF('Email Notification'!D2:D82,"Validation - Negative")+COUNTIF('In_App Notification'!D2:D65,"Validation - Negative") -> 122 | D24: =IFERROR(C24/(COUNTA(Register!D2:D41)+COUNTA(Login!D2:D34)+COUNTA('Forgot Password'!D2:D34)+COUNTA('Supplier Onboarding'!D2:D256)+COUNTA('Buyer Onboarding'!D2:D223)+COUNTA('Supplier Dashboard page'!D2:D109)+COUNTA('Supplier Buyer page'!D2:D115)+COUNTA('Supplier Reports Page'!D2:D75)+COUNTA('Supplier Invoices Page'!D2:D132)+COUNTA('Supplier Admin page '!D2:D84)+COUNTA('Supplier Help and Support Page'!D2:D55)+COUNTA('Supplier Entity'!D2:D305)+COUNTA('Buyer Dashboard'!D2:D83)+COUNTA('Add Supplier Page'!D2:D43)+COUNTA('Buyer Report Page'!D2:D75)+COUNTA('Buyer Help and Support Page'!D2:D55)+COUNTA('Buyer Entity Page'!D2:D258)+COUNTA('Buyer Add Card Page '!D2:D38)+COUNTA('Buyer Payable Page'!D2:D85)+COUNTA('Email Notification'!D2:D82)+COUNTA('In_App Notification'!D2:D65)),0) -> 0.05542935
B25: Functionality - Positive | C25: =COUNTIF(Register!D2:D41,"Functionality - Positive")+COUNTIF(Login!D2:D34,"Functionality - Positive")+COUNTIF('Forgot Password'!D2:D34,"Functionality - Positive")+COUNTIF('Supplier Onboarding'!D2:D256,"Functionality - Positive")+COUNTIF('Buyer Onboarding'!D2:D223,"Functionality - Positive")+COUNTIF('Supplier Dashboard page'!D2:D109,"Functionality - Positive")+COUNTIF('Supplier Buyer page'!D2:D115,"Functionality - Positive")+COUNTIF('Supplier Reports Page'!D2:D75,"Functionality - Positive")+COUNTIF('Supplier Invoices Page'!D2:D132,"Functionality - Positive")+COUNTIF('Supplier Admin page '!D2:D84,"Functionality - Positive")+COUNTIF('Supplier Help and Support Page'!D2:D55,"Functionality - Positive")+COUNTIF('Supplier Entity'!D2:D305,"Functionality - Positive")+COUNTIF('Buyer Dashboard'!D2:D83,"Functionality - Positive")+COUNTIF('Add Supplier Page'!D2:D43,"Functionality - Positive")+COUNTIF('Buyer Report Page'!D2:D75,"Functionality - Positive")+COUNTIF('Buyer Help and Support Page'!D2:D55,"Functionality - Positive")+COUNTIF('Buyer Entity Page'!D2:D258,"Functionality - Positive")+COUNTIF('Buyer Add Card Page '!D2:D38,"Functionality - Positive")+COUNTIF('Buyer Payable Page'!D2:D85,"Functionality - Positive")+COUNTIF('Email Notification'!D2:D82,"Functionality - Positive")+COUNTIF('In_App Notification'!D2:D65,"Functionality - Positive") -> 33 | D25: =IFERROR(C25/(COUNTA(Register!D2:D41)+COUNTA(Login!D2:D34)+COUNTA('Forgot Password'!D2:D34)+COUNTA('Supplier Onboarding'!D2:D256)+COUNTA('Buyer Onboarding'!D2:D223)+COUNTA('Supplier Dashboard page'!D2:D109)+COUNTA('Supplier Buyer page'!D2:D115)+COUNTA('Supplier Reports Page'!D2:D75)+COUNTA('Supplier Invoices Page'!D2:D132)+COUNTA('Supplier Admin page '!D2:D84)+COUNTA('Supplier Help and Support Page'!D2:D55)+COUNTA('Supplier Entity'!D2:D305)+COUNTA('Buyer Dashboard'!D2:D83)+COUNTA('Add Supplier Page'!D2:D43)+COUNTA('Buyer Report Page'!D2:D75)+COUNTA('Buyer Help and Support Page'!D2:D55)+COUNTA('Buyer Entity Page'!D2:D258)+COUNTA('Buyer Add Card Page '!D2:D38)+COUNTA('Buyer Payable Page'!D2:D85)+COUNTA('Email Notification'!D2:D82)+COUNTA('In_App Notification'!D2:D65)),0) -> 0.014993185
B26: Functionality - Negative | C26: =COUNTIF(Register!D2:D41,"Functionality - Negative")+COUNTIF(Login!D2:D34,"Functionality - Negative")+COUNTIF('Forgot Password'!D2:D34,"Functionality - Negative")+COUNTIF('Supplier Onboarding'!D2:D256,"Functionality - Negative")+COUNTIF('Buyer Onboarding'!D2:D223,"Functionality - Negative")+COUNTIF('Supplier Dashboard page'!D2:D109,"Functionality - Negative")+COUNTIF('Supplier Buyer page'!D2:D115,"Functionality - Negative")+COUNTIF('Supplier Reports Page'!D2:D75,"Functionality - Negative")+COUNTIF('Supplier Invoices Page'!D2:D132,"Functionality - Negative")+COUNTIF('Supplier Admin page '!D2:D84,"Functionality - Negative")+COUNTIF('Supplier Help and Support Page'!D2:D55,"Functionality - Negative")+COUNTIF('Supplier Entity'!D2:D305,"Functionality - Negative")+COUNTIF('Buyer Dashboard'!D2:D83,"Functionality - Negative")+COUNTIF('Add Supplier Page'!D2:D43,"Functionality - Negative")+COUNTIF('Buyer Report Page'!D2:D75,"Functionality - Negative")+COUNTIF('Buyer Help and Support Page'!D2:D55,"Functionality - Negative")+COUNTIF('Buyer Entity Page'!D2:D258,"Functionality - Negative")+COUNTIF('Buyer Add Card Page '!D2:D38,"Functionality - Negative")+COUNTIF('Buyer Payable Page'!D2:D85,"Functionality - Negative")+COUNTIF('Email Notification'!D2:D82,"Functionality - Negative")+COUNTIF('In_App Notification'!D2:D65,"Functionality - Negative") -> 6 | D26: =IFERROR(C26/(COUNTA(Register!D2:D41)+COUNTA(Login!D2:D34)+COUNTA('Forgot Password'!D2:D34)+COUNTA('Supplier Onboarding'!D2:D256)+COUNTA('Buyer Onboarding'!D2:D223)+COUNTA('Supplier Dashboard page'!D2:D109)+COUNTA('Supplier Buyer page'!D2:D115)+COUNTA('Supplier Reports Page'!D2:D75)+COUNTA('Supplier Invoices Page'!D2:D132)+COUNTA('Supplier Admin page '!D2:D84)+COUNTA('Supplier Help and Support Page'!D2:D55)+COUNTA('Supplier Entity'!D2:D305)+COUNTA('Buyer Dashboard'!D2:D83)+COUNTA('Add Supplier Page'!D2:D43)+COUNTA('Buyer Report Page'!D2:D75)+COUNTA('Buyer Help and Support Page'!D2:D55)+COUNTA('Buyer Entity Page'!D2:D258)+COUNTA('Buyer Add Card Page '!D2:D38)+COUNTA('Buyer Payable Page'!D2:D85)+COUNTA('Email Notification'!D2:D82)+COUNTA('In_App Notification'!D2:D65)),0) -> 0.0027260336
B27: Calculation - Positive | C27: =COUNTIF(Register!D2:D41,"Calculation - Positive")+COUNTIF(Login!D2:D34,"Calculation - Positive")+COUNTIF('Forgot Password'!D2:D34,"Calculation - Positive")+COUNTIF('Supplier Onboarding'!D2:D256,"Calculation - Positive")+COUNTIF('Buyer Onboarding'!D2:D223,"Calculation - Positive")+COUNTIF('Supplier Dashboard page'!D2:D109,"Calculation - Positive")+COUNTIF('Supplier Buyer page'!D2:D115,"Calculation - Positive")+COUNTIF('Supplier Reports Page'!D2:D75,"Calculation - Positive")+COUNTIF('Supplier Invoices Page'!D2:D132,"Calculation - Positive")+COUNTIF('Supplier Admin page '!D2:D84,"Calculation - Positive")+COUNTIF('Supplier Help and Support Page'!D2:D55,"Calculation - Positive")+COUNTIF('Supplier Entity'!D2:D305,"Calculation - Positive")+COUNTIF('Buyer Dashboard'!D2:D83,"Calculation - Positive")+COUNTIF('Add Supplier Page'!D2:D43,"Calculation - Positive")+COUNTIF('Buyer Report Page'!D2:D75,"Calculation - Positive")+COUNTIF('Buyer Help and Support Page'!D2:D55,"Calculation - Positive")+COUNTIF('Buyer Entity Page'!D2:D258,"Calculation - Positive")+COUNTIF('Buyer Add Card Page '!D2:D38,"Calculation - Positive")+COUNTIF('Buyer Payable Page'!D2:D85,"Calculation - Positive")+COUNTIF('Email Notification'!D2:D82,"Calculation - Positive")+COUNTIF('In_App Notification'!D2:D65,"Calculation - Positive") -> 16 | D27: =IFERROR(C27/(COUNTA(Register!D2:D41)+COUNTA(Login!D2:D34)+COUNTA('Forgot Password'!D2:D34)+COUNTA('Supplier Onboarding'!D2:D256)+COUNTA('Buyer Onboarding'!D2:D223)+COUNTA('Supplier Dashboard page'!D2:D109)+COUNTA('Supplier Buyer page'!D2:D115)+COUNTA('Supplier Reports Page'!D2:D75)+COUNTA('Supplier Invoices Page'!D2:D132)+COUNTA('Supplier Admin page '!D2:D84)+COUNTA('Supplier Help and Support Page'!D2:D55)+COUNTA('Supplier Entity'!D2:D305)+COUNTA('Buyer Dashboard'!D2:D83)+COUNTA('Add Supplier Page'!D2:D43)+COUNTA('Buyer Report Page'!D2:D75)+COUNTA('Buyer Help and Support Page'!D2:D55)+COUNTA('Buyer Entity Page'!D2:D258)+COUNTA('Buyer Add Card Page '!D2:D38)+COUNTA('Buyer Payable Page'!D2:D85)+COUNTA('Email Notification'!D2:D82)+COUNTA('In_App Notification'!D2:D65)),0) -> 0.007269423
B28: Calculation - Negative | C28: =COUNTIF(Register!D2:D41,"Calculation - Negative")+COUNTIF(Login!D2:D34,"Calculation - Negative")+COUNTIF('Forgot Password'!D2:D34,"Calculation - Negative")+COUNTIF('Supplier Onboarding'!D2:D256,"Calculation - Negative")+COUNTIF('Buyer Onboarding'!D2:D223,"Calculation - Negative")+COUNTIF('Supplier Dashboard page'!D2:D109,"Calculation - Negative")+COUNTIF('Supplier Buyer page'!D2:D115,"Calculation - Negative")+COUNTIF('Supplier Reports Page'!D2:D75,"Calculation - Negative")+COUNTIF('Supplier Invoices Page'!D2:D132,"Calculation - Negative")+COUNTIF('Supplier Admin page '!D2:D84,"Calculation - Negative")+COUNTIF('Supplier Help and Support Page'!D2:D55,"Calculation - Negative")+COUNTIF('Supplier Entity'!D2:D305,"Calculation - Negative")+COUNTIF('Buyer Dashboard'!D2:D83,"Calculation - Negative")+COUNTIF('Add Supplier Page'!D2:D43,"Calculation - Negative")+COUNTIF('Buyer Report Page'!D2:D75,"Calculation - Negative")+COUNTIF('Buyer Help and Support Page'!D2:D55,"Calculation - Negative")+COUNTIF('Buyer Entity Page'!D2:D258,"Calculation - Negative")+COUNTIF('Buyer Add Card Page '!D2:D38,"Calculation - Negative")+COUNTIF('Buyer Payable Page'!D2:D85,"Calculation - Negative")+COUNTIF('Email Notification'!D2:D82,"Calculation - Negative")+COUNTIF('In_App Notification'!D2:D65,"Calculation - Negative") -> 5 | D28: =IFERROR(C28/(COUNTA(Register!D2:D41)+COUNTA(Login!D2:D34)+COUNTA('Forgot Password'!D2:D34)+COUNTA('Supplier Onboarding'!D2:D256)+COUNTA('Buyer Onboarding'!D2:D223)+COUNTA('Supplier Dashboard page'!D2:D109)+COUNTA('Supplier Buyer page'!D2:D115)+COUNTA('Supplier Reports Page'!D2:D75)+COUNTA('Supplier Invoices Page'!D2:D132)+COUNTA('Supplier Admin page '!D2:D84)+COUNTA('Supplier Help and Support Page'!D2:D55)+COUNTA('Supplier Entity'!D2:D305)+COUNTA('Buyer Dashboard'!D2:D83)+COUNTA('Add Supplier Page'!D2:D43)+COUNTA('Buyer Report Page'!D2:D75)+COUNTA('Buyer Help and Support Page'!D2:D55)+COUNTA('Buyer Entity Page'!D2:D258)+COUNTA('Buyer Add Card Page '!D2:D38)+COUNTA('Buyer Payable Page'!D2:D85)+COUNTA('Email Notification'!D2:D82)+COUNTA('In_App Notification'!D2:D65)),0) -> 0.0022716947
B29: Positive (generic) | C29: =COUNTIF(Register!D2:D41,"Positive")+COUNTIF(Login!D2:D34,"Positive")+COUNTIF('Forgot Password'!D2:D34,"Positive")+COUNTIF('Supplier Onboarding'!D2:D256,"Positive")+COUNTIF('Buyer Onboarding'!D2:D223,"Positive")+COUNTIF('Supplier Dashboard page'!D2:D109,"Positive")+COUNTIF('Supplier Buyer page'!D2:D115,"Positive")+COUNTIF('Supplier Reports Page'!D2:D75,"Positive")+COUNTIF('Supplier Invoices Page'!D2:D132,"Positive")+COUNTIF('Supplier Admin page '!D2:D84,"Positive")+COUNTIF('Supplier Help and Support Page'!D2:D55,"Positive")+COUNTIF('Supplier Entity'!D2:D305,"Positive")+COUNTIF('Buyer Dashboard'!D2:D83,"Positive")+COUNTIF('Add Supplier Page'!D2:D43,"Positive")+COUNTIF('Buyer Report Page'!D2:D75,"Positive")+COUNTIF('Buyer Help and Support Page'!D2:D55,"Positive")+COUNTIF('Buyer Entity Page'!D2:D258,"Positive")+COUNTIF('Buyer Add Card Page '!D2:D38,"Positive")+COUNTIF('Buyer Payable Page'!D2:D85,"Positive")+COUNTIF('Email Notification'!D2:D82,"Positive")+COUNTIF('In_App Notification'!D2:D65,"Positive") -> 790 | D29: =IFERROR(C29/(COUNTA(Register!D2:D41)+COUNTA(Login!D2:D34)+COUNTA('Forgot Password'!D2:D34)+COUNTA('Supplier Onboarding'!D2:D256)+COUNTA('Buyer Onboarding'!D2:D223)+COUNTA('Supplier Dashboard page'!D2:D109)+COUNTA('Supplier Buyer page'!D2:D115)+COUNTA('Supplier Reports Page'!D2:D75)+COUNTA('Supplier Invoices Page'!D2:D132)+COUNTA('Supplier Admin page '!D2:D84)+COUNTA('Supplier Help and Support Page'!D2:D55)+COUNTA('Supplier Entity'!D2:D305)+COUNTA('Buyer Dashboard'!D2:D83)+COUNTA('Add Supplier Page'!D2:D43)+COUNTA('Buyer Report Page'!D2:D75)+COUNTA('Buyer Help and Support Page'!D2:D55)+COUNTA('Buyer Entity Page'!D2:D258)+COUNTA('Buyer Add Card Page '!D2:D38)+COUNTA('Buyer Payable Page'!D2:D85)+COUNTA('Email Notification'!D2:D82)+COUNTA('In_App Notification'!D2:D65)),0) -> 0.35892776
B30: Negative (generic) | C30: =COUNTIF(Register!D2:D41,"Negative")+COUNTIF(Login!D2:D34,"Negative")+COUNTIF('Forgot Password'!D2:D34,"Negative")+COUNTIF('Supplier Onboarding'!D2:D256,"Negative")+COUNTIF('Buyer Onboarding'!D2:D223,"Negative")+COUNTIF('Supplier Dashboard page'!D2:D109,"Negative")+COUNTIF('Supplier Buyer page'!D2:D115,"Negative")+COUNTIF('Supplier Reports Page'!D2:D75,"Negative")+COUNTIF('Supplier Invoices Page'!D2:D132,"Negative")+COUNTIF('Supplier Admin page '!D2:D84,"Negative")+COUNTIF('Supplier Help and Support Page'!D2:D55,"Negative")+COUNTIF('Supplier Entity'!D2:D305,"Negative")+COUNTIF('Buyer Dashboard'!D2:D83,"Negative")+COUNTIF('Add Supplier Page'!D2:D43,"Negative")+COUNTIF('Buyer Report Page'!D2:D75,"Negative")+COUNTIF('Buyer Help and Support Page'!D2:D55,"Negative")+COUNTIF('Buyer Entity Page'!D2:D258,"Negative")+COUNTIF('Buyer Add Card Page '!D2:D38,"Negative")+COUNTIF('Buyer Payable Page'!D2:D85,"Negative")+COUNTIF('Email Notification'!D2:D82,"Negative")+COUNTIF('In_App Notification'!D2:D65,"Negative") -> 976 | D30: =IFERROR(C30/(COUNTA(Register!D2:D41)+COUNTA(Login!D2:D34)+COUNTA('Forgot Password'!D2:D34)+COUNTA('Supplier Onboarding'!D2:D256)+COUNTA('Buyer Onboarding'!D2:D223)+COUNTA('Supplier Dashboard page'!D2:D109)+COUNTA('Supplier Buyer page'!D2:D115)+COUNTA('Supplier Reports Page'!D2:D75)+COUNTA('Supplier Invoices Page'!D2:D132)+COUNTA('Supplier Admin page '!D2:D84)+COUNTA('Supplier Help and Support Page'!D2:D55)+COUNTA('Supplier Entity'!D2:D305)+COUNTA('Buyer Dashboard'!D2:D83)+COUNTA('Add Supplier Page'!D2:D43)+COUNTA('Buyer Report Page'!D2:D75)+COUNTA('Buyer Help and Support Page'!D2:D55)+COUNTA('Buyer Entity Page'!D2:D258)+COUNTA('Buyer Add Card Page '!D2:D38)+COUNTA('Buyer Payable Page'!D2:D85)+COUNTA('Email Notification'!D2:D82)+COUNTA('In_App Notification'!D2:D65)),0) -> 0.4434348
B31: Defect - Functional | C31: =COUNTIF(Register!D2:D41,"Defect - Functional")+COUNTIF(Login!D2:D34,"Defect - Functional")+COUNTIF('Forgot Password'!D2:D34,"Defect - Functional")+COUNTIF('Supplier Onboarding'!D2:D256,"Defect - Functional")+COUNTIF('Buyer Onboarding'!D2:D223,"Defect - Functional")+COUNTIF('Supplier Dashboard page'!D2:D109,"Defect - Functional")+COUNTIF('Supplier Buyer page'!D2:D115,"Defect - Functional")+COUNTIF('Supplier Reports Page'!D2:D75,"Defect - Functional")+COUNTIF('Supplier Invoices Page'!D2:D132,"Defect - Functional")+COUNTIF('Supplier Admin page '!D2:D84,"Defect - Functional")+COUNTIF('Supplier Help and Support Page'!D2:D55,"Defect - Functional")+COUNTIF('Supplier Entity'!D2:D305,"Defect - Functional")+COUNTIF('Buyer Dashboard'!D2:D83,"Defect - Functional")+COUNTIF('Add Supplier Page'!D2:D43,"Defect - Functional")+COUNTIF('Buyer Report Page'!D2:D75,"Defect - Functional")+COUNTIF('Buyer Help and Support Page'!D2:D55,"Defect - Functional")+COUNTIF('Buyer Entity Page'!D2:D258,"Defect - Functional")+COUNTIF('Buyer Add Card Page '!D2:D38,"Defect - Functional")+COUNTIF('Buyer Payable Page'!D2:D85,"Defect - Functional")+COUNTIF('Email Notification'!D2:D82,"Defect - Functional")+COUNTIF('In_App Notification'!D2:D65,"Defect - Functional") -> 2 | D31: =IFERROR(C31/(COUNTA(Register!D2:D41)+COUNTA(Login!D2:D34)+COUNTA('Forgot Password'!D2:D34)+COUNTA('Supplier Onboarding'!D2:D256)+COUNTA('Buyer Onboarding'!D2:D223)+COUNTA('Supplier Dashboard page'!D2:D109)+COUNTA('Supplier Buyer page'!D2:D115)+COUNTA('Supplier Reports Page'!D2:D75)+COUNTA('Supplier Invoices Page'!D2:D132)+COUNTA('Supplier Admin page '!D2:D84)+COUNTA('Supplier Help and Support Page'!D2:D55)+COUNTA('Supplier Entity'!D2:D305)+COUNTA('Buyer Dashboard'!D2:D83)+COUNTA('Add Supplier Page'!D2:D43)+COUNTA('Buyer Report Page'!D2:D75)+COUNTA('Buyer Help and Support Page'!D2:D55)+COUNTA('Buyer Entity Page'!D2:D258)+COUNTA('Buyer Add Card Page '!D2:D38)+COUNTA('Buyer Payable Page'!D2:D85)+COUNTA('Email Notification'!D2:D82)+COUNTA('In_App Notification'!D2:D65)),0) -> 0.00090867787
B32: Defect - Validation | C32: =COUNTIF(Register!D2:D41,"Defect - Validation")+COUNTIF(Login!D2:D34,"Defect - Validation")+COUNTIF('Forgot Password'!D2:D34,"Defect - Validation")+COUNTIF('Supplier Onboarding'!D2:D256,"Defect - Validation")+COUNTIF('Buyer Onboarding'!D2:D223,"Defect - Validation")+COUNTIF('Supplier Dashboard page'!D2:D109,"Defect - Validation")+COUNTIF('Supplier Buyer page'!D2:D115,"Defect - Validation")+COUNTIF('Supplier Reports Page'!D2:D75,"Defect - Validation")+COUNTIF('Supplier Invoices Page'!D2:D132,"Defect - Validation")+COUNTIF('Supplier Admin page '!D2:D84,"Defect - Validation")+COUNTIF('Supplier Help and Support Page'!D2:D55,"Defect - Validation")+COUNTIF('Supplier Entity'!D2:D305,"Defect - Validation")+COUNTIF('Buyer Dashboard'!D2:D83,"Defect - Validation")+COUNTIF('Add Supplier Page'!D2:D43,"Defect - Validation")+COUNTIF('Buyer Report Page'!D2:D75,"Defect - Validation")+COUNTIF('Buyer Help and Support Page'!D2:D55,"Defect - Validation")+COUNTIF('Buyer Entity Page'!D2:D258,"Defect - Validation")+COUNTIF('Buyer Add Card Page '!D2:D38,"Defect - Validation")+COUNTIF('Buyer Payable Page'!D2:D85,"Defect - Validation")+COUNTIF('Email Notification'!D2:D82,"Defect - Validation")+COUNTIF('In_App Notification'!D2:D65,"Defect - Validation") -> 7 | D32: =IFERROR(C32/(COUNTA(Register!D2:D41)+COUNTA(Login!D2:D34)+COUNTA('Forgot Password'!D2:D34)+COUNTA('Supplier Onboarding'!D2:D256)+COUNTA('Buyer Onboarding'!D2:D223)+COUNTA('Supplier Dashboard page'!D2:D109)+COUNTA('Supplier Buyer page'!D2:D115)+COUNTA('Supplier Reports Page'!D2:D75)+COUNTA('Supplier Invoices Page'!D2:D132)+COUNTA('Supplier Admin page '!D2:D84)+COUNTA('Supplier Help and Support Page'!D2:D55)+COUNTA('Supplier Entity'!D2:D305)+COUNTA('Buyer Dashboard'!D2:D83)+COUNTA('Add Supplier Page'!D2:D43)+COUNTA('Buyer Report Page'!D2:D75)+COUNTA('Buyer Help and Support Page'!D2:D55)+COUNTA('Buyer Entity Page'!D2:D258)+COUNTA('Buyer Add Card Page '!D2:D38)+COUNTA('Buyer Payable Page'!D2:D85)+COUNTA('Email Notification'!D2:D82)+COUNTA('In_App Notification'!D2:D65)),0) -> 0.0031803726
B35: PER-MODULE / SCREEN BREAKDOWN
B36: Module / Screen | C36: Total TCs | D36: Positive | E36: Negative | F36: High | G36: Medium | H36: Low | I36: Pass | J36: Fail | K36: Blocked | L36: Not Executed | M36: Pass Rate % | N36: Execution %
B37: Register | C37: =COUNTA(Register!D2:D41) -> 40 | D37: =COUNTIF(Register!D2:D41,"*Positive*") -> 18 | E37: =COUNTIF(Register!D2:D41,"*Negative*") -> 22 | F37: =COUNTIF(Register!E2:E41,"High") -> 19 | G37: =COUNTIF(Register!E2:E41,"Medium") -> 11 | H37: =COUNTIF(Register!E2:E41,"Low") -> 10 | I37: =COUNTIF(Register!J2:J41,"Pass") -> 0 | J37: =COUNTIF(Register!J2:J41,"Fail") -> 0 | K37: =COUNTIF(Register!J2:J41,"Blocked") -> 0 | L37: =C37-I37-J37-K37 -> 40 | M37: =IFERROR(I37/(I37+J37),0) -> 0 | N37: =IFERROR((I37+J37+K37)/C37,0) -> 0
B38: Login | C38: =COUNTA(Login!D2:D34) -> 33 | D38: =COUNTIF(Login!D2:D34,"*Positive*") -> 16 | E38: =COUNTIF(Login!D2:D34,"*Negative*") -> 17 | F38: =COUNTIF(Login!E2:E34,"High") -> 18 | G38: =COUNTIF(Login!E2:E34,"Medium") -> 10 | H38: =COUNTIF(Login!E2:E34,"Low") -> 5 | I38: =COUNTIF(Login!J2:J34,"Pass") -> 28 | J38: =COUNTIF(Login!J2:J34,"Fail") -> 5 | K38: =COUNTIF(Login!J2:J34,"Blocked") -> 0 | L38: =C38-I38-J38-K38 -> 0 | M38: =IFERROR(I38/(I38+J38),0) -> 0.84848485 | N38: =IFERROR((I38+J38+K38)/C38,0) -> 1
B39: Forgot Password | C39: =COUNTA('Forgot Password'!D2:D34) -> 33 | D39: =COUNTIF('Forgot Password'!D2:D34,"*Positive*") -> 13 | E39: =COUNTIF('Forgot Password'!D2:D34,"*Negative*") -> 20 | F39: =COUNTIF('Forgot Password'!E2:E34,"High") -> 15 | G39: =COUNTIF('Forgot Password'!E2:E34,"Medium") -> 10 | H39: =COUNTIF('Forgot Password'!E2:E34,"Low") -> 8 | I39: =COUNTIF('Forgot Password'!J2:J34,"Pass") -> 0 | J39: =COUNTIF('Forgot Password'!J2:J34,"Fail") -> 0 | K39: =COUNTIF('Forgot Password'!J2:J34,"Blocked") -> 0 | L39: =C39-I39-J39-K39 -> 33 | M39: =IFERROR(I39/(I39+J39),0) -> 0 | N39: =IFERROR((I39+J39+K39)/C39,0) -> 0
B40: Supplier Onboarding | C40: =COUNTA('Supplier Onboarding'!D2:D256) -> 255 | D40: =COUNTIF('Supplier Onboarding'!D2:D256,"*Positive*") -> 89 | E40: =COUNTIF('Supplier Onboarding'!D2:D256,"*Negative*") -> 166 | F40: =COUNTIF('Supplier Onboarding'!E2:E256,"High") -> 43 | G40: =COUNTIF('Supplier Onboarding'!E2:E256,"Medium") -> 166 | H40: =COUNTIF('Supplier Onboarding'!E2:E256,"Low") -> 46 | I40: =COUNTIF('Supplier Onboarding'!J2:J256,"Pass") -> 0 | J40: =COUNTIF('Supplier Onboarding'!J2:J256,"Fail") -> 0 | K40: =COUNTIF('Supplier Onboarding'!J2:J256,"Blocked") -> 0 | L40: =C40-I40-J40-K40 -> 255 | M40: =IFERROR(I40/(I40+J40),0) -> 0 | N40: =IFERROR((I40+J40+K40)/C40,0) -> 0
B41: Buyer Onboarding | C41: =COUNTA('Buyer Onboarding'!D2:D223) -> 222 | D41: =COUNTIF('Buyer Onboarding'!D2:D223,"*Positive*") -> 81 | E41: =COUNTIF('Buyer Onboarding'!D2:D223,"*Negative*") -> 141 | F41: =COUNTIF('Buyer Onboarding'!E2:E223,"High") -> 41 | G41: =COUNTIF('Buyer Onboarding'!E2:E223,"Medium") -> 141 | H41: =COUNTIF('Buyer Onboarding'!E2:E223,"Low") -> 40 | I41: =COUNTIF('Buyer Onboarding'!J2:J223,"Pass") -> 0 | J41: =COUNTIF('Buyer Onboarding'!J2:J223,"Fail") -> 0 | K41: =COUNTIF('Buyer Onboarding'!J2:J223,"Blocked") -> 0 | L41: =C41-I41-J41-K41 -> 222 | M41: =IFERROR(I41/(I41+J41),0) -> 0 | N41: =IFERROR((I41+J41+K41)/C41,0) -> 0
B42: Supplier Dashboard page | C42: =COUNTA('Supplier Dashboard page'!D2:D109) -> 108 | D42: =COUNTIF('Supplier Dashboard page'!D2:D109,"*Positive*") -> 79 | E42: =COUNTIF('Supplier Dashboard page'!D2:D109,"*Negative*") -> 29 | F42: =COUNTIF('Supplier Dashboard page'!E2:E109,"High") -> 57 | G42: =COUNTIF('Supplier Dashboard page'!E2:E109,"Medium") -> 44 | H42: =COUNTIF('Supplier Dashboard page'!E2:E109,"Low") -> 7 | I42: =COUNTIF('Supplier Dashboard page'!J2:J109,"Pass") -> 0 | J42: =COUNTIF('Supplier Dashboard page'!J2:J109,"Fail") -> 0 | K42: =COUNTIF('Supplier Dashboard page'!J2:J109,"Blocked") -> 0 | L42: =C42-I42-J42-K42 -> 108 | M42: =IFERROR(I42/(I42+J42),0) -> 0 | N42: =IFERROR((I42+J42+K42)/C42,0) -> 0
B43: Supplier Buyer page | C43: =COUNTA('Supplier Buyer page'!D2:D115) -> 114 | D43: =COUNTIF('Supplier Buyer page'!D2:D115,"*Positive*") -> 48 | E43: =COUNTIF('Supplier Buyer page'!D2:D115,"*Negative*") -> 66 | F43: =COUNTIF('Supplier Buyer page'!E2:E115,"High") -> 43 | G43: =COUNTIF('Supplier Buyer page'!E2:E115,"Medium") -> 54 | H43: =COUNTIF('Supplier Buyer page'!E2:E115,"Low") -> 17 | I43: =COUNTIF('Supplier Buyer page'!J2:J115,"Pass") -> 0 | J43: =COUNTIF('Supplier Buyer page'!J2:J115,"Fail") -> 0 | K43: =COUNTIF('Supplier Buyer page'!J2:J115,"Blocked") -> 0 | L43: =C43-I43-J43-K43 -> 114 | M43: =IFERROR(I43/(I43+J43),0) -> 0 | N43: =IFERROR((I43+J43+K43)/C43,0) -> 0
B44: Supplier Reports Page | C44: =COUNTA('Supplier Reports Page'!D2:D75) -> 74 | D44: =COUNTIF('Supplier Reports Page'!D2:D75,"*Positive*") -> 40 | E44: =COUNTIF('Supplier Reports Page'!D2:D75,"*Negative*") -> 34 | F44: =COUNTIF('Supplier Reports Page'!E2:E75,"High") -> 34 | G44: =COUNTIF('Supplier Reports Page'!E2:E75,"Medium") -> 33 | H44: =COUNTIF('Supplier Reports Page'!E2:E75,"Low") -> 7 | I44: =COUNTIF('Supplier Reports Page'!J2:J75,"Pass") -> 0 | J44: =COUNTIF('Supplier Reports Page'!J2:J75,"Fail") -> 0 | K44: =COUNTIF('Supplier Reports Page'!J2:J75,"Blocked") -> 0 | L44: =C44-I44-J44-K44 -> 74 | M44: =IFERROR(I44/(I44+J44),0) -> 0 | N44: =IFERROR((I44+J44+K44)/C44,0) -> 0
B45: Supplier Invoices Page | C45: =COUNTA('Supplier Invoices Page'!D2:D132) -> 131 | D45: =COUNTIF('Supplier Invoices Page'!D2:D132,"*Positive*") -> 90 | E45: =COUNTIF('Supplier Invoices Page'!D2:D132,"*Negative*") -> 41 | F45: =COUNTIF('Supplier Invoices Page'!E2:E132,"High") -> 56 | G45: =COUNTIF('Supplier Invoices Page'!E2:E132,"Medium") -> 58 | H45: =COUNTIF('Supplier Invoices Page'!E2:E132,"Low") -> 17 | I45: =COUNTIF('Supplier Invoices Page'!J2:J132,"Pass") -> 0 | J45: =COUNTIF('Supplier Invoices Page'!J2:J132,"Fail") -> 0 | K45: =COUNTIF('Supplier Invoices Page'!J2:J132,"Blocked") -> 0 | L45: =C45-I45-J45-K45 -> 131 | M45: =IFERROR(I45/(I45+J45),0) -> 0 | N45: =IFERROR((I45+J45+K45)/C45,0) -> 0
B46: Supplier Admin page | C46: =COUNTA('Supplier Admin page '!D2:D84) -> 83 | D46: =COUNTIF('Supplier Admin page '!D2:D84,"*Positive*") -> 48 | E46: =COUNTIF('Supplier Admin page '!D2:D84,"*Negative*") -> 35 | F46: =COUNTIF('Supplier Admin page '!E2:E84,"High") -> 44 | G46: =COUNTIF('Supplier Admin page '!E2:E84,"Medium") -> 33 | H46: =COUNTIF('Supplier Admin page '!E2:E84,"Low") -> 6 | I46: =COUNTIF('Supplier Admin page '!J2:J84,"Pass") -> 0 | J46: =COUNTIF('Supplier Admin page '!J2:J84,"Fail") -> 0 | K46: =COUNTIF('Supplier Admin page '!J2:J84,"Blocked") -> 0 | L46: =C46-I46-J46-K46 -> 83 | M46: =IFERROR(I46/(I46+J46),0) -> 0 | N46: =IFERROR((I46+J46+K46)/C46,0) -> 0
B47: Supplier Help and Support Page | C47: =COUNTA('Supplier Help and Support Page'!D2:D55) -> 54 | D47: =COUNTIF('Supplier Help and Support Page'!D2:D55,"*Positive*") -> 37 | E47: =COUNTIF('Supplier Help and Support Page'!D2:D55,"*Negative*") -> 17 | F47: =COUNTIF('Supplier Help and Support Page'!E2:E55,"High") -> 33 | G47: =COUNTIF('Supplier Help and Support Page'!E2:E55,"Medium") -> 13 | H47: =COUNTIF('Supplier Help and Support Page'!E2:E55,"Low") -> 8 | I47: =COUNTIF('Supplier Help and Support Page'!J2:J55,"Pass") -> 0 | J47: =COUNTIF('Supplier Help and Support Page'!J2:J55,"Fail") -> 0 | K47: =COUNTIF('Supplier Help and Support Page'!J2:J55,"Blocked") -> 0 | L47: =C47-I47-J47-K47 -> 54 | M47: =IFERROR(I47/(I47+J47),0) -> 0 | N47: =IFERROR((I47+J47+K47)/C47,0) -> 0
B48: Supplier Entity | C48: =COUNTA('Supplier Entity'!D2:D305) -> 288 | D48: =COUNTIF('Supplier Entity'!D2:D305,"*Positive*") -> 108 | E48: =COUNTIF('Supplier Entity'!D2:D305,"*Negative*") -> 175 | F48: =COUNTIF('Supplier Entity'!E2:E305,"High") -> 50 | G48: =COUNTIF('Supplier Entity'!E2:E305,"Medium") -> 187 | H48: =COUNTIF('Supplier Entity'!E2:E305,"Low") -> 51 | I48: =COUNTIF('Supplier Entity'!J2:J305,"Pass") -> 0 | J48: =COUNTIF('Supplier Entity'!J2:J305,"Fail") -> 0 | K48: =COUNTIF('Supplier Entity'!J2:J305,"Blocked") -> 0 | L48: =C48-I48-J48-K48 -> 288 | M48: =IFERROR(I48/(I48+J48),0) -> 0 | N48: =IFERROR((I48+J48+K48)/C48,0) -> 0
B49: Buyer Dashboard | C49: =COUNTA('Buyer Dashboard'!D2:D83) -> 76 | D49: =COUNTIF('Buyer Dashboard'!D2:D83,"*Positive*") -> 59 | E49: =COUNTIF('Buyer Dashboard'!D2:D83,"*Negative*") -> 17 | F49: =COUNTIF('Buyer Dashboard'!E2:E83,"High") -> 35 | G49: =COUNTIF('Buyer Dashboard'!E2:E83,"Medium") -> 31 | H49: =COUNTIF('Buyer Dashboard'!E2:E83,"Low") -> 10 | I49: =COUNTIF('Buyer Dashboard'!J2:J83,"Pass") -> 0 | J49: =COUNTIF('Buyer Dashboard'!J2:J83,"Fail") -> 0 | K49: =COUNTIF('Buyer Dashboard'!J2:J83,"Blocked") -> 0 | L49: =C49-I49-J49-K49 -> 76 | M49: =IFERROR(I49/(I49+J49),0) -> 0 | N49: =IFERROR((I49+J49+K49)/C49,0) -> 0
B50: Add Supplier Page | C50: =COUNTA('Add Supplier Page'!D2:D43) -> 42 | D50: =COUNTIF('Add Supplier Page'!D2:D43,"*Positive*") -> 24 | E50: =COUNTIF('Add Supplier Page'!D2:D43,"*Negative*") -> 18 | F50: =COUNTIF('Add Supplier Page'!E2:E43,"High") -> 22 | G50: =COUNTIF('Add Supplier Page'!E2:E43,"Medium") -> 15 | H50: =COUNTIF('Add Supplier Page'!E2:E43,"Low") -> 5 | I50: =COUNTIF('Add Supplier Page'!J2:J43,"Pass") -> 0 | J50: =COUNTIF('Add Supplier Page'!J2:J43,"Fail") -> 0 | K50: =COUNTIF('Add Supplier Page'!J2:J43,"Blocked") -> 0 | L50: =C50-I50-J50-K50 -> 42 | M50: =IFERROR(I50/(I50+J50),0) -> 0 | N50: =IFERROR((I50+J50+K50)/C50,0) -> 0
B51: Buyer Report Page | C51: =COUNTA('Buyer Report Page'!D2:D75) -> 74 | D51: =COUNTIF('Buyer Report Page'!D2:D75,"*Positive*") -> 40 | E51: =COUNTIF('Buyer Report Page'!D2:D75,"*Negative*") -> 34 | F51: =COUNTIF('Buyer Report Page'!E2:E75,"High") -> 34 | G51: =COUNTIF('Buyer Report Page'!E2:E75,"Medium") -> 33 | H51: =COUNTIF('Buyer Report Page'!E2:E75,"Low") -> 7 | I51: =COUNTIF('Buyer Report Page'!J2:J75,"Pass") -> 0 | J51: =COUNTIF('Buyer Report Page'!J2:J75,"Fail") -> 0 | K51: =COUNTIF('Buyer Report Page'!J2:J75,"Blocked") -> 0 | L51: =C51-I51-J51-K51 -> 74 | M51: =IFERROR(I51/(I51+J51),0) -> 0 | N51: =IFERROR((I51+J51+K51)/C51,0) -> 0
B52: Buyer Help and Support Page | C52: =COUNTA('Buyer Help and Support Page'!D2:D55) -> 54 | D52: =COUNTIF('Buyer Help and Support Page'!D2:D55,"*Positive*") -> 37 | E52: =COUNTIF('Buyer Help and Support Page'!D2:D55,"*Negative*") -> 17 | F52: =COUNTIF('Buyer Help and Support Page'!E2:E55,"High") -> 33 | G52: =COUNTIF('Buyer Help and Support Page'!E2:E55,"Medium") -> 13 | H52: =COUNTIF('Buyer Help and Support Page'!E2:E55,"Low") -> 8 | I52: =COUNTIF('Buyer Help and Support Page'!J2:J55,"Pass") -> 0 | J52: =COUNTIF('Buyer Help and Support Page'!J2:J55,"Fail") -> 0 | K52: =COUNTIF('Buyer Help and Support Page'!J2:J55,"Blocked") -> 0 | L52: =C52-I52-J52-K52 -> 54 | M52: =IFERROR(I52/(I52+J52),0) -> 0 | N52: =IFERROR((I52+J52+K52)/C52,0) -> 0
B53: Buyer Entity Page | C53: =COUNTA('Buyer Entity Page'!D2:D258) -> 254 | D53: =COUNTIF('Buyer Entity Page'!D2:D258,"*Positive*") -> 100 | E53: =COUNTIF('Buyer Entity Page'!D2:D258,"*Negative*") -> 150 | F53: =COUNTIF('Buyer Entity Page'!E2:E258,"High") -> 48 | G53: =COUNTIF('Buyer Entity Page'!E2:E258,"Medium") -> 161 | H53: =COUNTIF('Buyer Entity Page'!E2:E258,"Low") -> 45 | I53: =COUNTIF('Buyer Entity Page'!J2:J258,"Pass") -> 0 | J53: =COUNTIF('Buyer Entity Page'!J2:J258,"Fail") -> 0 | K53: =COUNTIF('Buyer Entity Page'!J2:J258,"Blocked") -> 0 | L53: =C53-I53-J53-K53 -> 254 | M53: =IFERROR(I53/(I53+J53),0) -> 0 | N53: =IFERROR((I53+J53+K53)/C53,0) -> 0
B54: Buyer Add Card Page | C54: =COUNTA('Buyer Add Card Page '!D2:D38) -> 37 | D54: =COUNTIF('Buyer Add Card Page '!D2:D38,"*Positive*") -> 19 | E54: =COUNTIF('Buyer Add Card Page '!D2:D38,"*Negative*") -> 18 | F54: =COUNTIF('Buyer Add Card Page '!E2:E38,"High") -> 19 | G54: =COUNTIF('Buyer Add Card Page '!E2:E38,"Medium") -> 13 | H54: =COUNTIF('Buyer Add Card Page '!E2:E38,"Low") -> 5 | I54: =COUNTIF('Buyer Add Card Page '!J2:J38,"Pass") -> 0 | J54: =COUNTIF('Buyer Add Card Page '!J2:J38,"Fail") -> 0 | K54: =COUNTIF('Buyer Add Card Page '!J2:J38,"Blocked") -> 0 | L54: =C54-I54-J54-K54 -> 37 | M54: =IFERROR(I54/(I54+J54),0) -> 0 | N54: =IFERROR((I54+J54+K54)/C54,0) -> 0
B55: Buyer Payable Page | C55: =COUNTA('Buyer Payable Page'!D2:D85) -> 84 | D55: =COUNTIF('Buyer Payable Page'!D2:D85,"*Positive*") -> 52 | E55: =COUNTIF('Buyer Payable Page'!D2:D85,"*Negative*") -> 32 | F55: =COUNTIF('Buyer Payable Page'!E2:E85,"High") -> 35 | G55: =COUNTIF('Buyer Payable Page'!E2:E85,"Medium") -> 40 | H55: =COUNTIF('Buyer Payable Page'!E2:E85,"Low") -> 9 | I55: =COUNTIF('Buyer Payable Page'!J2:J85,"Pass") -> 0 | J55: =COUNTIF('Buyer Payable Page'!J2:J85,"Fail") -> 0 | K55: =COUNTIF('Buyer Payable Page'!J2:J85,"Blocked") -> 0 | L55: =C55-I55-J55-K55 -> 84 | M55: =IFERROR(I55/(I55+J55),0) -> 0 | N55: =IFERROR((I55+J55+K55)/C55,0) -> 0
B56: Email Notification | C56: =COUNTA('Email Notification'!D2:D82) -> 81 | D56: =COUNTIF('Email Notification'!D2:D82,"*Positive*") -> 40 | E56: =COUNTIF('Email Notification'!D2:D82,"*Negative*") -> 41 | F56: =COUNTIF('Email Notification'!E2:E82,"High") -> 45 | G56: =COUNTIF('Email Notification'!E2:E82,"Medium") -> 34 | H56: =COUNTIF('Email Notification'!E2:E82,"Low") -> 2 | I56: =COUNTIF('Email Notification'!J2:J82,"Pass") -> 0 | J56: =COUNTIF('Email Notification'!J2:J82,"Fail") -> 0 | K56: =COUNTIF('Email Notification'!J2:J82,"Blocked") -> 0 | L56: =C56-I56-J56-K56 -> 81 | M56: =IFERROR(I56/(I56+J56),0) -> 0 | N56: =IFERROR((I56+J56+K56)/C56,0) -> 0
B57: In_App Notification | C57: =COUNTA('In_App Notification'!D2:D65) -> 64 | D57: =COUNTIF('In_App Notification'!D2:D65,"*Positive*") -> 34 | E57: =COUNTIF('In_App Notification'!D2:D65,"*Negative*") -> 30 | F57: =COUNTIF('In_App Notification'!E2:E65,"High") -> 44 | G57: =COUNTIF('In_App Notification'!E2:E65,"Medium") -> 19 | H57: =COUNTIF('In_App Notification'!E2:E65,"Low") -> 1 | I57: =COUNTIF('In_App Notification'!J2:J65,"Pass") -> 0 | J57: =COUNTIF('In_App Notification'!J2:J65,"Fail") -> 0 | K57: =COUNTIF('In_App Notification'!J2:J65,"Blocked") -> 0 | L57: =C57-I57-J57-K57 -> 64 | M57: =IFERROR(I57/(I57+J57),0) -> 0 | N57: =IFERROR((I57+J57+K57)/C57,0) -> 0
B58: TOTAL (ALL MODULES) | C58: =SUM(C37:C57) -> 2201 | D58: =SUM(D37:D57) -> 1072 | E58: =SUM(E37:E57) -> 1120 | F58: =SUM(F37:F57) -> 768 | G58: =SUM(G37:G57) -> 1119 | H58: =SUM(H37:H57) -> 314 | I58: =SUM(I37:I57) -> 28 | J58: =SUM(J37:J57) -> 5 | K58: =SUM(K37:K57) -> 0 | L58: =C58-I58-J58-K58 -> 2168 | M58: =IFERROR(I58/(I58+J58),0) -> 0.84848485 | N58: =IFERROR((I58+J58+K58)/C58,0) -> 0.014993185
B60: Notes: 'Not Executed' includes rows with no Status value yet. 'Other' test-case types are defect-log entries recorded during authoring (e.g., Defect - Functional/Validation) and are excluded from Positive/Negative counts. All figures on this page are formulas — they update automatically as the QA team fills in Actual Result / Status on each module tab.
P63: Chart data
P64: Positive | Q64: =COUNTIF(Register!D2:D41,"*Positive*")+COUNTIF(Login!D2:D34,"*Positive*")+COUNTIF('Forgot Password'!D2:D34,"*Positive*")+COUNTIF('Supplier Onboarding'!D2:D256,"*Positive*")+COUNTIF('Buyer Onboarding'!D2:D223,"*Positive*")+COUNTIF('Supplier Dashboard page'!D2:D109,"*Positive*")+COUNTIF('Supplier Buyer page'!D2:D115,"*Positive*")+COUNTIF('Supplier Reports Page'!D2:D75,"*Positive*")+COUNTIF('Supplier Invoices Page'!D2:D132,"*Positive*")+COUNTIF('Supplier Admin page '!D2:D84,"*Positive*")+COUNTIF('Supplier Help and Support Page'!D2:D55,"*Positive*")+COUNTIF('Supplier Entity'!D2:D305,"*Positive*")+COUNTIF('Buyer Dashboard'!D2:D83,"*Positive*")+COUNTIF('Add Supplier Page'!D2:D43,"*Positive*")+COUNTIF('Buyer Report Page'!D2:D75,"*Positive*")+COUNTIF('Buyer Help and Support Page'!D2:D55,"*Positive*")+COUNTIF('Buyer Entity Page'!D2:D258,"*Positive*")+COUNTIF('Buyer Add Card Page '!D2:D38,"*Positive*")+COUNTIF('Buyer Payable Page'!D2:D85,"*Positive*")+COUNTIF('Email Notification'!D2:D82,"*Positive*")+COUNTIF('In_App Notification'!D2:D65,"*Positive*") -> 1072
P65: Negative | Q65: =COUNTIF(Register!D2:D41,"*Negative*")+COUNTIF(Login!D2:D34,"*Negative*")+COUNTIF('Forgot Password'!D2:D34,"*Negative*")+COUNTIF('Supplier Onboarding'!D2:D256,"*Negative*")+COUNTIF('Buyer Onboarding'!D2:D223,"*Negative*")+COUNTIF('Supplier Dashboard page'!D2:D109,"*Negative*")+COUNTIF('Supplier Buyer page'!D2:D115,"*Negative*")+COUNTIF('Supplier Reports Page'!D2:D75,"*Negative*")+COUNTIF('Supplier Invoices Page'!D2:D132,"*Negative*")+COUNTIF('Supplier Admin page '!D2:D84,"*Negative*")+COUNTIF('Supplier Help and Support Page'!D2:D55,"*Negative*")+COUNTIF('Supplier Entity'!D2:D305,"*Negative*")+COUNTIF('Buyer Dashboard'!D2:D83,"*Negative*")+COUNTIF('Add Supplier Page'!D2:D43,"*Negative*")+COUNTIF('Buyer Report Page'!D2:D75,"*Negative*")+COUNTIF('Buyer Help and Support Page'!D2:D55,"*Negative*")+COUNTIF('Buyer Entity Page'!D2:D258,"*Negative*")+COUNTIF('Buyer Add Card Page '!D2:D38,"*Negative*")+COUNTIF('Buyer Payable Page'!D2:D85,"*Negative*")+COUNTIF('Email Notification'!D2:D82,"*Negative*")+COUNTIF('In_App Notification'!D2:D65,"*Negative*") -> 1120
P66: Other | Q66: =COUNTA(Register!D2:D41)+COUNTA(Login!D2:D34)+COUNTA('Forgot Password'!D2:D34)+COUNTA('Supplier Onboarding'!D2:D256)+COUNTA('Buyer Onboarding'!D2:D223)+COUNTA('Supplier Dashboard page'!D2:D109)+COUNTA('Supplier Buyer page'!D2:D115)+COUNTA('Supplier Reports Page'!D2:D75)+COUNTA('Supplier Invoices Page'!D2:D132)+COUNTA('Supplier Admin page '!D2:D84)+COUNTA('Supplier Help and Support Page'!D2:D55)+COUNTA('Supplier Entity'!D2:D305)+COUNTA('Buyer Dashboard'!D2:D83)+COUNTA('Add Supplier Page'!D2:D43)+COUNTA('Buyer Report Page'!D2:D75)+COUNTA('Buyer Help and Support Page'!D2:D55)+COUNTA('Buyer Entity Page'!D2:D258)+COUNTA('Buyer Add Card Page '!D2:D38)+COUNTA('Buyer Payable Page'!D2:D85)+COUNTA('Email Notification'!D2:D82)+COUNTA('In_App Notification'!D2:D65)-(COUNTIF(Register!D2:D41,"*Positive*")+COUNTIF(Login!D2:D34,"*Positive*")+COUNTIF('Forgot Password'!D2:D34,"*Positive*")+COUNTIF('Supplier Onboarding'!D2:D256,"*Positive*")+COUNTIF('Buyer Onboarding'!D2:D223,"*Positive*")+COUNTIF('Supplier Dashboard page'!D2:D109,"*Positive*")+COUNTIF('Supplier Buyer page'!D2:D115,"*Positive*")+COUNTIF('Supplier Reports Page'!D2:D75,"*Positive*")+COUNTIF('Supplier Invoices Page'!D2:D132,"*Positive*")+COUNTIF('Supplier Admin page '!D2:D84,"*Positive*")+COUNTIF('Supplier Help and Support Page'!D2:D55,"*Positive*")+COUNTIF('Supplier Entity'!D2:D305,"*Positive*")+COUNTIF('Buyer Dashboard'!D2:D83,"*Positive*")+COUNTIF('Add Supplier Page'!D2:D43,"*Positive*")+COUNTIF('Buyer Report Page'!D2:D75,"*Positive*")+COUNTIF('Buyer Help and Support Page'!D2:D55,"*Positive*")+COUNTIF('Buyer Entity Page'!D2:D258,"*Positive*")+COUNTIF('Buyer Add Card Page '!D2:D38,"*Positive*")+COUNTIF('Buyer Payable Page'!D2:D85,"*Positive*")+COUNTIF('Email Notification'!D2:D82,"*Positive*")+COUNTIF('In_App Notification'!D2:D65,"*Positive*"))-(COUNTIF(Register!D2:D41,"*Negative*")+COUNTIF(Login!D2:D34,"*Negative*")+COUNTIF('Forgot Password'!D2:D34,"*Negative*")+COUNTIF('Supplier Onboarding'!D2:D256,"*Negative*")+COUNTIF('Buyer Onboarding'!D2:D223,"*Negative*")+COUNTIF('Supplier Dashboard page'!D2:D109,"*Negative*")+COUNTIF('Supplier Buyer page'!D2:D115,"*Negative*")+COUNTIF('Supplier Reports Page'!D2:D75,"*Negative*")+COUNTIF('Supplier Invoices Page'!D2:D132,"*Negative*")+COUNTIF('Supplier Admin page '!D2:D84,"*Negative*")+COUNTIF('Supplier Help and Support Page'!D2:D55,"*Negative*")+COUNTIF('Supplier Entity'!D2:D305,"*Negative*")+COUNTIF('Buyer Dashboard'!D2:D83,"*Negative*")+COUNTIF('Add Supplier Page'!D2:D43,"*Negative*")+COUNTIF('Buyer Report Page'!D2:D75,"*Negative*")+COUNTIF('Buyer Help and Support Page'!D2:D55,"*Negative*")+COUNTIF('Buyer Entity Page'!D2:D258,"*Negative*")+COUNTIF('Buyer Add Card Page '!D2:D38,"*Negative*")+COUNTIF('Buyer Payable Page'!D2:D85,"*Negative*")+COUNTIF('Email Notification'!D2:D82,"*Negative*")+COUNTIF('In_App Notification'!D2:D65,"*Negative*")) -> 9
P68: Pass | Q68: =COUNTIF(Register!J2:J41,"Pass")+COUNTIF(Login!J2:J34,"Pass")+COUNTIF('Forgot Password'!J2:J34,"Pass")+COUNTIF('Supplier Onboarding'!J2:J256,"Pass")+COUNTIF('Buyer Onboarding'!J2:J223,"Pass")+COUNTIF('Supplier Dashboard page'!J2:J109,"Pass")+COUNTIF('Supplier Buyer page'!J2:J115,"Pass")+COUNTIF('Supplier Reports Page'!J2:J75,"Pass")+COUNTIF('Supplier Invoices Page'!J2:J132,"Pass")+COUNTIF('Supplier Admin page '!J2:J84,"Pass")+COUNTIF('Supplier Help and Support Page'!J2:J55,"Pass")+COUNTIF('Supplier Entity'!J2:J305,"Pass")+COUNTIF('Buyer Dashboard'!J2:J83,"Pass")+COUNTIF('Add Supplier Page'!J2:J43,"Pass")+COUNTIF('Buyer Report Page'!J2:J75,"Pass")+COUNTIF('Buyer Help and Support Page'!J2:J55,"Pass")+COUNTIF('Buyer Entity Page'!J2:J258,"Pass")+COUNTIF('Buyer Add Card Page '!J2:J38,"Pass")+COUNTIF('Buyer Payable Page'!J2:J85,"Pass")+COUNTIF('Email Notification'!J2:J82,"Pass")+COUNTIF('In_App Notification'!J2:J65,"Pass") -> 28
P69: Fail | Q69: =COUNTIF(Register!J2:J41,"Fail")+COUNTIF(Login!J2:J34,"Fail")+COUNTIF('Forgot Password'!J2:J34,"Fail")+COUNTIF('Supplier Onboarding'!J2:J256,"Fail")+COUNTIF('Buyer Onboarding'!J2:J223,"Fail")+COUNTIF('Supplier Dashboard page'!J2:J109,"Fail")+COUNTIF('Supplier Buyer page'!J2:J115,"Fail")+COUNTIF('Supplier Reports Page'!J2:J75,"Fail")+COUNTIF('Supplier Invoices Page'!J2:J132,"Fail")+COUNTIF('Supplier Admin page '!J2:J84,"Fail")+COUNTIF('Supplier Help and Support Page'!J2:J55,"Fail")+COUNTIF('Supplier Entity'!J2:J305,"Fail")+COUNTIF('Buyer Dashboard'!J2:J83,"Fail")+COUNTIF('Add Supplier Page'!J2:J43,"Fail")+COUNTIF('Buyer Report Page'!J2:J75,"Fail")+COUNTIF('Buyer Help and Support Page'!J2:J55,"Fail")+COUNTIF('Buyer Entity Page'!J2:J258,"Fail")+COUNTIF('Buyer Add Card Page '!J2:J38,"Fail")+COUNTIF('Buyer Payable Page'!J2:J85,"Fail")+COUNTIF('Email Notification'!J2:J82,"Fail")+COUNTIF('In_App Notification'!J2:J65,"Fail") -> 5
P70: Blocked | Q70: =COUNTIF(Register!J2:J41,"Blocked")+COUNTIF(Login!J2:J34,"Blocked")+COUNTIF('Forgot Password'!J2:J34,"Blocked")+COUNTIF('Supplier Onboarding'!J2:J256,"Blocked")+COUNTIF('Buyer Onboarding'!J2:J223,"Blocked")+COUNTIF('Supplier Dashboard page'!J2:J109,"Blocked")+COUNTIF('Supplier Buyer page'!J2:J115,"Blocked")+COUNTIF('Supplier Reports Page'!J2:J75,"Blocked")+COUNTIF('Supplier Invoices Page'!J2:J132,"Blocked")+COUNTIF('Supplier Admin page '!J2:J84,"Blocked")+COUNTIF('Supplier Help and Support Page'!J2:J55,"Blocked")+COUNTIF('Supplier Entity'!J2:J305,"Blocked")+COUNTIF('Buyer Dashboard'!J2:J83,"Blocked")+COUNTIF('Add Supplier Page'!J2:J43,"Blocked")+COUNTIF('Buyer Report Page'!J2:J75,"Blocked")+COUNTIF('Buyer Help and Support Page'!J2:J55,"Blocked")+COUNTIF('Buyer Entity Page'!J2:J258,"Blocked")+COUNTIF('Buyer Add Card Page '!J2:J38,"Blocked")+COUNTIF('Buyer Payable Page'!J2:J85,"Blocked")+COUNTIF('Email Notification'!J2:J82,"Blocked")+COUNTIF('In_App Notification'!J2:J65,"Blocked") -> 0
P71: Not Executed | Q71: =COUNTA(Register!D2:D41)+COUNTA(Login!D2:D34)+COUNTA('Forgot Password'!D2:D34)+COUNTA('Supplier Onboarding'!D2:D256)+COUNTA('Buyer Onboarding'!D2:D223)+COUNTA('Supplier Dashboard page'!D2:D109)+COUNTA('Supplier Buyer page'!D2:D115)+COUNTA('Supplier Reports Page'!D2:D75)+COUNTA('Supplier Invoices Page'!D2:D132)+COUNTA('Supplier Admin page '!D2:D84)+COUNTA('Supplier Help and Support Page'!D2:D55)+COUNTA('Supplier Entity'!D2:D305)+COUNTA('Buyer Dashboard'!D2:D83)+COUNTA('Add Supplier Page'!D2:D43)+COUNTA('Buyer Report Page'!D2:D75)+COUNTA('Buyer Help and Support Page'!D2:D55)+COUNTA('Buyer Entity Page'!D2:D258)+COUNTA('Buyer Add Card Page '!D2:D38)+COUNTA('Buyer Payable Page'!D2:D85)+COUNTA('Email Notification'!D2:D82)+COUNTA('In_App Notification'!D2:D65)-(COUNTIF(Register!J2:J41,"Pass")+COUNTIF(Login!J2:J34,"Pass")+COUNTIF('Forgot Password'!J2:J34,"Pass")+COUNTIF('Supplier Onboarding'!J2:J256,"Pass")+COUNTIF('Buyer Onboarding'!J2:J223,"Pass")+COUNTIF('Supplier Dashboard page'!J2:J109,"Pass")+COUNTIF('Supplier Buyer page'!J2:J115,"Pass")+COUNTIF('Supplier Reports Page'!J2:J75,"Pass")+COUNTIF('Supplier Invoices Page'!J2:J132,"Pass")+COUNTIF('Supplier Admin page '!J2:J84,"Pass")+COUNTIF('Supplier Help and Support Page'!J2:J55,"Pass")+COUNTIF('Supplier Entity'!J2:J305,"Pass")+COUNTIF('Buyer Dashboard'!J2:J83,"Pass")+COUNTIF('Add Supplier Page'!J2:J43,"Pass")+COUNTIF('Buyer Report Page'!J2:J75,"Pass")+COUNTIF('Buyer Help and Support Page'!J2:J55,"Pass")+COUNTIF('Buyer Entity Page'!J2:J258,"Pass")+COUNTIF('Buyer Add Card Page '!J2:J38,"Pass")+COUNTIF('Buyer Payable Page'!J2:J85,"Pass")+COUNTIF('Email Notification'!J2:J82,"Pass")+COUNTIF('In_App Notification'!J2:J65,"Pass"))-(COUNTIF(Register!J2:J41,"Fail")+COUNTIF(Login!J2:J34,"Fail")+COUNTIF('Forgot Password'!J2:J34,"Fail")+COUNTIF('Supplier Onboarding'!J2:J256,"Fail")+COUNTIF('Buyer Onboarding'!J2:J223,"Fail")+COUNTIF('Supplier Dashboard page'!J2:J109,"Fail")+COUNTIF('Supplier Buyer page'!J2:J115,"Fail")+COUNTIF('Supplier Reports Page'!J2:J75,"Fail")+COUNTIF('Supplier Invoices Page'!J2:J132,"Fail")+COUNTIF('Supplier Admin page '!J2:J84,"Fail")+COUNTIF('Supplier Help and Support Page'!J2:J55,"Fail")+COUNTIF('Supplier Entity'!J2:J305,"Fail")+COUNTIF('Buyer Dashboard'!J2:J83,"Fail")+COUNTIF('Add Supplier Page'!J2:J43,"Fail")+COUNTIF('Buyer Report Page'!J2:J75,"Fail")+COUNTIF('Buyer Help and Support Page'!J2:J55,"Fail")+COUNTIF('Buyer Entity Page'!J2:J258,"Fail")+COUNTIF('Buyer Add Card Page '!J2:J38,"Fail")+COUNTIF('Buyer Payable Page'!J2:J85,"Fail")+COUNTIF('Email Notification'!J2:J82,"Fail")+COUNTIF('In_App Notification'!J2:J65,"Fail"))-(COUNTIF(Register!J2:J41,"Blocked")+COUNTIF(Login!J2:J34,"Blocked")+COUNTIF('Forgot Password'!J2:J34,"Blocked")+COUNTIF('Supplier Onboarding'!J2:J256,"Blocked")+COUNTIF('Buyer Onboarding'!J2:J223,"Blocked")+COUNTIF('Supplier Dashboard page'!J2:J109,"Blocked")+COUNTIF('Supplier Buyer page'!J2:J115,"Blocked")+COUNTIF('Supplier Reports Page'!J2:J75,"Blocked")+COUNTIF('Supplier Invoices Page'!J2:J132,"Blocked")+COUNTIF('Supplier Admin page '!J2:J84,"Blocked")+COUNTIF('Supplier Help and Support Page'!J2:J55,"Blocked")+COUNTIF('Supplier Entity'!J2:J305,"Blocked")+COUNTIF('Buyer Dashboard'!J2:J83,"Blocked")+COUNTIF('Add Supplier Page'!J2:J43,"Blocked")+COUNTIF('Buyer Report Page'!J2:J75,"Blocked")+COUNTIF('Buyer Help and Support Page'!J2:J55,"Blocked")+COUNTIF('Buyer Entity Page'!J2:J258,"Blocked")+COUNTIF('Buyer Add Card Page '!J2:J38,"Blocked")+COUNTIF('Buyer Payable Page'!J2:J85,"Blocked")+COUNTIF('Email Notification'!J2:J82,"Blocked")+COUNTIF('In_App Notification'!J2:J65,"Blocked")) -> 2168

Sheet Register
A1: Test Case ID | B1: Screen | C1: Test Case Description | D1: Test Case Type | E1: Priority | F1: Test Steps | G1: Test Data | H1: Expected Result | I1: Actual Result | J1: Status | K1: Remarks
A2: TC_REG_AIR_01 | B2: Register - Airlines | C2: Register successfully with all valid mandatory fields | D2: Positive | E2: High | F2: 1. Navigate to Register page 2. Select 'Airlines' tab 3. Enter valid Organisation Name, Mobile Number (with country code), Organisation Email, Password, Confirm Password 4. Click 'Sign Up' | G2: Org Name: Rehan Airlines; Country Code: +971; Mobile: 378457834; Email: rehanairlines@yopmail.com; Password: Test@1234 | H2: Registration succeeds; 'Verification Email Sent!' pop-up is displayed showing the masked registered email | J2: Not Executed
A3: TC_REG_AIR_02 | B3: Register - Airlines | C3: Country code dropdown allows selecting a different code | D3: Positive | E3: Medium | F3: 1. On Register - Airlines, click the country code dropdown 2. Select a different country code 3. Enter mobile number 4. Complete remaining fields and Sign Up | G3: Country Code: +91; Mobile: 9876543210 | H3: Selected country code is applied correctly and reflected in the submitted mobile number; registration proceeds normally | J3: Not Executed
A4: TC_REG_AIR_03 | B4: Register - Airlines | C4: Password Show/Hide toggle works on Register page | D4: Positive | E4: Low | F4: 1. Enter a password in the Password field 2. Click the eye icon on Password field 3. Click the eye icon on Confirm Password field | G4: Password: Test@1234 | H4: Masked password text toggles to plain text and back correctly for both Password and Confirm Password fields independently | J4: Not Executed
A5: TC_REG_AIR_04 | B5: Register - Airlines | C5: Login' link on Register page navigates to Login screen | D5: Positive | E5: Low | F5: 1. On Register - Airlines page, click 'Login' link next to 'Already a user ?' | G5: N/A | H5: User is navigated to the Login screen without submitting the registration form | J5: Not Executed
A6: TC_REG_AIR_05 | B6: Register - Airlines | C6: Terms and conditions' link is accessible from Register page | D6: Positive | E6: Low | F6: 1. On Register - Airlines page, click the 'terms and conditions' link at the bottom of the form | G6: N/A | H6: Terms and conditions content/page opens correctly (new tab or in-page), without disrupting entered form data | J6: Not Executed
A7: TC_REG_AIR_06 | B7: Register - Airlines | C7: Switching tabs (Airlines <-> Freight-forwarders) does not carry over entered data | D7: Positive | E7: Medium | F7: 1. On Register page, enter data under 'Airlines' tab 2. Switch to 'Freight-forwarders' tab 3. Switch back to 'Airlines' tab 4. Observe field states | G7: Org Name: Rehan Airlines (entered before switching) | H7: Fields are cleared/reset when switching tabs (or clearly retained per intended design) — behaviour should be consistent and not show stale/mismatched data between tabs | J7: Not Executed | K7: Confirm intended behaviour (clear vs retain) with BA/Dev
A8: TC_REG_AIR_07 | B8: Register - Airlines | C8: Register with empty mandatory fields | D8: Negative | E8: High | F8: 1. Leave one or more mandatory fields empty (Org Name / Mobile / Email / Password / Confirm Password) 2. Click 'Sign Up' | G8: (empty fields) | H8: Inline validation errors are shown for each empty mandatory field; form is not submitted | J8: Not Executed
A9: TC_REG_AIR_08 | B9: Register - Airlines | C9: Register with invalid email format | D9: Negative | E9: High | F9: 1. Enter an invalid email format in Organisation Email 2. Fill remaining fields validly 3. Click 'Sign Up' | G9: Email: rehanairlines@, rehanairlines.com | H9: Inline validation error shown: 'Enter a valid email address'; submission is blocked | J9: Not Executed
A10: TC_REG_AIR_09 | B10: Register - Airlines | C10: Register with an already-registered email | D10: Negative | E10: High | F10: 1. Enter an email that is already registered on the platform 2. Fill remaining fields validly 3. Click 'Sign Up' | G10: Email: rehanairlines@yopmail.com (already registered) | H10: Registration is rejected with a clear error (e.g., 'Email already registered. Please login or use Forgot Password.') | J10: Not Executed
A11: TC_REG_AIR_10 | B11: Register - Airlines | C11: Register with password not meeting policy | D11: Negative | E11: High | F11: 1. Enter a weak password not meeting complexity rules (e.g., too short, missing number/special character) 2. Click 'Sign Up' | G11: Password: test123 | H11: Validation error shown listing the missing password requirements; registration is blocked | J11: Not Executed | K11: Confirm exact password policy (min length, character classes) with Dev/BA
A12: TC_REG_AIR_11 | B12: Register - Airlines | C12: Register with Password and Confirm Password mismatch | D12: Negative | E12: High | F12: 1. Enter a valid password 2. Enter a different value in Confirm Password 3. Click 'Sign Up' | G12: Password: Test@1234; Confirm Password: Test@1235 | H12: Validation error shown: 'Passwords do not match'; registration is blocked | J12: Not Executed
A13: TC_REG_AIR_12 | B13: Register - Airlines | C13: Register with invalid/incomplete mobile number | D13: Negative | E13: Medium | F13: 1. Enter an incomplete or invalid mobile number (too short, contains letters) 2. Fill remaining fields validly 3. Click 'Sign Up' | G13: Mobile: 123, or 37845abc4 | H13: Validation error shown for the mobile number field; registration is blocked | J13: Not Executed
A14: TC_REG_AIR_13 | B14: Register - Airlines | C14: Register with script/SQL injection in Organisation Name field | D14: Negative | E14: High | F14: 1. Enter a script/SQL injection payload in the Organisation Name field 2. Fill remaining fields validly 3. Click 'Sign Up' | G14: Org Name: <script>alert(1)</script> | H14: Input is sanitized/rejected as invalid; no script executes; no unhandled server error is exposed | J14: Not Executed
A15: TC_REG_AIR_14 | B15: Register - Airlines | C15: Register with Organisation Name exceeding maximum length | D15: Negative | E15: Low | F15: 1. Enter an excessively long value (e.g., 300+ characters) in Organisation Name 2. Click 'Sign Up' | G15: Org Name: 300+ character string | H15: Field enforces a sensible maximum length; validation error shown or input is truncated with a warning, not silently accepted | J15: Not Executed | K15: Confirm exact max length with Dev/BA
A16: TC_REG_AIR_15 | B16: Register - Airlines | C16: Duplicate submission via double-click on Sign Up | D16: Negative | E16: Medium | F16: 1. Fill all fields validly 2. Click 'Sign Up' 3. Immediately click 'Sign Up' again before the first request completes | G16: Valid registration data | H16: Only one account/registration request is processed; the duplicate click is idempotently ignored; only one verification email is sent | J16: Not Executed
A17: TC_REG_AIR_16 | B17: Register - Airlines | C17: Register with special characters in mobile number field | D17: Negative | E17: Low | F17: 1. Enter special characters/symbols in the mobile number field (e.g., '37845#834') 2. Click 'Sign Up' | G17: Mobile: 37845#834 | H17: Field rejects non-numeric characters with a validation error; registration is blocked | J17: Not Executed
A18: TC_REG_FF_01 | B18: Register - Freight Forwarders | C18: Register successfully with all valid mandatory fields (Freight-forwarders tab) | D18: Positive | E18: High | F18: 1. Navigate to Register page 2. Select 'Freight-forwarders' tab 3. Enter valid Organisation Name, Mobile Number (with country code), Organisation Email, Password, Confirm Password 4. Click 'Sign Up' | G18: Org Name: Anjali Forwarders; Country Code: +971; Mobile: 501122334; Email: anjaliforwarders@yopmail.com; Password: Test@1234 | H18: Registration succeeds; 'Verification Email Sent!' pop-up is displayed showing the masked registered email, identical behaviour to the Airlines tab | J18: Not Executed
A19: TC_REG_FF_02 | B19: Register - Freight Forwarders | C19: Freight-forwarders tab has identical field set to Airlines tab | D19: Positive | E19: Medium | F19: 1. Select 'Freight-forwarders' tab 2. Compare visible fields against the 'Airlines' tab | G19: N/A | H19: Field set (Organisation Name, Mobile with country code, Organisation Email, Password, Confirm Password) is identical to the Airlines tab, with no additional or missing fields | J19: Not Executed
A20: TC_REG_FF_03 | B20: Register - Freight Forwarders | C20: Password Show/Hide toggle works on Freight-forwarders tab | D20: Positive | E20: Low | F20: 1. Enter a password 2. Click the eye icon on Password and Confirm Password fields | G20: Password: Test@1234 | H20: Masked password text toggles to plain text and back correctly for both fields | J20: Not Executed
A21: TC_REG_FF_04 | B21: Register - Freight Forwarders | C21: Login' link on Freight-forwarders tab navigates to Login screen | D21: Positive | E21: Low | F21: 1. On Register - Freight-forwarders, click 'Login' link | G21: N/A | H21: User is navigated to the Login screen without submitting the registration form | J21: Not Executed
A22: TC_REG_FF_05 | B22: Register - Freight Forwarders | C22: Register with empty mandatory fields (Freight-forwarders) | D22: Negative | E22: High | F22: 1. Leave one or more mandatory fields empty on the Freight-forwarders tab 2. Click 'Sign Up' | G22: (empty fields) | H22: Inline validation errors are shown for each empty mandatory field; form is not submitted | J22: Not Executed
A23: TC_REG_FF_06 | B23: Register - Freight Forwarders | C23: Register with invalid email format (Freight-forwarders) | D23: Negative | E23: High | F23: 1. Enter an invalid email format 2. Fill remaining fields validly 3. Click 'Sign Up' | G23: Email: anjaliforwarders@, anjaliforwarders.com | H23: Inline validation error shown: 'Enter a valid email address'; submission is blocked | J23: Not Executed
A24: TC_REG_FF_07 | B24: Register - Freight Forwarders | C24: Register with an already-registered email (Freight-forwarders) | D24: Negative | E24: High | F24: 1. Enter an email already registered on the platform (under either tab) 2. Fill remaining fields validly 3. Click 'Sign Up' | G24: Email: anjaliforwarders@yopmail.com (already registered) | H24: Registration is rejected with a clear error indicating the email is already in use | J24: Not Executed
A25: TC_REG_FF_08 | B25: Register - Freight Forwarders | C25: Register with Password and Confirm Password mismatch (Freight-forwarders) | D25: Negative | E25: High | F25: 1. Enter a valid password 2. Enter a different value in Confirm Password 3. Click 'Sign Up' | G25: Password: Test@1234; Confirm Password: Test@9999 | H25: Validation error shown: 'Passwords do not match'; registration is blocked | J25: Not Executed
A26: TC_REG_FF_09 | B26: Register - Freight Forwarders | C26: Register with password not meeting policy (Freight-forwarders) | D26: Negative | E26: High | F26: 1. Enter a weak password not meeting complexity rules 2. Click 'Sign Up' | G26: Password: forward1 | H26: Validation error shown listing missing password requirements; registration is blocked | J26: Not Executed
A27: TC_REG_FF_10 | B27: Register - Freight Forwarders | C27: Cross-tab duplicate email check (registered under Airlines, retried under Freight-forwarders) | D27: Negative | E27: High | F27: 1. Register successfully with an email under 'Airlines' tab 2. Switch to 'Freight-forwarders' tab 3. Attempt to register again using the same email | G27: Email: rehanairlines@yopmail.com (already used on Airlines tab) | H27: Registration is rejected as the email is already registered, regardless of which tab (Airlines/Freight-forwarders) it was originally registered under | J27: Not Executed | K27: Confirm whether email uniqueness is enforced globally across both entity types
A28: TC_VERPOPUP_01 | B28: Verification Email Pop-up | C28: Pop-up displays correctly after successful registration | D28: Positive | E28: High | F28: 1. Complete registration with valid data on either Airlines or Freight-forwarders tab 2. Observe the pop-up shown | G28: Email: rehanairlines@yopmail.com | H28: Pop-up displays with heading 'Verification Email Sent!' and message referencing the masked registered email (e.g., 'reha****@yopmail.com'), along with a 'Close' button and a 'Resend' link | J28: Not Executed
A29: TC_VERPOPUP_02 | B29: Verification Email Pop-up | C29: Close' button dismisses the pop-up | D29: Positive | E29: Medium | F29: 1. On the Verification Email pop-up, click 'Close' (X icon or Close button) | G29: N/A | H29: Pop-up closes; user remains on/returns to the Register page underneath | J29: Not Executed
A30: TC_VERPOPUP_03 | B30: Verification Email Pop-up | C30: Verification email is actually received in the inbox | D30: Positive | E30: High | F30: 1. Complete registration 2. Check the registered email inbox (and spam folder) | G30: Email: rehanairlines@yopmail.com | H30: A verification email is received within a reasonable time, containing a working 'Verify' link/button | J30: Not Executed
A31: TC_VERPOPUP_04 | B31: Verification Email Pop-up | C31: Resend' link/button does not trigger a new verification email (confirmed defect) | D31: Negative | E31: High | F31: 1. On the Verification Email pop-up, click 'Resend' 2. Wait and check the registered inbox for a new email | G31: Email: rehanairlines@yopmail.com | H31: Clicking 'Resend' should trigger and deliver a new verification email to the registered address, with user-facing confirmation (e.g., toast/message) that it was resent | J31: Not Executed | K31: Confirmed defect from the recording — Resend functionality is not working. Recommend logging this as a bug separately; this test case documents it for tracking/regression purposes
A32: TC_VERPOPUP_05 | B32: Verification Email Pop-up | C32: Repeated clicks on non-functional 'Resend' do not cause errors or duplicate emails | D32: Negative | E32: Medium | F32: 1. Click 'Resend' multiple times in succession | G32: N/A | H32: Even though Resend is not functioning, repeated clicks should not throw an unhandled error, crash the pop-up, or queue multiple duplicate emails once the feature is fixed | J32: Not Executed | K32: Re-verify once the Resend defect (TC_VERPOPUP_04) is fixed
A33: TC_VERPOPUP_06 | B33: Verification Email Pop-up | C33: Pop-up email masking correctly obscures the registered email | D33: Positive | E33: Low | F33: 1. Complete registration 2. Observe the masked email format shown in the pop-up | G33: Email: rehanairlines@yopmail.com | H33: Email is masked in a consistent, readable pattern (e.g., 'reha****@yopmail.com') without exposing the full address | J33: Not Executed
A34: TC_VERPOPUP_07 | B34: Verification Email Pop-up | C34: Closing the pop-up and refreshing does not re-trigger a duplicate verification email | D34: Negative | E34: Medium | F34: 1. Complete registration 2. Close the pop-up 3. Refresh the Register/landing page | G34: N/A | H34: Refreshing the page after closing the pop-up does not resend or duplicate the verification email automatically | J34: Not Executed
A35: TC_VERPOPUP_08 | B35: Verification Email Pop-up | C35: Pop-up wording matches specified text exactly | D35: Positive | E35: Low | F35: 1. Complete registration 2. Read the exact pop-up message text | G35: N/A | H35: Message reads exactly: "We've sent a verification email to your [masked email]. Please verify your account to continue." with the note about checking spam folder / resending | J35: Not Executed
A36: TC_EMAILVER_01 | B36: Email Verification Link | C36: Clicking Verify link in the email successfully verifies the account | D36: Positive | E36: High | F36: 1. Open the verification email received after registration 2. Click the 'Verify' button/link inside it | G36: Email: rehanairlines@yopmail.com | H36: User is taken to a confirmation page displaying 'Your business e-mail has been verified' with a 'Log back in' button; account is marked as verified in the system | J36: Not Executed
A37: TC_EMAILVER_02 | B37: Email Verification Link | C37: Log back in' button navigates to the Login screen | D37: Positive | E37: Medium | F37: 1. After successful email verification, click 'Log back in' on the confirmation page | G37: N/A | H37: User is navigated to the Login screen | J37: Not Executed
A38: TC_EMAILVER_03 | B38: Email Verification Link | C38: Verification link works only once (cannot be reused) | D38: Negative | E38: Medium | F38: 1. Click the Verify link once (account gets verified) 2. Click the same Verify link again from the email | G38: Same verification link, reused | H38: Second click either shows an 'already verified' message or safely redirects to Login, without re-processing or erroring out | J38: Not Executed
A39: TC_EMAILVER_04 | B39: Email Verification Link | C39: Expired verification link is handled gracefully | D39: Negative | E39: Medium | F39: 1. Wait until the verification link's validity window has passed (per configured expiry) 2. Click the expired link | G39: Expired verification link | H39: A clear 'This verification link has expired' message is shown, with guidance to request a new one (e.g., via Resend, once that is fixed) or contact support | J39: Not Executed | K39: Confirm exact link expiry duration with Dev/BA; also dependent on Resend being functional (TC_VERPOPUP_04)
A40: TC_EMAILVER_05 | B40: Email Verification Link | C40: Tampered/invalid verification link is rejected | D40: Negative | E40: High | F40: 1. Modify the verification token/link (e.g., change a character in the URL) 2. Attempt to open the tampered link | G40: Tampered verification URL | H40: System rejects the invalid token with an appropriate error message; account is not marked as verified | J40: Not Executed
A41: TC_EMAILVER_06 | B41: Email Verification Link | C41: Verifying via link on a different browser/device than registration still succeeds | D41: Positive | E41: Low | F41: 1. Register on Device/Browser A 2. Open the verification email and click Verify on Device/Browser B | G41: N/A | H41: Verification succeeds regardless of which browser/device the link is opened on, since verification is tied to the account/token, not the session | J41: Not Executed

Sheet Login
A1: Test Case ID | B1: Screen | C1: Test Case Description | D1: Test Case Type | E1: Priority | F1: Test Steps | G1: Test Data | H1: Expected Result | I1: Actual Result | J1: Status | K1: Remarks
A2: TC_LOGIN_01 | B2: Login | C2: Login with valid, verified credentials | D2: Positive | E2: High | F2: 1. Navigate to Login page 2. Enter registered and verified email and correct password 3. Click 'Login' 4. Complete OTP verification on the OTP screen that follows (see 'Login - OTP Verification' screen) | G2: Email: rehanairlines@yopmail.com; Password: Test@1234 | H2: Credentials are accepted and the OTP screen is displayed; after successful OTP verification, user is redirected to the Onboarding screen (since onboarding is not yet completed for a newly registered account) | I2: After entering the correct OTP, the user is successfully authenticated, and the application navigates to the Onboarding page. | J2: Pass
A3: TC_LOGIN_02 | B3: Login | C3: Create an Account' link navigates to Register page | D3: Positive | E3: Low | F3: 1. On Login page, click 'Create an Account' link | G3: N/A | H3: User is navigated to the Register page | I3: Upon clicking the Create an Account button, the application successfully navigates to the Registration page. | J3: Pass
A4: TC_LOGIN_03 | B4: Login | C4: Password Show/Hide toggle works on Login page | D4: Positive | E4: Low | F4: 1. Enter a password in the Password field 2. Click the eye icon | G4: Password: Test@1234 | H4: Masked password text toggles to plain text and back correctly | I4: Upon clicking the **Eye** icon, the password is displayed in plain text. Clicking the **Eye** icon again hides the password by masking it. | J4: Pass
A5: TC_LOGIN_04 | B5: Login | C5: Forgot Password?' link navigates to password recovery flow | D5: Positive | E5: Low | F5: 1. On Login page, click 'Forgot Password?' link | G5: N/A | H5: User is navigated to the Forgot Password screen | I5: Upon clicking the forgot password button the application successfullly navigates to the forgot password page. | J5: Pass
A6: TC_LOGIN_05 | B6: Login | C6: Login redirects a fully onboarded user directly to Dashboard (not Onboarding) | D6: Positive | E6: High | F6: 1. Login with an account that has already completed onboarding 2. Complete the OTP verification step that follows | G6: Email: onboarded.user@yopmail.com | H6: After OTP verification succeeds, user is redirected directly to the Dashboard; onboarding flow is not shown again | I6: Once the onboarding done, after OTP verification succeeds user redirect directly to the dashboard page. | J6: Pass
A7: TC_LOGIN_06 | B7: Login | C7: Login with incorrect password | D7: Negative | E7: High | F7: 1. Enter a registered, verified email 2. Enter an incorrect password 3. Click 'Login' | G7: Email: rehanairlines@yopmail.com; Password: WrongPass1 | H7: Login is rejected; error message shown: 'Invalid email or password'; user remains on Login page | I7: Login is rejected and displayed error message "Invalid credentials. Please check your email and password". | J7: Pass
A8: TC_LOGIN_07 | B8: Login | C8: Login with unregistered email | D8: Negative | E8: High | F8: 1. Enter an email that has not been registered 2. Enter any password 3. Click 'Login' | G8: Email: unknown.user@yopmail.com | H8: Login is rejected with a generic error ('Invalid email or password') without confirming whether the email exists | I8: Login is rejected and displayed error message "Invalid credentials. Please check your email and password". | J8: Pass
A9: TC_LOGIN_08 | B9: Login | C9: Login with empty Email/Password fields | D9: Negative | E9: High | F9: 1. Leave Registered Email and/or Password fields empty 2. Click 'Login' | G9: (empty fields) | H9: Inline validation errors shown ('Email is required', 'Password is required'); login is not attempted | I9: Without entering email ID and password the user can't able to click the login button. | J9: Pass
A10: TC_LOGIN_09 | B10: Login | C10: Repeated failed login attempts are throttled/locked | D10: Negative | E10: Medium | F10: 1. Attempt login with an incorrect password 5+ times consecutively | G10: Email: rehanairlines@yopmail.com; Password: incorrect (repeated) | H10: After a defined threshold, further attempts are blocked/throttled with an appropriate message | I10: Login is rejected and displayed error message "Invalid credentials. Please check your email and password". | J10: Pass
A11: TC_LOGIN_UNVER_01 | B11: Login - Unverified Account | C11: Login attempt with registered but unverified account displays the verification pop-up | D11: Positive | E11: High | F11: 1. Register a new account but do not click the verification link in the email 2. Attempt to login with that account's credentials | G11: Email: unverified.user@yopmail.com; Password: Test@1234 | H11: Login is not completed; the verification pop-up (e.g., 'Please verify your account to continue') is displayed again, prompting the user to verify before proceeding | I11: Login is rejected and displayed error message "Invalid credentials. Please check your email and password". | J11: Fail
A12: TC_LOGIN_UNVER_02 | B12: Login - Unverified Account | C12: Resend' on the re-triggered verification pop-up during login also does not work | D12: Negative | E12: High | F12: 1. Trigger the verification pop-up by attempting to login with an unverified account 2. Click 'Resend' on this pop-up | G12: Email: unverified.user@yopmail.com | H12: Clicking 'Resend' should trigger and deliver a new verification email | I12: Login is rejected and displayed error message "Invalid credentials. Please check your email and password". | J12: Fail
A13: TC_LOGIN_UNVER_03 | B13: Login - Unverified Account | C13: User can still complete verification via the original email and then log in successfully | D13: Positive | E13: High | F13: 1. After the verification pop-up reappears at login, go to the registered email inbox (using the original verification email, since Resend is broken) 2. Click the original Verify link 3. Return and login again | G13: Email: unverified.user@yopmail.com | H13: Verification succeeds using the original email's link; subsequent login attempt succeeds and navigates to Onboarding | I13: Once the account verification is completed, the user is able to log in successfully, and the application navigates to the **Onboarding** page. | J13: Pass
... A24: TC_LOGIN_OTP_09 | B24: Login - OTP Verification | C24: Expired OTP is rejected | D24: Negative | E24: High | F24: 1. Wait until the OTP's validity window has passed 2. Enter the previously valid OTP 3. Click Verify | G24: Expired OTP: 483920 | H24: Error message shown ('OTP expired, please resend'); Verify is blocked; login is not completed | I24: When an expired OTP is entered and the Verify button is clicked, the OTP verification is rejected, and the application displays the error message: "OTP has expired. Please request a new one." | J24: Pass
A25: TC_LOGIN_OTP_10 | B25: Login - OTP Verification | C25: Repeated incorrect OTP attempts lock further attempts | D25: Negative | E25: High | F25: 1. Enter an incorrect OTP 5 times consecutively 2. Attempt a 6th entry | G25: Incorrect OTP entered repeatedly | H25: After the defined threshold, further OTP attempts are blocked/locked with a message; user must request a new OTP via Resend | I25: When an invalid OTP is entered and the Verify button is clicked repeatedly (up to five times), the application consistently displays the error message: "Incorrect OTP. Please try again." | J25: Pass | K25: Confirm exact lockout threshold and cooldown period with Dev/BA
A26: TC_LOGIN_OTP_11 | B26: Login - OTP Verification | C26: Resend is disabled while the countdown timer is still active | D26: Negative | E26: Medium | F26: 1. Attempt to click 'Resend OTP' before the countdown reaches 00:00 | G26: N/A | H26: Resend action is disabled/not clickable until the countdown timer reaches zero | I26: Once the OTP timer expires, the Resend OTP button is enabled, allowing the user to request a new OTP. | J26: Pass
A27: TC_LOGIN_OTP_12 | B27: Login - OTP Verification | C27: Verify is blocked with an incomplete OTP | D27: Negative | E27: Medium | F27: 1. Enter only part of the OTP 2. Attempt to click Verify | G27: OTP: 483 (incomplete) | H27: Verify remains blocked or shows a validation message ('Please enter all digits'); login is not completed | I27: The Verify button remains disabled until the user enters all six OTP digits. Once a six-digit OTP is entered, the Verify button is enabled. | J27: Pass
A28: TC_LOGIN_OTP_13 | B28: Login - OTP Verification | C28: Non-numeric characters are rejected in OTP boxes | D28: Negative | E28: Medium | F28: 1. Attempt to type letters or special characters into an OTP box | G28: Input: 'a', '#', ' ' | H28: Non-numeric characters are not accepted; only digits 0-9 can be entered | I28: The OTP input field accepts only numeric characters. Non-numeric characters are rejected and cannot be entered into the OTP field. | J28: Pass
A29: TC_LOGIN_OTP_14 | B29: Login - OTP Verification | C29: Closing/abandoning the OTP screen requires re-login and a fresh OTP | D29: Negative | E29: Medium | F29: 1. Reach the OTP screen after entering correct credentials 2. Close the browser tab/navigate away without completing OTP 3. Return and log in again | G29: Email: rehanairlines@yopmail.com | H29: The prior OTP is invalidated; the user must re-enter credentials and receive/enter a fresh OTP; the abandoned session does not grant access | I29: After closing the OTP Verification pop-up and attempting to log in again before the previous OTP expires, the existing OTP timer continues from where it left off, and no new OTP is generated. Once the previous OTP expires, logging in again generates a new OTP, and a new OTP timer starts. | J29: Pass
A30: TC_LOGIN_OTP_15 | B30: Login - OTP Verification | C30: OTP is tied to the correct user/session and cannot be reused across accounts | D30: Negative | E30: High | F30: 1. Trigger an OTP for Account A 2. Attempt to use Account A's OTP while logging in as Account B | G30: Account A's OTP entered during Account B's login attempt | H30: OTP is rejected as invalid for Account B; OTPs are strictly scoped to the account/session that generated them | I30: The OTP is rejected as invalid when entered for Account B, and the application displays the appropriate validation error. The OTP is accepted only for the account/session in which it was generated. | J30: Pass
A31: TC_ONBOARD_REDIR_01 | B31: Post-Login Onboarding Redirect | C31: Newly verified and logged-in user is redirected to the Onboarding screen | D31: Positive | E31: High | F31: 1. Complete registration and email verification 2. Login with the verified account 3. Complete OTP verification | G31: Email: rehanairlines@yopmail.com | H31: User is redirected to the Onboarding screen (Business Details / Step 1) immediately after OTP verification, since onboarding has not yet been completed | I31: After successful OTP verification, the user is redirected to the Onboarding screen (Business Details – Step 1), as the onboarding process has not yet been completed. | J31: Pass
A32: TC_ONBOARD_REDIR_02 | B32: Post-Login Onboarding Redirect | C32: Onboarding redirect works consistently for both Airlines and Freight-forwarders registrations | D32: Positive | E32: Medium | F32: 1. Complete registration, verification, login, and OTP verification separately for an Airlines account and a Freight-forwarders account 2. Observe the post-OTP redirect for each | G32: Airlines account + Freight-forwarders account | H32: Both account types are redirected to the Onboarding screen consistently after OTP verification on their first login, with no difference in behaviour based on entity type | I32: After successful OTP verification on the first login, both account types are consistently redirected to the Onboarding screen, with identical behavior regardless of the selected entity type. | J32: Pass
A33: TC_ONBOARD_REDIR_03 | B33: Post-Login Onboarding Redirect | C33: Attempting to access Dashboard directly before completing onboarding redirects back to Onboarding | D33: Negative | E33: High | F33: 1. Login with a newly verified account (onboarding incomplete) 2. Directly navigate to the Dashboard URL | G33: URL: /dashboard | H33: User is redirected back to the Onboarding screen; Dashboard content is not accessible until onboarding is complete | I33: The user is redirected back to the Onboarding screen, and the Dashboard remains inaccessible until the onboarding process is completed. | J33: Pass
A34: TC_ONBOARD_REDIR_04 | B34: Post-Login Onboarding Redirect | C34: Logging out and back in during incomplete onboarding resumes at the correct step | D34: Negative | E34: Medium | F34: 1. Login and start onboarding (complete Step 1) 2. Logout 3. Login again with the same account | G34: Email: rehanairlines@yopmail.com | H34: User is redirected back into the Onboarding flow at the correct incomplete step, with previously entered data intact | I34: The user is redirected back to the correct incomplete step in the Onboarding flow, and all previously entered data is retained successfully. | J34: Pass

Sheet Forgot Password
A1: Test Case ID | B1: Screen | C1: Test Case Description | D1: Test Case Type | E1: Priority | F1: Test Steps | G1: Test Data | H1: Expected Result | I1: Actual Result | J1: Status | K1: Remarks
A2: TC_FP_EMAIL_01 | B2: Forgot Password - Email | C2: Submit a valid registered email successfully | D2: Positive | E2: High | F2: 1. Navigate to Login page 2. Click 'Forgot Password?' 3. Enter a valid registered email 4. Click 'Submit' | G2: Email: produbaiairlines@yopmail.com | H2: Request is accepted; user is navigated to the OTP verification screen; an OTP is sent to the registered email | J2: Not Executed
A3: TC_FP_EMAIL_02 | B3: Forgot Password - Email | C3: Back to Login' link navigates to Login screen | D3: Positive | E3: Low | F3: 1. On the Forgot Password screen, click 'Back to Login' | G3: N/A | H3: User is navigated to the Login screen without submitting the form | J3: Not Executed
A4: TC_FP_EMAIL_03 | B4: Forgot Password - Email | C4: Submit button is enabled once a syntactically valid email is entered | D4: Positive | E4: Low | F4: 1. Enter a valid email format 2. Observe the Submit button state | G4: Email: test@yopmail.com | H4: Submit button is enabled/clickable | J4: Not Executed
A5: TC_FP_EMAIL_04 | B5: Forgot Password - Email | C5: Page heading and instructions display correctly | D5: Positive | E5: Low | F5: 1. Navigate to the Forgot Password screen 2. Read the heading and instruction text | G5: N/A | H5: Heading reads 'Forgot password' with instruction text: 'Please enter your registered email address below. We'll send you a link to reset your password.' | J5: Not Executed
A6: TC_FP_EMAIL_05 | B6: Forgot Password - Email | C6: Submit with an unregistered email | D6: Negative | E6: High | F6: 1. Enter an email that is not registered on the platform 2. Click 'Submit' | G6: Email: unknown.user@yopmail.com | H6: A generic message is shown ('If this email is registered, you will receive a reset link/OTP') without confirming whether the email exists; no OTP is actually sent | J6: Not Executed | K6: Confirm actual behaviour — recording only showed the registered-email happy path
A7: TC_FP_EMAIL_06 | B7: Forgot Password - Email | C7: Submit with an empty email field | D7: Negative | E7: High | F7: 1. Leave the Registered Email field empty 2. Click 'Submit' | G7: (empty) | H7: Inline validation error shown: 'Email is required'; form is not submitted | J7: Not Executed
A8: TC_FP_EMAIL_07 | B8: Forgot Password - Email | C8: Submit with an invalid email format | D8: Negative | E8: High | F8: 1. Enter a malformed email (missing '@', missing domain, no dot) 2. Click 'Submit' | G8: Email: produbaiairlines, produbaiairlines@domain | H8: Inline validation error shown: 'Enter a valid email address'; Submit is blocked | J8: Not Executed
A9: TC_FP_EMAIL_08 | B9: Forgot Password - Email | C9: Repeated rapid submissions for the same email are rate-limited | D9: Negative | E9: Medium | F9: 1. Submit the Forgot Password request for the same email 5+ times within a short window | G9: Email: produbaiairlines@yopmail.com | H9: After a defined threshold, further requests are throttled/blocked with a 'Please try again later' message | J9: Not Executed
A10: TC_FP_EMAIL_09 | B10: Forgot Password - Email | C10: Script/SQL injection attempt in the email field | D10: Negative | E10: High | F10: 1. Enter a script/SQL injection payload in the email field 2. Click 'Submit' | G10: Email: <script>alert(1)</script>@test.com | H10: Input is rejected/sanitized as invalid email format; no script executes; no server error is exposed | J10: Not Executed
A11: TC_FP_EMAIL_10 | B11: Forgot Password - Email | C11: Leading/trailing spaces in the email field | D11: Negative | E11: Low | F11: 1. Enter an email with leading/trailing spaces 2. Click 'Submit' | G11: produbaiairlines@yopmail.com ' | H11: Whitespace is trimmed automatically and processed correctly, or a clear validation error is shown consistently | J11: Not Executed
A12: TC_FP_OTP_01 | B12: OTP Verification | C12: Correct OTP entered successfully verifies and proceeds | D12: Positive | E12: High | F12: 1. Retrieve the OTP from the registered email inbox 2. Enter all digits correctly on the OTP screen 3. Click 'Verify' | G12: OTP received via yopmail inbox | H12: OTP is verified successfully; user is navigated to the 'Change your password' screen | J12: Not Executed
A13: TC_FP_OTP_02 | B13: OTP Verification | C13: Pasting a full OTP auto-fills all boxes correctly | D13: Positive | E13: Medium | F13: 1. Copy the OTP from the received email 2. Paste into the first OTP box | G13: Pasted OTP value | H13: All OTP boxes are auto-filled correctly in order; Verify button becomes enabled | J13: Not Executed
A14: TC_FP_OTP_03 | B14: OTP Verification | C14: X' close icon dismisses the OTP modal | D14: Positive | E14: Low | F14: 1. On the OTP screen, click the 'X' icon | G14: N/A | H14: OTP modal closes; user returns to the Forgot Password (email entry) screen underneath | J14: Not Executed
A15: TC_FP_OTP_04 | B15: OTP Verification | C15: Verify button enabled only once all OTP digits are entered | D15: Positive | E15: Medium | F15: 1. Enter fewer than the required digits 2. Observe Verify button state 3. Enter the final digit 4. Observe Verify button state | G15: OTP: partial then complete | H15: Verify button is disabled with partial input and becomes enabled only once all digits are entered | J15: Not Executed
A16: TC_FP_OTP_05 | B16: OTP Verification | C16: Auto-focus moves to next box as each digit is entered | D16: Positive | E16: Low | F16: 1. Type a digit in the first OTP box 2. Observe cursor/focus position | G16: Single digit entry | H16: Focus automatically advances to the next box after each digit is entered | J16: Not Executed
A17: TC_FP_OTP_06 | B17: OTP Verification | C17: Resend OTP after timer expiry sends a new OTP | D17: Positive | E17: Medium | F17: 1. Wait for the resend countdown to reach 00:00 2. Click 'Resend OTP' | G17: N/A | H17: A new OTP is sent to the registered email; countdown resets; the previous OTP is invalidated | J17: Not Executed | K17: Not shown in this recording — verify separately; confirm this is unaffected by the Resend defect confirmed on the Register verification pop-up
A18: TC_FP_OTP_07 | B18: OTP Verification | C18: Incorrect OTP is rejected | D18: Negative | E18: High | F18: 1. Enter an incorrect OTP 2. Click 'Verify' | G18: Incorrect OTP entered | H18: Error message shown ('Incorrect OTP, please try again'); user remains on the OTP screen | J18: Not Executed
A19: TC_FP_OTP_08 | B19: OTP Verification | C19: Expired OTP is rejected | D19: Negative | E19: High | F19: 1. Wait until the OTP's validity window has passed 2. Enter the previously valid OTP 3. Click 'Verify' | G19: Expired OTP | H19: Error message shown ('OTP expired, please resend'); Verify is blocked | J19: Not Executed | K19: Confirm exact OTP validity duration with Dev/BA
A20: TC_FP_OTP_09 | B20: OTP Verification | C20: Repeated incorrect OTP attempts lock further attempts | D20: Negative | E20: High | F20: 1. Enter an incorrect OTP 5 times consecutively 2. Attempt a 6th entry | G20: Incorrect OTP entered repeatedly | H20: After a defined threshold, further attempts are blocked/locked with a message; user must request a new OTP via Resend | J20: Not Executed | K20: Confirm exact lockout threshold with Dev/BA
A21: TC_FP_OTP_10 | B21: OTP Verification | C21: Resend is disabled while the countdown timer is active | D21: Negative | E21: Medium | F21: 1. Attempt to click 'Resend OTP' before the countdown reaches 00:00 | G21: N/A | H21: Resend action is disabled/not clickable until the countdown reaches zero | J21: Not Executed
A22: TC_FP_OTP_11 | B22: OTP Verification | C22: Verify is blocked with an incomplete OTP | D22: Negative | E22: Medium | F22: 1. Enter only part of the OTP 2. Attempt to click 'Verify' | G22: Incomplete OTP | H22: Verify remains blocked or shows a validation message; the request is not submitted | J22: Not Executed
A23: TC_FP_OTP_12 | B23: OTP Verification | C23: Non-numeric characters are rejected in OTP boxes | D23: Negative | E23: Medium | F23: 1. Attempt to type letters or special characters into an OTP box | G23: Input: 'a', '#', ' ' | H23: Non-numeric characters are not accepted; only digits 0-9 can be entered | J23: Not Executed
A24: TC_FP_OTP_13 | B24: OTP Verification | C24: Closing the OTP modal and restarting Forgot Password invalidates the earlier OTP | D24: Negative | E24: Medium | F24: 1. Close the OTP modal 2. Restart the Forgot Password flow for the same email 3. Attempt to use the original OTP | G24: Original OTP | H24: The original OTP no longer works; only the newly generated OTP is valid | J24: Not Executed
A25: TC_FP_CHANGEPW_01 | B25: Change Password | C25: Valid new password with matching confirm succeeds | D25: Positive | E25: High | F25: 1. Enter a valid new password 2. Enter the same value in Confirm Password 3. Click 'Change Password' | G25: New Password: Test123@ | H25: Password is updated successfully; confirmation shown; user is redirected to Login | J25: Not Executed
A26: TC_FP_CHANGEPW_02 | B26: Change Password | C26: Show/Hide password toggle works for both fields | D26: Positive | E26: Low | F26: 1. Enter a value in the new password field 2. Click the eye icon 3. Repeat for Confirm Password | G26: Password: Test123@ | H26: Each field's masked text toggles to plain text and back independently when its eye icon is clicked | J26: Not Executed
A27: TC_FP_CHANGEPW_03 | B27: Change Password | C27: Login' link on Change Password screen navigates to Login | D27: Positive | E27: Low | F27: 1. Click the 'Login' link next to 'Back to Login ?' | G27: N/A | H27: User is navigated to the Login screen without changing the password | J27: Not Executed
A28: TC_FP_CHANGEPW_04 | B28: Change Password | C28: New password and confirm password mismatch | D28: Negative | E28: High | F28: 1. Enter a valid new password 2. Enter a different value in Confirm Password 3. Click 'Change Password' | G28: New Password: Test123@; Confirm: Test456@ | H28: Validation error shown ('Passwords do not match'); password is not updated | J28: Not Executed
A29: TC_FP_CHANGEPW_05 | B29: Change Password | C29: Submit with both fields empty | D29: Negative | E29: High | F29: 1. Leave both password fields empty 2. Click 'Change Password' | G29: (empty, empty) | H29: Inline validation errors shown for both fields; form is not submitted | J29: Not Executed
A30: TC_FP_CHANGEPW_06 | B30: Change Password | C30: Password below minimum length | D30: Negative | E30: High | F30: 1. Enter a password shorter than the minimum required length in both fields 2. Click 'Change Password' | G30: New Password: Ab1@ | H30: Validation error shown stating the minimum length requirement; password is not updated | J30: Not Executed | K30: Confirm exact minimum length policy with BA/Dev
A31: TC_FP_CHANGEPW_07 | B31: Change Password | C31: Password missing required character types | D31: Negative | E31: High | F31: 1. Enter a password missing a required character category (e.g., no special character or number) 2. Click 'Change Password' | G31: New Password: producdubai | H31: Validation error shown listing the missing requirement(s); password is not updated | J31: Not Executed | K31: Confirm exact password complexity policy with BA/Dev
A32: TC_FP_CHANGEPW_08 | B32: Change Password | C32: Reusing the previous password | D32: Negative | E32: Medium | F32: 1. Enter the account's current password as the 'new' password in both fields 2. Click 'Change Password' | G32: Current password reused as new password | H32: Error shown ('New password must be different from the current password'); update is blocked | J32: Not Executed | K32: Confirm whether password-reuse restriction is part of FlexCapPro's policy
A33: TC_FP_CHANGEPW_09 | B33: Change Password | C33: Session/reset token expiry between OTP verification and password change | D33: Negative | E33: Medium | F33: 1. Verify OTP successfully 2. Wait beyond the reset-session expiry window 3. Attempt to change the password | G33: N/A | H33: System rejects the request with a session-expired message; user must restart the Forgot Password flow | J33: Not Executed | K33: Confirm exact session validity duration with Dev
A34: TC_FP_CHANGEPW_10 | B34: Change Password | C34: Direct access to Change Password screen without completing OTP verification | D34: Negative | E34: High | F34: 1. Attempt to directly navigate to the Change Password screen URL/state without verifying an OTP first | G34: N/A | H34: Access is blocked/redirected to the Forgot Password screen; password cannot be changed without prior OTP verification | J34: Not Executed

Sheet Supplier Onboarding
A1: Test Case ID | B1: Screen | C1: Test Case Description | D1: Test Case Type | E1: Priority | F1: Test Steps | G1: Test Data | H1: Expected Result | I1: Actual Result | J1: Status | K1: Remarks
A2: TC_BIZ_NAME_01 | B2: Business Details - Business Info | C2: Enter valid value in 'Organisation Name' field | D2: Positive | E2: Medium | F2: 1. Navigate to the step containing 'Organisation Name' 2. Enter a valid value 3. Proceed / Save | G2: Organisation Name: Rehan Airlines | H2: Value is accepted; no validation error is shown for 'Organisation Name' | J2: Not Executed
A3: TC_BIZ_NAME_02 | B3: Business Details - Business Info | C3: Leave 'Organisation Name' empty and attempt to proceed | D3: Negative | E3: Medium | F3: 1. Leave 'Organisation Name' field empty 2. Click 'Save and Proceed' | G3: Organisation Name: (empty) | H3: Inline validation error shown: 'Organisation Name is required'; user cannot proceed to the next step | J3: Not Executed
A4: TC_BIZ_NAME_03 | B4: Business Details - Business Info | C4: Enter script/special-character injection in 'Organisation Name' | D4: Negative | E4: Medium | F4: 1. Enter a script/SQL injection payload in 'Organisation Name' 2. Attempt to proceed | G4: Organisation Name: <script>alert(1)</script> | H4: Input is sanitized/rejected as invalid; no script executes; no unhandled server error is exposed | J4: Not Executed
A5: TC_BIZ_NAME_04 | B5: Business Details - Business Info | C5: Enter value exceeding maximum length in 'Organisation Name' | D5: Negative | E5: Low | F5: 1. Enter an excessively long value (e.g., 300+ characters) in 'Organisation Name' 2. Attempt to proceed | G5: Organisation Name: 300+ character string | H5: Field enforces a sensible maximum length; validation error shown or input blocked beyond the limit | J5: Not Executed | K5: Assumed — confirm exact validation rule/format with BA/Dev (not fully visible in recording)
A6: TC_BIZ_TRADE_01 | B6: Business Details - Business Info | C6: Enter valid alphanumeric value in 'Trade/RE Reference Number' | D6: Positive | E6: Medium | F6: 1. Navigate to the step containing 'Trade/RE Reference Number' 2. Enter a valid value matching the expected format 3. Proceed / Save | G6: Trade/RE Reference Number: RE7437853878348 | H6: Value is accepted; no validation error is shown for 'Trade/RE Reference Number' | J6: Not Executed
A7: TC_BIZ_TRADE_02 | B7: Business Details - Business Info | C7: Leave 'Trade/RE Reference Number' empty and attempt to proceed | D7: Negative | E7: Medium | F7: 1. Leave 'Trade/RE Reference Number' field empty 2. Click 'Save and Proceed' | G7: Trade/RE Reference Number: (empty) | H7: Inline validation error shown: 'Trade/RE Reference Number is required'; user cannot proceed | J7: Not Executed
A8: TC_BIZ_TRADE_03 | B8: Business Details - Business Info | C8: Enter value with invalid format/characters in 'Trade/RE Reference Number' | D8: Negative | E8: Medium | F8: 1. Enter a value that does not match the expected format for 'Trade/RE Reference Number' (e.g., RE@#$123) 2. Attempt to proceed | G8: Trade/RE Reference Number: RE@#$123 | H8: Validation error shown indicating the expected format for 'Trade/RE Reference Number'; user cannot proceed with invalid input | J8: Not Executed | K8: Assumed — confirm exact validation rule/format with BA/Dev (not fully visible in recording)
A9: TC_BIZ_TRADE_04 | B9: Business Details - Business Info | C9: Enter duplicate/already-used value in 'Trade/RE Reference Number' (if uniqueness applies) | D9: Negative | E9: Low | F9: 1. Enter a value for 'Trade/RE Reference Number' that is already registered/used elsewhere in the system 2. Attempt to proceed | G9: Trade/RE Reference Number: duplicate value | H9: Validation error shown if uniqueness is enforced for this field; otherwise value is accepted normally | J9: Not Executed | K9: Assumed — confirm exact validation rule/format with BA/Dev (not fully visible in recording)
A10: TC_BIZ_TRN_01 | B10: Business Details - Business Info | C10: Enter valid alphanumeric value in 'Tax Registration Number (TRN)' | D10: Positive | E10: Medium | F10: 1. Navigate to the step containing 'Tax Registration Number (TRN)' 2. Enter a valid value matching the expected format 3. Proceed / Save | G10: Tax Registration Number (TRN): REH93949234 | H10: Value is accepted; no validation error is shown for 'Tax Registration Number (TRN)' | J10: Not Executed
A11: TC_BIZ_TRN_02 | B11: Business Details - Business Info | C11: Leave 'Tax Registration Number (TRN)' empty and attempt to proceed | D11: Negative | E11: Medium | F11: 1. Leave 'Tax Registration Number (TRN)' field empty 2. Click 'Save and Proceed' | G11: Tax Registration Number (TRN): (empty) | H11: Inline validation error shown: 'Tax Registration Number (TRN) is required'; user cannot proceed | J11: Not Executed
A12: TC_BIZ_TRN_03 | B12: Business Details - Business Info | C12: Enter value with invalid format/characters in 'Tax Registration Number (TRN)' | D12: Negative | E12: Medium | F12: 1. Enter a value that does not match the expected format for 'Tax Registration Number (TRN)' (e.g., REH939) 2. Attempt to proceed | G12: Tax Registration Number (TRN): REH939 | H12: Validation error shown indicating the expected format for 'Tax Registration Number (TRN)'; user cannot proceed with invalid input | J12: Not Executed | K12: Assumed — confirm exact validation rule/format with BA/Dev (not fully visible in recording)
A13: TC_BIZ_TRN_04 | B13: Business Details - Business Info | C13: Enter duplicate/already-used value in 'Tax Registration Number (TRN)' (if uniqueness applies) | D13: Negative | E13: Low | F13: 1. Enter a value for 'Tax Registration Number (TRN)' that is already registered/used elsewhere in the system 2. Attempt to proceed | G13: Tax Registration Number (TRN): duplicate value | H13: Validation error shown if uniqueness is enforced for this field; otherwise value is accepted normally | J13: Not Executed | K13: Assumed — confirm exact validation rule/format with BA/Dev (not fully visible in recording)
A14: TC_BIZ_ADDR1_01 | B14: Business Details - Business Info | C14: Enter valid value in 'Address Line 1' field | D14: Positive | E14: Medium | F14: 1. Navigate to the step containing 'Address Line 1' 2. Enter a valid value 3. Proceed / Save | G14: Address Line 1: PO-47 Street, Haba Mall, 5th floor | H14: Value is accepted; no validation error is shown for 'Address Line 1' | J14: Not Executed
A15: TC_BIZ_ADDR1_02 | B15: Business Details - Business Info | C15: Leave 'Address Line 1' empty and attempt to proceed | D15: Negative | E15: Medium | F15: 1. Leave 'Address Line 1' field empty 2. Click 'Save and Proceed' | G15: Address Line 1: (empty) | H15: Inline validation error shown: 'Address Line 1 is required'; user cannot proceed to the next step | J15: Not Executed
A16: TC_BIZ_ADDR1_03 | B16: Business Details - Business Info | C16: Enter script/special-character injection in 'Address Line 1' | D16: Negative | E16: Medium | F16: 1. Enter a script/SQL injection payload in 'Address Line 1' 2. Attempt to proceed | G16: Address Line 1: <script>alert(1)</script> | H16: Input is sanitized/rejected as invalid; no script executes; no unhandled server error is exposed | J16: Not Executed
A17: TC_BIZ_ADDR1_04 | B17: Business Details - Business Info | C17: Enter value exceeding maximum length in 'Address Line 1' | D17: Negative | E17: Low | F17: 1. Enter an excessively long value (e.g., 300+ characters) in 'Address Line 1' 2. Attempt to proceed | G17: Address Line 1: 300+ character string | H17: Field enforces a sensible maximum length; validation error shown or input blocked beyond the limit | J17: Not Executed | K17: Assumed — confirm exact validation rule/format with BA/Dev (not fully visible in recording)
A18: TC_BIZ_ADDR2_01 | B18: Business Details - Business Info | C18: Enter valid value in 'Address Line 2' field | D18: Positive | E18: Medium | F18: 1. Navigate to the step containing 'Address Line 2' 2. Enter a valid value 3. Proceed / Save | G18: Address Line 2: Near Al Barsha | H18: Value is accepted; no validation error is shown for 'Address Line 2' | J18: Not Executed
A19: TC_BIZ_ADDR2_03 | B19: Business Details - Business Info | C19: Enter script/special-character injection in 'Address Line 2' | D19: Negative | E19: Medium | F19: 1. Enter a script/SQL injection payload in 'Address Line 2' 2. Attempt to proceed | G19: Address Line 2: <script>alert(1)</script> | H19: Input is sanitized/rejected as invalid; no script executes; no unhandled server error is exposed | J19: Not Executed
A20: TC_BIZ_ADDR2_04 | B20: Business Details - Business Info | C20: Enter value exceeding maximum length in 'Address Line 2' | D20: Negative | E20: Low | F20: 1. Enter an excessively long value (e.g., 300+ characters) in 'Address Line 2' 2. Attempt to proceed | G20: Address Line 2: 300+ character string | H20: Field enforces a sensible maximum length; validation error shown or input blocked beyond the limit | J20: Not Executed | K20: Assumed — confirm exact validation rule/format with BA/Dev (not fully visible in recording)
A21: TC_BIZ_CITY_01 | B21: Business Details - Business Info | C21: Enter valid value in 'City' field | D21: Positive | E21: Medium | F21: 1. Navigate to the step containing 'City' 2. Enter a valid value 3. Proceed / Save | G21: City: Dubai | H21: Value is accepted; no validation error is shown for 'City' | J21: Not Executed
A22: TC_BIZ_CITY_02 | B22: Business Details - Business Info | C22: Leave 'City' empty and attempt to proceed | D22: Negative | E22: Medium | F22: 1. Leave 'City' field empty 2. Click 'Save and Proceed' | G22: City: (empty) | H22: Inline validation error shown: 'City is required'; user cannot proceed to the next step | J22: Not Executed
A23: TC_BIZ_CITY_03 | B23: Business Details - Business Info | C23: Enter script/special-character injection in 'City' | D23: Negative | E23: Medium | F23: 1. Enter a script/SQL injection payload in 'City' 2. Attempt to proceed | G23: City: <script>alert(1)</script> | H23: Input is sanitized/rejected as invalid; no script executes; no unhandled server error is exposed | J23: Not Executed
A24: TC_BIZ_CITY_04 | B24: Business Details - Business Info | C24: Enter value exceeding maximum length in 'City' | D24: Negative | E24: Low | F24: 1. Enter an excessively long value (e.g., 300+ characters) in 'City' 2. Attempt to proceed | G24: City: 300+ character string | H24: Field enforces a sensible maximum length; validation error shown or input blocked beyond the limit | J24: Not Executed | K24: Assumed — confirm exact validation rule/format with BA/Dev (not fully visible in recording)
A25: TC_BIZ_ZIP_01 | B25: Business Details - Business Info | C25: Enter valid alphanumeric value in 'ZIP Code / Area Code' | D25: Positive | E25: Medium | F25: 1. Navigate to the step containing 'ZIP Code / Area Code' 2. Enter a valid value matching the expected format 3. Proceed / Save | G25: ZIP Code / Area Code: 687376 | H25: Value is accepted; no validation error is shown for 'ZIP Code / Area Code' | J25: Not Executed
A26: TC_BIZ_ZIP_02 | B26: Business Details - Business Info | C26: Leave 'ZIP Code / Area Code' empty and attempt to proceed | D26: Negative | E26: Medium | F26: 1. Leave 'ZIP Code / Area Code' field empty 2. Click 'Save and Proceed' | G26: ZIP Code / Area Code: (empty) | H26: Inline validation error shown: 'ZIP Code / Area Code is required'; user cannot proceed | J26: Not Executed
A27: TC_BIZ_ZIP_03 | B27: Business Details - Business Info | C27: Enter value with invalid format/characters in 'ZIP Code / Area Code' | D27: Negative | E27: Medium | F27: 1. Enter a value that does not match the expected format for 'ZIP Code / Area Code' (e.g., AB!!) 2. Attempt to proceed | G27: ZIP Code / Area Code: AB!! | H27: Validation error shown indicating the expected format for 'ZIP Code / Area Code'; user cannot proceed with invalid input | J27: Not Executed | K27: Assumed — confirm exact validation rule/format with BA/Dev (not fully visible in recording)
A28: TC_BIZ_ZIP_04 | B28: Business Details - Business Info | C28: Enter duplicate/already-used value in 'ZIP Code / Area Code' (if uniqueness applies) | D28: Negative | E28: Low | F28: 1. Enter a value for 'ZIP Code / Area Code' that is already registered/used elsewhere in the system 2. Attempt to proceed | G28: ZIP Code / Area Code: duplicate value | H28: Validation error shown if uniqueness is enforced for this field; otherwise value is accepted normally | J28: Not Executed | K28: Assumed — confirm exact validation rule/format with BA/Dev (not fully visible in recording)
A29: TC_BIZ_COUNTRY_01 | B29: Business Details - Business Info | C29: Select a valid option in 'Country' dropdown | D29: Positive | E29: Medium | F29: 1. Click the 'Country' dropdown 2. Select a valid option 3. Proceed / Save | G29: Country: United Arab Emirates | H29: Selected value is accepted and retained; no validation error is shown | J29: Not Executed
A30: TC_BIZ_COUNTRY_02 | B30: Business Details - Business Info | C30: Leave 'Country' dropdown unselected and attempt to proceed | D30: Negative | E30: Medium | F30: 1. Leave 'Country' at its default/placeholder state 2. Click 'Save and Proceed' | G30: Country: (unselected) | H30: Inline validation error shown: 'Country is required'; user cannot proceed | J30: Not Executed
A31: TC_BIZ_COUNTRY_03 | B31: Business Details - Business Info | C31: Verify 'Country' dropdown options are complete and correctly labeled | D31: Positive | E31: Low | F31: 1. Click the 'Country' dropdown 2. Review the full list of available options | G31: Country: full option list | H31: All expected options are present, correctly spelled, and in a logical order (e.g., alphabetical) | J31: Not Executed | K31: Assumed — confirm exact validation rule/format with BA/Dev (not fully visible in recording)
A32: TC_BIZ_MOBILE_01 | B32: Business Details - Business Info | C32: Enter a valid mobile number with country code in 'Mobile Number' | D32: Positive | E32: Medium | F32: 1. Select the correct country code 2. Enter a valid mobile number 3. Proceed / Save | G32: Mobile Number: +971 666464566 | H32: Value is accepted; no validation error is shown | J32: Not Executed
A33: TC_BIZ_MOBILE_02 | B33: Business Details - Business Info | C33: Leave 'Mobile Number' empty and attempt to proceed | D33: Negative | E33: Medium | F33: 1. Leave 'Mobile Number' empty 2. Click 'Save and Proceed' | G33: Mobile Number: (empty) | H33: Inline validation error shown: 'Mobile Number is required'; user cannot proceed | J33: Not Executed
A34: TC_BIZ_MOBILE_03 | B34: Business Details - Business Info | C34: Enter an invalid/incomplete number in 'Mobile Number' | D34: Negative | E34: Medium | F34: 1. Enter a number that is too short, too long, or contains letters 2. Attempt to proceed | G34: Mobile Number: 123 or 37845abc4 | H34: Validation error shown for the mobile number field; user cannot proceed | J34: Not Executed
A35: TC_BIZ_VAT_01 | B35: Business Details - Business Info | C35: Enter valid alphanumeric value in 'VAT Registration Number' | D35: Positive | E35: Medium | F35: 1. Navigate to the step containing 'VAT Registration Number' 2. Enter a valid value matching the expected format 3. Proceed / Save | G35: VAT Registration Number: RE9838948932948 | H35: Value is accepted; no validation error is shown for 'VAT Registration Number' | J35: Not Executed
A36: TC_BIZ_VAT_02 | B36: Business Details - Business Info | C36: Leave 'VAT Registration Number' empty and attempt to proceed | D36: Negative | E36: Medium | F36: 1. Leave 'VAT Registration Number' field empty 2. Click 'Save and Proceed' | G36: VAT Registration Number: (empty) | H36: Inline validation error shown: 'VAT Registration Number is required'; user cannot proceed | J36: Not Executed
A37: TC_BIZ_VAT_03 | B37: Business Details - Business Info | C37: Enter value with invalid format/characters in 'VAT Registration Number' | D37: Negative | E37: Medium | F37: 1. Enter a value that does not match the expected format for 'VAT Registration Number' (e.g., VAT##123) 2. Attempt to proceed | G37: VAT Registration Number: VAT##123 | H37: Validation error shown indicating the expected format for 'VAT Registration Number'; user cannot proceed with invalid input | J37: Not Executed | K37: Assumed — confirm exact validation rule/format with BA/Dev (not fully visible in recording)
A38: TC_BIZ_VAT_04 | B38: Business Details - Business Info | C38: Enter duplicate/already-used value in 'VAT Registration Number' (if uniqueness applies) | D38: Negative | E38: Low | F38: 1. Enter a value for 'VAT Registration Number' that is already registered/used elsewhere in the system 2. Attempt to proceed | G38: VAT Registration Number: duplicate value | H38: Validation error shown if uniqueness is enforced for this field; otherwise value is accepted normally | J38: Not Executed | K38: Assumed — confirm exact validation rule/format with BA/Dev (not fully visible in recording)
A39: TC_BIZ_WEB_01 | B39: Business Details - Business Info | C39: Enter a valid URL in 'Website Address' | D39: Positive | E39: Medium | F39: 1. Navigate to the step containing 'Website Address' 2. Enter a valid website URL 3. Proceed / Save | G39: Website Address: www.rehanairlines.com | H39: Value is accepted; no validation error is shown | J39: Not Executed
A40: TC_BIZ_WEB_02 | B40: Business Details - Business Info | C40: Leave 'Website Address' empty and attempt to proceed | D40: Negative | E40: Medium | F40: 1. Leave 'Website Address' empty 2. Click 'Save and Proceed' | G40: Website Address: (empty) | H40: Inline validation error shown: 'Website Address is required'; user cannot proceed | J40: Not Executed
A41: TC_BIZ_WEB_03 | B41: Business Details - Business Info | C41: Enter an invalid URL format in 'Website Address' | D41: Negative | E41: Medium | F41: 1. Enter a malformed URL (e.g., 'wwrehanairlines', 'htp://site') 2. Attempt to proceed | G41: Website Address: wwrehanairlines | H41: Validation error shown: 'Enter a valid website address'; user cannot proceed | J41: Not Executed
A42: TC_BIZ_ESTAB_01 | B42: Business Details - Business Info | C42: Select a valid option in 'Establishment Type' dropdown | D42: Positive | E42: Medium | F42: 1. Click the 'Establishment Type' dropdown 2. Select a valid option 3. Proceed / Save | G42: Establishment Type: Private Limited Company | H42: Selected value is accepted and retained; no validation error is shown | J42: Not Executed
A43: TC_BIZ_ESTAB_02 | B43: Business Details - Business Info | C43: Leave 'Establishment Type' dropdown unselected and attempt to proceed | D43: Negative | E43: Medium | F43: 1. Leave 'Establishment Type' at its default/placeholder state 2. Click 'Save and Proceed' | G43: Establishment Type: (unselected) | H43: Inline validation error shown: 'Establishment Type is required'; user cannot proceed | J43: Not Executed
A44: TC_BIZ_ESTAB_03 | B44: Business Details - Business Info | C44: Verify 'Establishment Type' dropdown options are complete and correctly labeled | D44: Positive | E44: Low | F44: 1. Click the 'Establishment Type' dropdown 2. Review the full list of available options | G44: Establishment Type: full option list | H44: All expected options are present, correctly spelled, and in a logical order (e.g., alphabetical) | J44: Not Executed | K44: Assumed — confirm exact validation rule/format with BA/Dev (not fully visible in recording)
A45: TC_BIZ_YEARS_01 | B45: Business Details - Business Info | C45: Enter a valid positive number in 'Years in Business' | D45: Positive | E45: Medium | F45: 1. Navigate to the step containing 'Years in Business' 2. Enter a valid positive numeric value 3. Proceed / Save | G45: Years in Business: 8 | H45: Value is accepted; no validation error is shown for 'Years in Business' | J45: Not Executed
A46: TC_BIZ_YEARS_02 | B46: Business Details - Business Info | C46: Leave 'Years in Business' empty and attempt to proceed | D46: Negative | E46: Medium | F46: 1. Leave 'Years in Business' field empty 2. Click 'Save and Proceed' | G46: Years in Business: (empty) | H46: Inline validation error shown: 'Years in Business is required'; user cannot proceed | J46: Not Executed
A47: TC_BIZ_YEARS_03 | B47: Business Details - Business Info | C47: Enter a negative or zero value in 'Years in Business' | D47: Negative | E47: Medium | F47: 1. Enter '0' or a negative number in 'Years in Business' 2. Attempt to proceed | G47: Years in Business: -5 or 0 | H47: Validation error shown indicating the value must be greater than zero; user cannot proceed | J47: Not Executed | K47: Assumed — confirm exact validation rule/format with BA/Dev (not fully visible in recording)
A48: TC_BIZ_YEARS_04 | B48: Business Details - Business Info | C48: Enter non-numeric characters in 'Years in Business' | D48: Negative | E48: Medium | F48: 1. Enter letters/special characters in 'Years in Business' (e.g., 'abc', '12@3') 2. Attempt to proceed | G48: Years in Business: abc | H48: Field rejects non-numeric input; validation error shown or characters are not accepted at all | J48: Not Executed
A49: TC_BIZ_NATURE_01 | B49: Business Details - Business Info | C49: Enter valid value in 'Nature of Business' field | D49: Positive | E49: Medium | F49: 1. Navigate to the step containing 'Nature of Business' 2. Enter a valid value 3. Proceed / Save | G49: Nature of Business: Airline / Air Cargo Services | H49: Value is accepted; no validation error is shown for 'Nature of Business' | J49: Not Executed
A50: TC_BIZ_NATURE_02 | B50: Business Details - Business Info | C50: Leave 'Nature of Business' empty and attempt to proceed | D50: Negative | E50: Medium | F50: 1. Leave 'Nature of Business' field empty 2. Click 'Save and Proceed' | G50: Nature of Business: (empty) | H50: Inline validation error shown: 'Nature of Business is required'; user cannot proceed to the next step | J50: Not Executed
A51: TC_BIZ_NATURE_03 | B51: Business Details - Business Info | C51: Enter script/special-character injection in 'Nature of Business' | D51: Negative | E51: Medium | F51: 1. Enter a script/SQL injection payload in 'Nature of Business' 2. Attempt to proceed | G51: Nature of Business: <script>alert(1)</script> | H51: Input is sanitized/rejected as invalid; no script executes; no unhandled server error is exposed | J51: Not Executed
A52: TC_BIZ_NATURE_04 | B52: Business Details - Business Info | C52: Enter value exceeding maximum length in 'Nature of Business' | D52: Negative | E52: Low | F52: 1. Enter an excessively long value (e.g., 300+ characters) in 'Nature of Business' 2. Attempt to proceed | G52: Nature of Business: 300+ character string | H52: Field enforces a sensible maximum length; validation error shown or input blocked beyond the limit | J52: Not Executed | K52: Assumed — confirm exact validation rule/format with BA/Dev (not fully visible in recording)
A53: TC_BIZ_ANNUAL_01 | B53: Business Details - Business Info | C53: Enter a valid amount with currency selected for 'Annual Projected Volume' | D53: Positive | E53: Medium | F53: 1. Select a currency in the 'Annual Projected Volume' currency dropdown 2. Enter a valid positive amount 3. Proceed / Save | G53: Annual Projected Volume: AED 50,000 | H53: Value and currency are accepted; no validation error is shown | J53: Not Executed
A54: TC_BIZ_ANNUAL_02 | B54: Business Details - Business Info | C54: Leave 'Annual Projected Volume' amount empty and attempt to proceed | D54: Negative | E54: Medium | F54: 1. Leave the 'Annual Projected Volume' amount field empty 2. Click 'Save and Proceed' | G54: Annual Projected Volume: (empty) | H54: Inline validation error shown: 'Annual Projected Volume is required'; user cannot proceed | J54: Not Executed
A55: TC_BIZ_ANNUAL_03 | B55: Business Details - Business Info | C55: Enter a negative or zero amount in 'Annual Projected Volume' | D55: Negative | E55: Medium | F55: 1. Enter '0' or a negative number as the 'Annual Projected Volume' amount 2. Attempt to proceed | G55: Annual Projected Volume: -1000 or 0 | H55: Validation error shown indicating the amount must be greater than zero; user cannot proceed | J55: Not Executed | K55: Assumed — confirm exact validation rule/format with BA/Dev (not fully visible in recording)
A56: TC_BIZ_ANNUAL_04 | B56: Business Details - Business Info | C56: Leave currency dropdown for 'Annual Projected Volume' unselected (if no default) | D56: Negative | E56: Low | F56: 1. Leave the currency dropdown for 'Annual Projected Volume' at a blank/placeholder state (if possible) 2. Enter a valid amount 3. Attempt to proceed | G56: Annual Projected Volume: amount entered, currency unselected | H56: Validation error shown requiring a currency selection; user cannot proceed without one | J56: Not Executed | K56: Assumed — confirm exact validation rule/format with BA/Dev (not fully visible in recording)
A57: TC_BIZ_ANNUAL_05 | B57: Business Details - Business Info | C57: Cross-field consistency check for 'Annual Projected Volume' against related volume/value fields | D57: Negative | E57: Low | F57: 1. Enter a value for 'Annual Projected Volume' that is logically inconsistent with a related field (e.g., 'Highest Single Transaction Value' lower than 'Average Transaction Value') 2. Attempt to proceed | G57: Annual Projected Volume: inconsistent value relative to related field | H57: System either flags the inconsistency with a warning/error or accepts it if no cross-field validation is implemented — confirm intended behaviour | J57: Not Executed | K57: Assumed — confirm exact validation rule/format with BA/Dev (not fully visible in recording)
A58: TC_BIZ_MONTHVOL_01 | B58: Business Details - Business Info | C58: Enter a valid amount with currency selected for 'Expected Monthly Transaction Volume' | D58: Positive | E58: Medium | F58: 1. Select a currency in the 'Expected Monthly Transaction Volume' currency dropdown 2. Enter a valid positive amount 3. Proceed / Save | G58: Expected Monthly Transaction Volume: AED 50,000 | H58: Value and currency are accepted; no validation error is shown | J58: Not Executed
A59: TC_BIZ_MONTHVOL_02 | B59: Business Details - Business Info | C59: Leave 'Expected Monthly Transaction Volume' amount empty and attempt to proceed | D59: Negative | E59: Medium | F59: 1. Leave the 'Expected Monthly Transaction Volume' amount field empty 2. Click 'Save and Proceed' | G59: Expected Monthly Transaction Volume: (empty) | H59: Inline validation error shown: 'Expected Monthly Transaction Volume is required'; user cannot proceed | J59: Not Executed
A60: TC_BIZ_MONTHVOL_03 | B60: Business Details - Business Info | C60: Enter a negative or zero amount in 'Expected Monthly Transaction Volume' | D60: Negative | E60: Medium | F60: 1. Enter '0' or a negative number as the 'Expected Monthly Transaction Volume' amount 2. Attempt to proceed | G60: Expected Monthly Transaction Volume: -1000 or 0 | H60: Validation error shown indicating the amount must be greater than zero; user cannot proceed | J60: Not Executed | K60: Assumed — confirm exact validation rule/format with BA/Dev (not fully visible in recording)
A61: TC_BIZ_MONTHVOL_04 | B61: Business Details - Business Info | C61: Leave currency dropdown for 'Expected Monthly Transaction Volume' unselected (if no default) | D61: Negative | E61: Low | F61: 1. Leave the currency dropdown for 'Expected Monthly Transaction Volume' at a blank/placeholder state (if possible) 2. Enter a valid amount 3. Attempt to proceed | G61: Expected Monthly Transaction Volume: amount entered, currency unselected | H61: Validation error shown requiring a currency selection; user cannot proceed without one | J61: Not Executed | K61: Assumed — confirm exact validation rule/format with BA/Dev (not fully visible in recording)
A62: TC_BIZ_MONTHVOL_05 | B62: Business Details - Business Info | C62: Cross-field consistency check for 'Expected Monthly Transaction Volume' against related volume/value fields | D62: Negative | E62: Low | F62: 1. Enter a value for 'Expected Monthly Transaction Volume' that is logically inconsistent with a related field (e.g., 'Highest Single Transaction Value' lower than 'Average Transaction Value') 2. Attempt to proceed | G62: Expected Monthly Transaction Volume: inconsistent value relative to related field | H62: System either flags the inconsistency with a warning/error or accepts it if no cross-field validation is implemented — confirm intended behaviour | J62: Not Executed | K62: Assumed — confirm exact validation rule/format with BA/Dev (not fully visible in recording)
A63: TC_BIZ_AVGVAL_01 | B63: Business Details - Business Info | C63: Enter a valid amount with currency selected for 'Average Transaction Value' | D63: Positive | E63: Medium | F63: 1. Select a currency in the 'Average Transaction Value' currency dropdown 2. Enter a valid positive amount 3. Proceed / Save | G63: Average Transaction Value: AED 50,000 | H63: Value and currency are accepted; no validation error is shown | J63: Not Executed
A64: TC_BIZ_AVGVAL_02 | B64: Business Details - Business Info | C64: Leave 'Average Transaction Value' amount empty and attempt to proceed | D64: Negative | E64: Medium | F64: 1. Leave the 'Average Transaction Value' amount field empty 2. Click 'Save and Proceed' | G64: Average Transaction Value: (empty) | H64: Inline validation error shown: 'Average Transaction Value is required'; user cannot proceed | J64: Not Executed
A65: TC_BIZ_AVGVAL_03 | B65: Business Details - Business Info | C65: Enter a negative or zero amount in 'Average Transaction Value' | D65: Negative | E65: Medium | F65: 1. Enter '0' or a negative number as the 'Average Transaction Value' amount 2. Attempt to proceed | G65: Average Transaction Value: -1000 or 0 | H65: Validation error shown indicating the amount must be greater than zero; user cannot proceed | J65: Not Executed | K65: Assumed — confirm exact validation rule/format with BA/Dev (not fully visible in recording)
A66: TC_BIZ_AVGVAL_04 | B66: Business Details - Business Info | C66: Leave currency dropdown for 'Average Transaction Value' unselected (if no default) | D66: Negative | E66: Low | F66: 1. Leave the currency dropdown for 'Average Transaction Value' at a blank/placeholder state (if possible) 2. Enter a valid amount 3. Attempt to proceed | G66: Average Transaction Value: amount entered, currency unselected | H66: Validation error shown requiring a currency selection; user cannot proceed without one | J66: Not Executed | K66: Assumed — confirm exact validation rule/format with BA/Dev (not fully visible in recording)
A67: TC_BIZ_AVGVAL_05 | B67: Business Details - Business Info | C67: Cross-field consistency check for 'Average Transaction Value' against related volume/value fields | D67: Negative | E67: Low | F67: 1. Enter a value for 'Average Transaction Value' that is logically inconsistent with a related field (e.g., 'Highest Single Transaction Value' lower than 'Average Transaction Value') 2. Attempt to proceed | G67: Average Transaction Value: inconsistent value relative to related field | H67: System either flags the inconsistency with a warning/error or accepts it if no cross-field validation is implemented — confirm intended behaviour | J67: Not Executed | K67: Assumed — confirm exact validation rule/format with BA/Dev (not fully visible in recording)
A68: TC_BIZ_MAXDAILY_01 | B68: Business Details - Business Info | C68: Enter a valid amount with currency selected for 'Maximum Daily Volume' | D68: Positive | E68: Medium | F68: 1. Select a currency in the 'Maximum Daily Volume' currency dropdown 2. Enter a valid positive amount 3. Proceed / Save | G68: Maximum Daily Volume: AED 50,000 | H68: Value and currency are accepted; no validation error is shown | J68: Not Executed
A69: TC_BIZ_MAXDAILY_02 | B69: Business Details - Business Info | C69: Leave 'Maximum Daily Volume' amount empty and attempt to proceed | D69: Negative | E69: Medium | F69: 1. Leave the 'Maximum Daily Volume' amount field empty 2. Click 'Save and Proceed' | G69: Maximum Daily Volume: (empty) | H69: Inline validation error shown: 'Maximum Daily Volume is required'; user cannot proceed | J69: Not Executed
A70: TC_BIZ_MAXDAILY_03 | B70: Business Details - Business Info | C70: Enter a negative or zero amount in 'Maximum Daily Volume' | D70: Negative | E70: Medium | F70: 1. Enter '0' or a negative number as the 'Maximum Daily Volume' amount 2. Attempt to proceed | G70: Maximum Daily Volume: -1000 or 0 | H70: Validation error shown indicating the amount must be greater than zero; user cannot proceed | J70: Not Executed | K70: Assumed — confirm exact validation rule/format with BA/Dev (not fully visible in recording)
A71: TC_BIZ_MAXDAILY_04 | B71: Business Details - Business Info | C71: Leave currency dropdown for 'Maximum Daily Volume' unselected (if no default) | D71: Negative | E71: Low | F71: 1. Leave the currency dropdown for 'Maximum Daily Volume' at a blank/placeholder state (if possible) 2. Enter a valid amount 3. Attempt to proceed | G71: Maximum Daily Volume: amount entered, currency unselected | H71: Validation error shown requiring a currency selection; user cannot proceed without one | J71: Not Executed | K71: Assumed — confirm exact validation rule/format with BA/Dev (not fully visible in recording)
A72: TC_BIZ_MAXDAILY_05 | B72: Business Details - Business Info | C72: Cross-field consistency check for 'Maximum Daily Volume' against related volume/value fields | D72: Negative | E72: Low | F72: 1. Enter a value for 'Maximum Daily Volume' that is logically inconsistent with a related field (e.g., 'Highest Single Transaction Value' lower than 'Average Transaction Value') 2. Attempt to proceed | G72: Maximum Daily Volume: inconsistent value relative to related field | H72: System either flags the inconsistency with a warning/error or accepts it if no cross-field validation is implemented — confirm intended behaviour | J72: Not Executed | K72: Assumed — confirm exact validation rule/format with BA/Dev (not fully visible in recording)
A73: TC_BIZ_HIGHTXN_01 | B73: Business Details - Business Info | C73: Enter a valid amount with currency selected for 'Highest Single Transaction Value' | D73: Positive | E73: Medium | F73: 1. Select a currency in the 'Highest Single Transaction Value' currency dropdown 2. Enter a valid positive amount 3. Proceed / Save | G73: Highest Single Transaction Value: AED 50,000 | H73: Value and currency are accepted; no validation error is shown | J73: Not Executed
A74: TC_BIZ_HIGHTXN_02 | B74: Business Details - Business Info | C74: Leave 'Highest Single Transaction Value' amount empty and attempt to proceed | D74: Negative | E74: Medium | F74: 1. Leave the 'Highest Single Transaction Value' amount field empty 2. Click 'Save and Proceed' | G74: Highest Single Transaction Value: (empty) | H74: Inline validation error shown: 'Highest Single Transaction Value is required'; user cannot proceed | J74: Not Executed
A75: TC_BIZ_HIGHTXN_03 | B75: Business Details - Business Info | C75: Enter a negative or zero amount in 'Highest Single Transaction Value' | D75: Negative | E75: Medium | F75: 1. Enter '0' or a negative number as the 'Highest Single Transaction Value' amount 2. Attempt to proceed | G75: Highest Single Transaction Value: -1000 or 0 | H75: Validation error shown indicating the amount must be greater than zero; user cannot proceed | J75: Not Executed | K75: Assumed — confirm exact validation rule/format with BA/Dev (not fully visible in recording)
A76: TC_BIZ_HIGHTXN_04 | B76: Business Details - Business Info | C76: Leave currency dropdown for 'Highest Single Transaction Value' unselected (if no default) | D76: Negative | E76: Low | F76: 1. Leave the currency dropdown for 'Highest Single Transaction Value' at a blank/placeholder state (if possible) 2. Enter a valid amount 3. Attempt to proceed | G76: Highest Single Transaction Value: amount entered, currency unselected | H76: Validation error shown requiring a currency selection; user cannot proceed without one | J76: Not Executed | K76: Assumed — confirm exact validation rule/format with BA/Dev (not fully visible in recording)
A77: TC_BIZ_HIGHTXN_05 | B77: Business Details - Business Info | C77: Cross-field consistency check for 'Highest Single Transaction Value' against related volume/value fields | D77: Negative | E77: Low | F77: 1. Enter a value for 'Highest Single Transaction Value' that is logically inconsistent with a related field (e.g., 'Highest Single Transaction Value' lower than 'Average Transaction Value') 2. Attempt to proceed | G77: Highest Single Transaction Value: inconsistent value relative to related field | H77: System either flags the inconsistency with a warning/error or accepts it if no cross-field validation is implemented — confirm intended behaviour | J77: Not Executed | K77: Assumed — confirm exact validation rule/format with BA/Dev (not fully visible in recording)
A78: TC_BIZ_LOGO_U01 | B78: Business Details - Business Info | C78: Upload a clean file in an allowed format for 'Business Logo' | D78: Positive | E78: High | F78: 1. Navigate to the step containing 'Business Logo' 2. Select a clean file matching an allowed format (JPG, JPEG, PNG) within 1 MB 3. Upload | G78: clean_biz_logo.jpg (within 1 MB) | H78: File passes the ClamAV scan with result 'Clean'; upload completes; file is accepted for this field | J78: Not Executed
A79: TC_BIZ_LOGO_U02 | B79: Business Details - Business Info | C79: Attempt to proceed without uploading 'Business Logo' (mandatory) | D79: Negative | E79: High | F79: 1. Leave 'Business Logo' empty 2. Click 'Save and Proceed' | G79: Business Logo: (no file uploaded) | H79: Validation error shown: 'Business Logo is required'; user cannot proceed | J79: Not Executed
A80: TC_BIZ_LOGO_U03 | B80: Business Details - Business Info | C80: Upload the EICAR antivirus test file to 'Business Logo' | D80: Negative | E80: High | F80: 1. Prepare the EICAR test string as a .jpg file 2. Upload it to 'Business Logo' | G80: eicar_test.jpg | H80: ClamAV detects the file as infected ('Eicar-Test-Signature'); upload is rejected with a clear, non-technical error message; file is not saved | J80: Not Executed
A81: TC_BIZ_LOGO_U04 | B81: Business Details - Business Info | C81: Upload a file in an unsupported format to 'Business Logo' | D81: Negative | E81: Medium | F81: 1. Select a file in a format not in the allowed list (JPG, JPEG, PNG) 2. Attempt to upload to 'Business Logo' | G81: unsupported_file.exe | H81: Upload is rejected with a validation error indicating the allowed formats (JPG, JPEG, PNG) | J81: Not Executed
A82: TC_BIZ_LOGO_U05 | B82: Business Details - Business Info | C82: Upload a file exceeding the maximum size limit for 'Business Logo' | D82: Negative | E82: Medium | F82: 1. Select a file exceeding 1 MB 2. Attempt to upload to 'Business Logo' | G82: oversized_biz_logo.jpg (exceeds 1 MB) | H82: Upload is rejected with a validation error indicating the 1 MB size limit | J82: Not Executed
A83: TC_BIZ_LOGO_U06 | B83: Business Details - Business Info | C83: Upload a corrupted/malformed file to 'Business Logo' | D83: Negative | E83: Medium | F83: 1. Prepare a deliberately corrupted file with a valid extension 2. Upload it to 'Business Logo' | G83: corrupted_biz_logo.jpg | H83: File is rejected with a clear error; no server crash or unhandled exception occurs | J83: Not Executed
A84: TC_CLIC_U01 | B84: Business Details - Commercial License | C84: Upload a clean file in an allowed format for 'Commercial License Proof' | D84: Positive | E84: High | F84: 1. Navigate to the step containing 'Commercial License Proof' 2. Select a clean file matching an allowed format (PDF, DOC, DOCX, JPG, JPEG, PNG) within 1 MB 3. Upload | G84: clean_clic.pdf (within 1 MB) | H84: File passes the ClamAV scan with result 'Clean'; upload completes; file is accepted for this field | J84: Not Executed
A85: TC_CLIC_U02 | B85: Business Details - Commercial License | C85: Attempt to proceed without uploading 'Commercial License Proof' (mandatory) | D85: Negative | E85: High | F85: 1. Leave 'Commercial License Proof' empty 2. Click 'Save and Proceed' | G85: Commercial License Proof: (no file uploaded) | H85: Validation error shown: 'Commercial License Proof is required'; user cannot proceed | J85: Not Executed
A86: TC_CLIC_U03 | B86: Business Details - Commercial License | C86: Upload the EICAR antivirus test file to 'Commercial License Proof' | D86: Negative | E86: High | F86: 1. Prepare the EICAR test string as a .pdf file 2. Upload it to 'Commercial License Proof' | G86: eicar_test.pdf | H86: ClamAV detects the file as infected ('Eicar-Test-Signature'); upload is rejected with a clear, non-technical error message; file is not saved | J86: Not Executed
A87: TC_CLIC_U04 | B87: Business Details - Commercial License | C87: Upload a file in an unsupported format to 'Commercial License Proof' | D87: Negative | E87: Medium | F87: 1. Select a file in a format not in the allowed list (PDF, DOC, DOCX, JPG, JPEG, PNG) 2. Attempt to upload to 'Commercial License Proof' | G87: unsupported_file.exe | H87: Upload is rejected with a validation error indicating the allowed formats (PDF, DOC, DOCX, JPG, JPEG, PNG) | J87: Not Executed
A88: TC_CLIC_U05 | B88: Business Details - Commercial License | C88: Upload a file exceeding the maximum size limit for 'Commercial License Proof' | D88: Negative | E88: Medium | F88: 1. Select a file exceeding 1 MB 2. Attempt to upload to 'Commercial License Proof' | G88: oversized_clic.pdf (exceeds 1 MB) | H88: Upload is rejected with a validation error indicating the 1 MB size limit | J88: Not Executed
A89: TC_CLIC_U06 | B89: Business Details - Commercial License | C89: Upload a corrupted/malformed file to 'Commercial License Proof' | D89: Negative | E89: Medium | F89: 1. Prepare a deliberately corrupted file with a valid extension 2. Upload it to 'Commercial License Proof' | G89: corrupted_clic.pdf | H89: File is rejected with a clear error; no server crash or unhandled exception occurs | J89: Not Executed
A90: TC_CLIC_EXP01 | B90: Business Details - Commercial License | C90: Upload a Commercial License document expiring in more than 21 days | D90: Positive | E90: High | F90: 1. Upload a Commercial License Proof with an expiry date more than 21 days from today 2. Attempt to proceed | G90: Document expiry: today + 60 days | H90: File is accepted; user can proceed to the next step without any renewal warning | J90: Not Executed
A91: TC_CLIC_EXP02 | B91: Business Details - Commercial License | C91: Upload a Commercial License document expiring within 21 days | D91: Negative | E91: High | F91: 1. Upload a Commercial License Proof with an expiry date less than 21 days from today 2. Attempt to proceed | G91: Document expiry: today + 10 days | H91: System displays the specified warning: document must be renewed before proceeding since its expiry date is less than 21 days away; user cannot proceed until a renewed document is uploaded | J91: Not Executed | K91: Confirm exact detection method — e.g., manual date field entry vs automatic extraction from the uploaded file
A92: TC_CLIC_EXP03 | B92: Business Details - Commercial License | C92: Upload a Commercial License document that has already expired | D92: Negative | E92: High | F92: 1. Upload a Commercial License Proof with an expiry date in the past 2. Attempt to proceed | G92: Document expiry: yesterday | H92: System rejects the document as expired with a clear message; user cannot proceed until a valid, unexpired document is uploaded | J92: Not Executed
A93: TC_AOA_U01 | B93: Business Details - Articles of Association | C93: Upload a clean file in an allowed format for 'Articles of Association Proof' | D93: Positive | E93: High | F93: 1. Navigate to the step containing 'Articles of Association Proof' 2. Select a clean file matching an allowed format (PDF, DOC, DOCX, JPG, JPEG, PNG) within 1 MB 3. Upload | G93: clean_aoa.pdf (within 1 MB) | H93: File passes the ClamAV scan with result 'Clean'; upload completes; file is accepted for this field | J93: Not Executed | K93: Assumed — confirm exact validation rule/format with BA/Dev (not fully visible in recording)
A94: TC_AOA_U02 | B94: Business Details - Articles of Association | C94: Attempt to proceed without uploading 'Articles of Association Proof' (mandatory) | D94: Negative | E94: High | F94: 1. Leave 'Articles of Association Proof' empty 2. Click 'Save and Proceed' | G94: Articles of Association Proof: (no file uploaded) | H94: Validation error shown: 'Articles of Association Proof is required'; user cannot proceed | J94: Not Executed
A95: TC_AOA_U03 | B95: Business Details - Articles of Association | C95: Upload the EICAR antivirus test file to 'Articles of Association Proof' | D95: Negative | E95: High | F95: 1. Prepare the EICAR test string as a .pdf file 2. Upload it to 'Articles of Association Proof' | G95: eicar_test.pdf | H95: ClamAV detects the file as infected ('Eicar-Test-Signature'); upload is rejected with a clear, non-technical error message; file is not saved | J95: Not Executed
A96: TC_AOA_U04 | B96: Business Details - Articles of Association | C96: Upload a file in an unsupported format to 'Articles of Association Proof' | D96: Negative | E96: Medium | F96: 1. Select a file in a format not in the allowed list (PDF, DOC, DOCX, JPG, JPEG, PNG) 2. Attempt to upload to 'Articles of Association Proof' | G96: unsupported_file.exe | H96: Upload is rejected with a validation error indicating the allowed formats (PDF, DOC, DOCX, JPG, JPEG, PNG) | J96: Not Executed
A97: TC_AOA_U05 | B97: Business Details - Articles of Association | C97: Upload a file exceeding the maximum size limit for 'Articles of Association Proof' | D97: Negative | E97: Medium | F97: 1. Select a file exceeding 1 MB 2. Attempt to upload to 'Articles of Association Proof' | G97: oversized_aoa.pdf (exceeds 1 MB) | H97: Upload is rejected with a validation error indicating the 1 MB size limit | J97: Not Executed
A98: TC_AOA_U06 | B98: Business Details - Articles of Association | C98: Upload a corrupted/malformed file to 'Articles of Association Proof' | D98: Negative | E98: Medium | F98: 1. Prepare a deliberately corrupted file with a valid extension 2. Upload it to 'Articles of Association Proof' | G98: corrupted_aoa.pdf | H98: File is rejected with a clear error; no server crash or unhandled exception occurs | J98: Not Executed
A99: TC_SH_NAME_01 | B99: Stakeholder Details | C99: Enter valid value in 'Stakeholder Name' field | D99: Positive | E99: Medium | F99: 1. Navigate to the step containing 'Stakeholder Name' 2. Enter a valid value 3. Proceed / Save | G99: Stakeholder Name: Sergey Kovalenko | H99: Value is accepted; no validation error is shown for 'Stakeholder Name' | J99: Not Executed
A100: TC_SH_NAME_02 | B100: Stakeholder Details | C100: Leave 'Stakeholder Name' empty and attempt to proceed | D100: Negative | E100: Medium | F100: 1. Leave 'Stakeholder Name' field empty 2. Click 'Save and Proceed' | G100: Stakeholder Name: (empty) | H100: Inline validation error shown: 'Stakeholder Name is required'; user cannot proceed to the next step | J100: Not Executed
...

Sheet Buyer Onboarding
A1: Test Case ID | B1: Screen | C1: Test Case Description | D1: Test Case Type | E1: Priority | F1: Test Steps | G1: Test Data | H1: Expected Result | I1: Actual Result | J1: Status | K1: Remarks
A2: TC_FF_BIZ_NAME_01 | B2: Business Details - Business Info | C2: Enter valid value in 'Organisation Name' field | D2: Positive | E2: Medium | F2: 1. Navigate to the step containing 'Organisation Name' 2. Enter a valid value 3. Proceed / Save | G2: Organisation Name: Anjali Forwarders | H2: Value is accepted; no validation error is shown for 'Organisation Name' | J2: Not Executed | K2: Freight Forwarders field label/rule assumed based on parallel Airlines flow — confirm exact wording/rule with BA/Dev since the two onboarding forms are built separately
A3: TC_FF_BIZ_NAME_02 | B3: Business Details - Business Info | C3: Leave 'Organisation Name' empty and attempt to proceed | D3: Negative | E3: Medium | F3: 1. Leave 'Organisation Name' field empty 2. Click 'Save and Proceed' | G3: Organisation Name: (empty) | H3: Inline validation error shown: 'Organisation Name is required'; user cannot proceed to the next step | J3: Not Executed | K3: Freight Forwarders field label/rule assumed based on parallel Airlines flow — confirm exact wording/rule with BA/Dev since the two onboarding forms are built separately
A4: TC_FF_BIZ_NAME_03 | B4: Business Details - Business Info | C4: Enter script/special-character injection in 'Organisation Name' | D4: Negative | E4: Medium | F4: 1. Enter a script/SQL injection payload in 'Organisation Name' 2. Attempt to proceed | G4: Organisation Name: <script>alert(1)</script> | H4: Input is sanitized/rejected as invalid; no script executes; no unhandled server error is exposed | J4: Not Executed | K4: Freight Forwarders field label/rule assumed based on parallel Airlines flow — confirm exact wording/rule with BA/Dev since the two onboarding forms are built separately
A5: TC_FF_BIZ_NAME_04 | B5: Business Details - Business Info | C5: Enter value exceeding maximum length in 'Organisation Name' | D5: Negative | E5: Low | F5: 1. Enter an excessively long value (e.g., 300+ characters) in 'Organisation Name' 2. Attempt to proceed | G5: Organisation Name: 300+ character string | H5: Field enforces a sensible maximum length; validation error shown or input blocked beyond the limit | J5: Not Executed | K5: Assumed — confirm exact validation rule/format with BA/Dev (not fully visible in recording)
A6: TC_FF_BIZ_TRADE_01 | B6: Business Details - Business Info | C6: Enter valid alphanumeric value in 'Trade/RE Reference Number' | D6: Positive | E6: Medium | F6: 1. Navigate to the step containing 'Trade/RE Reference Number' 2. Enter a valid value matching the expected format 3. Proceed / Save | G6: Trade/RE Reference Number: RE8823741029384 | H6: Value is accepted; no validation error is shown for 'Trade/RE Reference Number' | J6: Not Executed | K6: Freight Forwarders field label/rule assumed based on parallel Airlines flow — confirm exact wording/rule with BA/Dev since the two onboarding forms are built separately
A7: TC_FF_BIZ_TRADE_02 | B7: Business Details - Business Info | C7: Leave 'Trade/RE Reference Number' empty and attempt to proceed | D7: Negative | E7: Medium | F7: 1. Leave 'Trade/RE Reference Number' field empty 2. Click 'Save and Proceed' | G7: Trade/RE Reference Number: (empty) | H7: Inline validation error shown: 'Trade/RE Reference Number is required'; user cannot proceed | J7: Not Executed | K7: Freight Forwarders field label/rule assumed based on parallel Airlines flow — confirm exact wording/rule with BA/Dev since the two onboarding forms are built separately
A8: TC_FF_BIZ_TRADE_03 | B8: Business Details - Business Info | C8: Enter value with invalid format/characters in 'Trade/RE Reference Number' | D8: Negative | E8: Medium | F8: 1. Enter a value that does not match the expected format for 'Trade/RE Reference Number' (e.g., RE@#$123) 2. Attempt to proceed | G8: Trade/RE Reference Number: RE@#$123 | H8: Validation error shown indicating the expected format for 'Trade/RE Reference Number'; user cannot proceed with invalid input | J8: Not Executed | K8: Assumed — confirm exact validation rule/format with BA/Dev (not fully visible in recording)
A9: TC_FF_BIZ_TRADE_04 | B9: Business Details - Business Info | C9: Enter duplicate/already-used value in 'Trade/RE Reference Number' (if uniqueness applies) | D9: Negative | E9: Low | F9: 1. Enter a value for 'Trade/RE Reference Number' that is already registered/used elsewhere in the system 2. Attempt to proceed | G9: Trade/RE Reference Number: duplicate value | H9: Validation error shown if uniqueness is enforced for this field; otherwise value is accepted normally | J9: Not Executed | K9: Assumed — confirm exact validation rule/format with BA/Dev (not fully visible in recording)
A10: TC_FF_BIZ_TRN_01 | B10: Business Details - Business Info | C10: Enter valid alphanumeric value in 'Tax Registration Number (TRN)' | D10: Positive | E10: Medium | F10: 1. Navigate to the step containing 'Tax Registration Number (TRN)' 2. Enter a valid value matching the expected format 3. Proceed / Save | G10: Tax Registration Number (TRN): ANJ83920123 | H10: Value is accepted; no validation error is shown for 'Tax Registration Number (TRN)' | J10: Not Executed
A11: TC_FF_BIZ_TRN_02 | B11: Business Details - Business Info | C11: Leave 'Tax Registration Number (TRN)' empty and attempt to proceed | D11: Negative | E11: Medium | F11: 1. Leave 'Tax Registration Number (TRN)' field empty 2. Click 'Save and Proceed' | G11: Tax Registration Number (TRN): (empty) | H11: Inline validation error shown: 'Tax Registration Number (TRN) is required'; user cannot proceed | J11: Not Executed
A12: TC_FF_BIZ_TRN_03 | B12: Business Details - Business Info | C12: Enter value with invalid format/characters in 'Tax Registration Number (TRN)' | D12: Negative | E12: Medium | F12: 1. Enter a value that does not match the expected format for 'Tax Registration Number (TRN)' (e.g., ANJ839) 2. Attempt to proceed | G12: Tax Registration Number (TRN): ANJ839 | H12: Validation error shown indicating the expected format for 'Tax Registration Number (TRN)'; user cannot proceed with invalid input | J12: Not Executed | K12: Assumed — confirm exact validation rule/format with BA/Dev (not fully visible in recording)
A13: TC_FF_BIZ_TRN_04 | B13: Business Details - Business Info | C13: Enter duplicate/already-used value in 'Tax Registration Number (TRN)' (if uniqueness applies) | D13: Negative | E13: Low | F13: 1. Enter a value for 'Tax Registration Number (TRN)' that is already registered/used elsewhere in the system 2. Attempt to proceed | G13: Tax Registration Number (TRN): duplicate value | H13: Validation error shown if uniqueness is enforced for this field; otherwise value is accepted normally | J13: Not Executed | K13: Assumed — confirm exact validation rule/format with BA/Dev (not fully visible in recording)
A14: TC_FF_BIZ_ADDR1_01 | B14: Business Details - Business Info | C14: Enter valid value in 'Address Line 1' field | D14: Positive | E14: Medium | F14: 1. Navigate to the step containing 'Address Line 1' 2. Enter a valid value 3. Proceed / Save | G14: Address Line 1: Warehouse 12, Al Quoz Industrial Area | H14: Value is accepted; no validation error is shown for 'Address Line 1' | J14: Not Executed
A15: TC_FF_BIZ_ADDR1_02 | B15: Business Details - Business Info | C15: Leave 'Address Line 1' empty and attempt to proceed | D15: Negative | E15: Medium | F15: 1. Leave 'Address Line 1' field empty 2. Click 'Save and Proceed' | G15: Address Line 1: (empty) | H15: Inline validation error shown: 'Address Line 1 is required'; user cannot proceed to the next step | J15: Not Executed
A16: TC_FF_BIZ_ADDR1_03 | B16: Business Details - Business Info | C16: Enter script/special-character injection in 'Address Line 1' | D16: Negative | E16: Medium | F16: 1. Enter a script/SQL injection payload in 'Address Line 1' 2. Attempt to proceed | G16: Address Line 1: <script>alert(1)</script> | H16: Input is sanitized/rejected as invalid; no script executes; no unhandled server error is exposed | J16: Not Executed
A17: TC_FF_BIZ_ADDR1_04 | B17: Business Details - Business Info | C17: Enter value exceeding maximum length in 'Address Line 1' | D17: Negative | E17: Low | F17: 1. Enter an excessively long value (e.g., 300+ characters) in 'Address Line 1' 2. Attempt to proceed | G17: Address Line 1: 300+ character string | H17: Field enforces a sensible maximum length; validation error shown or input blocked beyond the limit | J17: Not Executed | K17: Assumed — confirm exact validation rule/format with BA/Dev (not fully visible in recording)
A18: TC_FF_BIZ_ADDR2_01 | B18: Business Details - Business Info | C18: Enter valid value in 'Address Line 2' field | D18: Positive | E18: Medium | F18: 1. Navigate to the step containing 'Address Line 2' 2. Enter a valid value 3. Proceed / Save | G18: Address Line 2: Near Logistics Hub | H18: Value is accepted; no validation error is shown for 'Address Line 2' | J18: Not Executed
A19: TC_FF_BIZ_ADDR2_03 | B19: Business Details - Business Info | C19: Enter script/special-character injection in 'Address Line 2' | D19: Negative | E19: Medium | F19: 1. Enter a script/SQL injection payload in 'Address Line 2' 2. Attempt to proceed | G19: Address Line 2: <script>alert(1)</script> | H19: Input is sanitized/rejected as invalid; no script executes; no unhandled server error is exposed | J19: Not Executed
A20: TC_FF_BIZ_ADDR2_04 | B20: Business Details - Business Info | C20: Enter value exceeding maximum length in 'Address Line 2' | D20: Negative | E20: Low | F20: 1. Enter an excessively long value (e.g., 300+ characters) in 'Address Line 2' 2. Attempt to proceed | G20: Address Line 2: 300+ character string | H20: Field enforces a sensible maximum length; validation error shown or input blocked beyond the limit | J20: Not Executed | K20: Assumed — confirm exact validation rule/format with BA/Dev (not fully visible in recording)
A21: TC_FF_BIZ_CITY_01 | B21: Business Details - Business Info | C21: Enter valid value in 'City' field | D21: Positive | E21: Medium | F21: 1. Navigate to the step containing 'City' 2. Enter a valid value 3. Proceed / Save | G21: City: Dubai | H21: Value is accepted; no validation error is shown for 'City' | J21: Not Executed
A22: TC_FF_BIZ_CITY_02 | B22: Business Details - Business Info | C22: Leave 'City' empty and attempt to proceed | D22: Negative | E22: Medium | F22: 1. Leave 'City' field empty 2. Click 'Save and Proceed' | G22: City: (empty) | H22: Inline validation error shown: 'City is required'; user cannot proceed to the next step | J22: Not Executed
A23: TC_FF_BIZ_CITY_03 | B23: Business Details - Business Info | C23: Enter script/special-character injection in 'City' | D23: Negative | E23: Medium | F23: 1. Enter a script/SQL injection payload in 'City' 2. Attempt to proceed | G23: City: <script>alert(1)</script> | H23: Input is sanitized/rejected as invalid; no script executes; no unhandled server error is exposed | J23: Not Executed
A24: TC_FF_BIZ_CITY_04 | B24: Business Details - Business Info | C24: Enter value exceeding maximum length in 'City' | D24: Negative | E24: Low | F24: 1. Enter an excessively long value (e.g., 300+ characters) in 'City' 2. Attempt to proceed | G24: City: 300+ character string | H24: Field enforces a sensible maximum length; validation error shown or input blocked beyond the limit | J24: Not Executed | K24: Assumed — confirm exact validation rule/format with BA/Dev (not fully visible in recording)
A25: TC_FF_BIZ_ZIP_01 | B25: Business Details - Business Info | C25: Enter valid alphanumeric value in 'ZIP Code / Area Code' | D25: Positive | E25: Medium | F25: 1. Navigate to the step containing 'ZIP Code / Area Code' 2. Enter a valid value matching the expected format 3. Proceed / Save | G25: ZIP Code / Area Code: 512394 | H25: Value is accepted; no validation error is shown for 'ZIP Code / Area Code' | J25: Not Executed
A26: TC_FF_BIZ_ZIP_02 | B26: Business Details - Business Info | C26: Leave 'ZIP Code / Area Code' empty and attempt to proceed | D26: Negative | E26: Medium | F26: 1. Leave 'ZIP Code / Area Code' field empty 2. Click 'Save and Proceed' | G26: ZIP Code / Area Code: (empty) | H26: Inline validation error shown: 'ZIP Code / Area Code is required'; user cannot proceed | J26: Not Executed
A27: TC_FF_BIZ_ZIP_03 | B27: Business Details - Business Info | C27: Enter value with invalid format/characters in 'ZIP Code / Area Code' | D27: Negative | E27: Medium | F27: 1. Enter a value that does not match the expected format for 'ZIP Code / Area Code' (e.g., AB!!) 2. Attempt to proceed | G27: ZIP Code / Area Code: AB!! | H27: Validation error shown indicating the expected format for 'ZIP Code / Area Code'; user cannot proceed with invalid input | J27: Not Executed | K27: Assumed — confirm exact validation rule/format with BA/Dev (not fully visible in recording)
A28: TC_FF_BIZ_ZIP_04 | B28: Business Details - Business Info | C28: Enter duplicate/already-used value in 'ZIP Code / Area Code' (if uniqueness applies) | D28: Negative | E28: Low | F28: 1. Enter a value for 'ZIP Code / Area Code' that is already registered/used elsewhere in the system 2. Attempt to proceed | G28: ZIP Code / Area Code: duplicate value | H28: Validation error shown if uniqueness is enforced for this field; otherwise value is accepted normally | J28: Not Executed | K28: Assumed — confirm exact validation rule/format with BA/Dev (not fully visible in recording)
A29: TC_FF_BIZ_COUNTRY_01 | B29: Business Details - Business Info | C29: Select a valid option in 'Country' dropdown | D29: Positive | E29: Medium | F29: 1. Click the 'Country' dropdown 2. Select a valid option 3. Proceed / Save | G29: Country: United Arab Emirates | H29: Selected value is accepted and retained; no validation error is shown | J29: Not Executed
A30: TC_FF_BIZ_COUNTRY_02 | B30: Business Details - Business Info | C30: Leave 'Country' dropdown unselected and attempt to proceed | D30: Negative | E30: Medium | F30: 1. Leave 'Country' at its default/placeholder state 2. Click 'Save and Proceed' | G30: Country: (unselected) | H30: Inline validation error shown: 'Country is required'; user cannot proceed | J30: Not Executed
A31: TC_FF_BIZ_COUNTRY_03 | B31: Business Details - Business Info | C31: Verify 'Country' dropdown options are complete and correctly labeled | D31: Positive | E31: Low | F31: 1. Click the 'Country' dropdown 2. Review the full list of available options | G31: Country: full option list | H31: All expected options are present, correctly spelled, and in a logical order (e.g., alphabetical) | J31: Not Executed | K31: Assumed — confirm exact validation rule/format with BA/Dev (not fully visible in recording)
A32: TC_FF_BIZ_MOBILE_01 | B32: Business Details - Business Info | C32: Enter a valid mobile number with country code in 'Mobile Number' | D32: Positive | E32: Medium | F32: 1. Select the correct country code 2. Enter a valid mobile number 3. Proceed / Save | G32: Mobile Number: +971 551234567 | H32: Value is accepted; no validation error is shown | J32: Not Executed
A33: TC_FF_BIZ_MOBILE_02 | B33: Business Details - Business Info | C33: Leave 'Mobile Number' empty and attempt to proceed | D33: Negative | E33: Medium | F33: 1. Leave 'Mobile Number' empty 2. Click 'Save and Proceed' | G33: Mobile Number: (empty) | H33: Inline validation error shown: 'Mobile Number is required'; user cannot proceed | J33: Not Executed
A34: TC_FF_BIZ_MOBILE_03 | B34: Business Details - Business Info | C34: Enter an invalid/incomplete number in 'Mobile Number' | D34: Negative | E34: Medium | F34: 1. Enter a number that is too short, too long, or contains letters 2. Attempt to proceed | G34: Mobile Number: 123 or 37845abc4 | H34: Validation error shown for the mobile number field; user cannot proceed | J34: Not Executed
A35: TC_FF_BIZ_VAT_01 | B35: Business Details - Business Info | C35: Enter valid alphanumeric value in 'VAT Registration Number' | D35: Positive | E35: Medium | F35: 1. Navigate to the step containing 'VAT Registration Number' 2. Enter a valid value matching the expected format 3. Proceed / Save | G35: VAT Registration Number: ANJ9838948932 | H35: Value is accepted; no validation error is shown for 'VAT Registration Number' | J35: Not Executed
A36: TC_FF_BIZ_VAT_02 | B36: Business Details - Business Info | C36: Leave 'VAT Registration Number' empty and attempt to proceed | D36: Negative | E36: Medium | F36: 1. Leave 'VAT Registration Number' field empty 2. Click 'Save and Proceed' | G36: VAT Registration Number: (empty) | H36: Inline validation error shown: 'VAT Registration Number is required'; user cannot proceed | J36: Not Executed
A37: TC_FF_BIZ_VAT_03 | B37: Business Details - Business Info | C37: Enter value with invalid format/characters in 'VAT Registration Number' | D37: Negative | E37: Medium | F37: 1. Enter a value that does not match the expected format for 'VAT Registration Number' (e.g., VAT##123) 2. Attempt to proceed | G37: VAT Registration Number: VAT##123 | H37: Validation error shown indicating the expected format for 'VAT Registration Number'; user cannot proceed with invalid input | J37: Not Executed | K37: Assumed — confirm exact validation rule/format with BA/Dev (not fully visible in recording)
A38: TC_FF_BIZ_VAT_04 | B38: Business Details - Business Info | C38: Enter duplicate/already-used value in 'VAT Registration Number' (if uniqueness applies) | D38: Negative | E38: Low | F38: 1. Enter a value for 'VAT Registration Number' that is already registered/used elsewhere in the system 2. Attempt to proceed | G38: VAT Registration Number: duplicate value | H38: Validation error shown if uniqueness is enforced for this field; otherwise value is accepted normally | J38: Not Executed | K38: Assumed — confirm exact validation rule/format with BA/Dev (not fully visible in recording)
A39: TC_FF_BIZ_WEB_01 | B39: Business Details - Business Info | C39: Enter a valid URL in 'Website Address' | D39: Positive | E39: Medium | F39: 1. Navigate to the step containing 'Website Address' 2. Enter a valid website URL 3. Proceed / Save | G39: Website Address: www.anjaliforwarders.com | H39: Value is accepted; no validation error is shown | J39: Not Executed
A40: TC_FF_BIZ_WEB_02 | B40: Business Details - Business Info | C40: Leave 'Website Address' empty and attempt to proceed | D40: Negative | E40: Medium | F40: 1. Leave 'Website Address' empty 2. Click 'Save and Proceed' | G40: Website Address: (empty) | H40: Inline validation error shown: 'Website Address is required'; user cannot proceed | J40: Not Executed
A41: TC_FF_BIZ_WEB_03 | B41: Business Details - Business Info | C41: Enter an invalid URL format in 'Website Address' | D41: Negative | E41: Medium | F41: 1. Enter a malformed URL (e.g., 'wwfreightco', 'htp://site') 2. Attempt to proceed | G41: Website Address: wwfreightco | H41: Validation error shown: 'Enter a valid website address'; user cannot proceed | J41: Not Executed
A42: TC_FF_BIZ_ESTAB_01 | B42: Business Details - Business Info | C42: Select a valid option in 'Establishment Type' dropdown | D42: Positive | E42: Medium | F42: 1. Click the 'Establishment Type' dropdown 2. Select a valid option 3. Proceed / Save | G42: Establishment Type: Private Limited Company | H42: Selected value is accepted and retained; no validation error is shown | J42: Not Executed
A43: TC_FF_BIZ_ESTAB_02 | B43: Business Details - Business Info | C43: Leave 'Establishment Type' dropdown unselected and attempt to proceed | D43: Negative | E43: Medium | F43: 1. Leave 'Establishment Type' at its default/placeholder state 2. Click 'Save and Proceed' | G43: Establishment Type: (unselected) | H43: Inline validation error shown: 'Establishment Type is required'; user cannot proceed | J43: Not Executed
A44: TC_FF_BIZ_ESTAB_03 | B44: Business Details - Business Info | C44: Verify 'Establishment Type' dropdown options are complete and correctly labeled | D44: Positive | E44: Low | F44: 1. Click the 'Establishment Type' dropdown 2. Review the full list of available options | G44: Establishment Type: full option list | H44: All expected options are present, correctly spelled, and in a logical order (e.g., alphabetical) | J44: Not Executed | K44: Assumed — confirm exact validation rule/format with BA/Dev (not fully visible in recording)
A45: TC_FF_BIZ_YEARS_01 | B45: Business Details - Business Info | C45: Enter a valid positive number in 'Years in Business' | D45: Positive | E45: Medium | F45: 1. Navigate to the step containing 'Years in Business' 2. Enter a valid positive numeric value 3. Proceed / Save | G45: Years in Business: 6 | H45: Value is accepted; no validation error is shown for 'Years in Business' | J45: Not Executed
A46: TC_FF_BIZ_YEARS_02 | B46: Business Details - Business Info | C46: Leave 'Years in Business' empty and attempt to proceed | D46: Negative | E46: Medium | F46: 1. Leave 'Years in Business' field empty 2. Click 'Save and Proceed' | G46: Years in Business: (empty) | H46: Inline validation error shown: 'Years in Business is required'; user cannot proceed | J46: Not Executed
A47: TC_FF_BIZ_YEARS_03 | B47: Business Details - Business Info | C47: Enter a negative or zero value in 'Years in Business' | D47: Negative | E47: Medium | F47: 1. Enter '0' or a negative number in 'Years in Business' 2. Attempt to proceed | G47: Years in Business: -5 or 0 | H47: Validation error shown indicating the value must be greater than zero; user cannot proceed | J47: Not Executed | K47: Assumed — confirm exact validation rule/format with BA/Dev (not fully visible in recording)
A48: TC_FF_BIZ_YEARS_04 | B48: Business Details - Business Info | C48: Enter non-numeric characters in 'Years in Business' | D48: Negative | E48: Medium | F48: 1. Enter letters/special characters in 'Years in Business' (e.g., 'abc', '12@3') 2. Attempt to proceed | G48: Years in Business: abc | H48: Field rejects non-numeric input; validation error shown or characters are not accepted at all | J48: Not Executed
A49: TC_FF_BIZ_NATURE_01 | B49: Business Details - Business Info | C49: Enter valid value in 'Nature of Business' field | D49: Positive | E49: Medium | F49: 1. Navigate to the step containing 'Nature of Business' 2. Enter a valid value 3. Proceed / Save | G49: Nature of Business: Freight Forwarding / Logistics Services | H49: Value is accepted; no validation error is shown for 'Nature of Business' | J49: Not Executed
A50: TC_FF_BIZ_NATURE_02 | B50: Business Details - Business Info | C50: Leave 'Nature of Business' empty and attempt to proceed | D50: Negative | E50: Medium | F50: 1. Leave 'Nature of Business' field empty 2. Click 'Save and Proceed' | G50: Nature of Business: (empty) | H50: Inline validation error shown: 'Nature of Business is required'; user cannot proceed to the next step | J50: Not Executed
A51: TC_FF_BIZ_NATURE_03 | B51: Business Details - Business Info | C51: Enter script/special-character injection in 'Nature of Business' | D51: Negative | E51: Medium | F51: 1. Enter a script/SQL injection payload in 'Nature of Business' 2. Attempt to proceed | G51: Nature of Business: <script>alert(1)</script> | H51: Input is sanitized/rejected as invalid; no script executes; no unhandled server error is exposed | J51: Not Executed
A52: TC_FF_BIZ_NATURE_04 | B52: Business Details - Business Info | C52: Enter value exceeding maximum length in 'Nature of Business' | D52: Negative | E52: Low | F52: 1. Enter an excessively long value (e.g., 300+ characters) in 'Nature of Business' 2. Attempt to proceed | G52: Nature of Business: 300+ character string | H52: Field enforces a sensible maximum length; validation error shown or input blocked beyond the limit | J52: Not Executed | K52: Assumed — confirm exact validation rule/format with BA/Dev (not fully visible in recording)
A53: TC_FF_BIZ_ANNUAL_01 | B53: Business Details - Business Info | C53: Enter a valid amount with currency selected for 'Annual Projected Volume' | D53: Positive | E53: Medium | F53: 1. Select a currency in the 'Annual Projected Volume' currency dropdown 2. Enter a valid positive amount 3. Proceed / Save | G53: Annual Projected Volume: AED 50,000 | H53: Value and currency are accepted; no validation error is shown | J53: Not Executed
A54: TC_FF_BIZ_ANNUAL_02 | B54: Business Details - Business Info | C54: Leave 'Annual Projected Volume' amount empty and attempt to proceed | D54: Negative | E54: Medium | F54: 1. Leave the 'Annual Projected Volume' amount field empty 2. Click 'Save and Proceed' | G54: Annual Projected Volume: (empty) | H54: Inline validation error shown: 'Annual Projected Volume is required'; user cannot proceed | J54: Not Executed
A55: TC_FF_BIZ_ANNUAL_03 | B55: Business Details - Business Info | C55: Enter a negative or zero amount in 'Annual Projected Volume' | D55: Negative | E55: Medium | F55: 1. Enter '0' or a negative number as the 'Annual Projected Volume' amount 2. Attempt to proceed | G55: Annual Projected Volume: -1000 or 0 | H55: Validation error shown indicating the amount must be greater than zero; user cannot proceed | J55: Not Executed | K55: Assumed — confirm exact validation rule/format with BA/Dev (not fully visible in recording)
A56: TC_FF_BIZ_ANNUAL_04 | B56: Business Details - Business Info | C56: Leave currency dropdown for 'Annual Projected Volume' unselected (if no default) | D56: Negative | E56: Low | F56: 1. Leave the currency dropdown for 'Annual Projected Volume' at a blank/placeholder state (if possible) 2. Enter a valid amount 3. Attempt to proceed | G56: Annual Projected Volume: amount entered, currency unselected | H56: Validation error shown requiring a currency selection; user cannot proceed without one | J56: Not Executed | K56: Assumed — confirm exact validation rule/format with BA/Dev (not fully visible in recording)
A57: TC_FF_BIZ_ANNUAL_05 | B57: Business Details - Business Info | C57: Cross-field consistency check for 'Annual Projected Volume' against related volume/value fields | D57: Negative | E57: Low | F57: 1. Enter a value for 'Annual Projected Volume' that is logically inconsistent with a related field (e.g., 'Highest Single Transaction Value' lower than 'Average Transaction Value') 2. Attempt to proceed | G57: Annual Projected Volume: inconsistent value relative to related field | H57: System either flags the inconsistency with a warning/error or accepts it if no cross-field validation is implemented — confirm intended behaviour | J57: Not Executed | K57: Assumed — confirm exact validation rule/format with BA/Dev (not fully visible in recording)
A58: TC_FF_BIZ_MONTHVOL_01 | B58: Business Details - Business Info | C58: Enter a valid amount with currency selected for 'Expected Monthly Transaction Volume' | D58: Positive | E58: Medium | F58: 1. Select a currency in the 'Expected Monthly Transaction Volume' currency dropdown 2. Enter a valid positive amount 3. Proceed / Save | G58: Expected Monthly Transaction Volume: AED 50,000 | H58: Value and currency are accepted; no validation error is shown | J58: Not Executed
A59: TC_FF_BIZ_MONTHVOL_02 | B59: Business Details - Business Info | C59: Leave 'Expected Monthly Transaction Volume' amount empty and attempt to proceed | D59: Negative | E59: Medium | F59: 1. Leave the 'Expected Monthly Transaction Volume' amount field empty 2. Click 'Save and Proceed' | G59: Expected Monthly Transaction Volume: (empty) | H59: Inline validation error shown: 'Expected Monthly Transaction Volume is required'; user cannot proceed | J59: Not Executed
A60: TC_FF_BIZ_MONTHVOL_03 | B60: Business Details - Business Info | C60: Enter a negative or zero amount in 'Expected Monthly Transaction Volume' | D60: Negative | E60: Medium | F60: 1. Enter '0' or a negative number as the 'Expected Monthly Transaction Volume' amount 2. Attempt to proceed | G60: Expected Monthly Transaction Volume: -1000 or 0 | H60: Validation error shown indicating the amount must be greater than zero; user cannot proceed | J60: Not Executed | K60: Assumed — confirm exact validation rule/format with BA/Dev (not fully visible in recording)
A61: TC_FF_BIZ_MONTHVOL_04 | B61: Business Details - Business Info | C61: Leave currency dropdown for 'Expected Monthly Transaction Volume' unselected (if no default) | D61: Negative | E61: Low | F61: 1. Leave the currency dropdown for 'Expected Monthly Transaction Volume' at a blank/placeholder state (if possible) 2. Enter a valid amount 3. Attempt to proceed | G61: Expected Monthly Transaction Volume: amount entered, currency unselected | H61: Validation error shown requiring a currency selection; user cannot proceed without one | J61: Not Executed | K61: Assumed — confirm exact validation rule/format with BA/Dev (not fully visible in recording)
A62: TC_FF_BIZ_MONTHVOL_05 | B62: Business Details - Business Info | C62: Cross-field consistency check for 'Expected Monthly Transaction Volume' against related volume/value fields | D62: Negative | E62: Low | F62: 1. Enter a value for 'Expected Monthly Transaction Volume' that is logically inconsistent with a related field (e.g., 'Highest Single Transaction Value' lower than 'Average Transaction Value') 2. Attempt to proceed | G62: Expected Monthly Transaction Volume: inconsistent value relative to related field | H62: System either flags the inconsistency with a warning/error or accepts it if no cross-field validation is implemented — confirm intended behaviour | J62: Not Executed | K62: Assumed — confirm exact validation rule/format with BA/Dev (not fully visible in recording)
A63: TC_FF_BIZ_AVGVAL_01 | B63: Business Details - Business Info | C63: Enter a valid amount with currency selected for 'Average Transaction Value' | D63: Positive | E63: Medium | F63: 1. Select a currency in the 'Average Transaction Value' currency dropdown 2. Enter a valid positive amount 3. Proceed / Save | G63: Average Transaction Value: AED 50,000 | H63: Value and currency are accepted; no validation error is shown | J63: Not Executed
A64: TC_FF_BIZ_AVGVAL_02 | B64: Business Details - Business Info | C64: Leave 'Average Transaction Value' amount empty and attempt to proceed | D64: Negative | E64: Medium | F64: 1. Leave the 'Average Transaction Value' amount field empty 2. Click 'Save and Proceed' | G64: Average Transaction Value: (empty) | H64: Inline validation error shown: 'Average Transaction Value is required'; user cannot proceed | J64: Not Executed
A65: TC_FF_BIZ_AVGVAL_03 | B65: Business Details - Business Info | C65: Enter a negative or zero amount in 'Average Transaction Value' | D65: Negative | E65: Medium | F65: 1. Enter '0' or a negative number as the 'Average Transaction Value' amount 2. Attempt to proceed | G65: Average Transaction Value: -1000 or 0 | H65: Validation error shown indicating the amount must be greater than zero; user cannot proceed | J65: Not Executed | K65: Assumed — confirm exact validation rule/format with BA/Dev (not fully visible in recording)
A66: TC_FF_BIZ_AVGVAL_04 | B66: Business Details - Business Info | C66: Leave currency dropdown for 'Average Transaction Value' unselected (if no default) | D66: Negative | E66: Low | F66: 1. Leave the currency dropdown for 'Average Transaction Value' at a blank/placeholder state (if possible) 2. Enter a valid amount 3. Attempt to proceed | G66: Average Transaction Value: amount entered, currency unselected | H66: Validation error shown requiring a currency selection; user cannot proceed without one | J66: Not Executed | K66: Assumed — confirm exact validation rule/format with BA/Dev (not fully visible in recording)
A67: TC_FF_BIZ_AVGVAL_05 | B67: Business Details - Business Info | C67: Cross-field consistency check for 'Average Transaction Value' against related volume/value fields | D67: Negative | E67: Low | F67: 1. Enter a value for 'Average Transaction Value' that is logically inconsistent with a related field (e.g., 'Highest Single Transaction Value' lower than 'Average Transaction Value') 2. Attempt to proceed | G67: Average Transaction Value: inconsistent value relative to related field | H67: System either flags the inconsistency with a warning/error or accepts it if no cross-field validation is implemented — confirm intended behaviour | J67: Not Executed | K67: Assumed — confirm exact validation rule/format with BA/Dev (not fully visible in recording)
A68: TC_FF_BIZ_MAXDAILY_01 | B68: Business Details - Business Info | C68: Enter a valid amount with currency selected for 'Maximum Daily Volume' | D68: Positive | E68: Medium | F68: 1. Select a currency in the 'Maximum Daily Volume' currency dropdown 2. Enter a valid positive amount 3. Proceed / Save | G68: Maximum Daily Volume: AED 50,000 | H68: Value and currency are accepted; no validation error is shown | J68: Not Executed
